Workbook

Sheet LCL+LOCAL - IMPORT (2)
A1: LCL + LOCAL
A2: No | B2: INVOICE No | C2: AWB,B/L No | D2: DATE | E2: KGS | F2: KGS OF BL | G2: CBM | H2: FREIGHT AIR | I2: FREIGHT SEA | J2: TRUCKING FEE | K2: SERVICE FEE | L2: CFS | M2: CIC | N2: THC | O2: D/O | P2: HANDLING | Q2: STORAGE | R2: CSHT | S2: INCURRED | T2: VAT PASS THROUGH | U2: CLEARING EXPENSE | V2: TOTAL | W2: PORT | X2: No | Y2: INVOICE No | Z2: DATE | AA2: FREIGHT AIR PER P/L | AB2: FREIGHT SEA PER P/L | AC2: TRUCKING FEE | AD2: SERVICE FEE | AE2: CFS | AF2: CIC | AG2: THC | AH2: D/O | AI2: HANDLING | AJ2: STORAGE | AK2: CSHT | AL2: INCURRED | AM2: VAT PASS THROUGH | AN2: CLEARING EXPENSE PER P/L | AO2: TOTAL | AP2: PORT | AR2: Biển số xe | AS2: Nơi đi - Nơi đến
A3: PS254498 | B3: IE20250716073 | C3: SJS5071963 | D3: 45861 | E3: 49 | F3: 49 | J3: =+IF(F3<=50,1060000, IF(F3<=200, 1210000, IF(F3<=500, 1230000, IF(F3<=1000, 1440000, IF(F3<=2000, 1990000, IF(F3>2000, 1990000+(F3-2000)*1464)))))) -> 1060000 | K3: 990000 | Q3: 162000 | T3: =SUM(J3:S3)*0.08 -> 176960 | U3: =SUM(J3:T3) -> 2388960 | V3: =U3 -> 2388960 | W3: TCS | X3: =A3 -> PS254498 | Y3: =B3 -> IE20250716073 | Z3: =D3 -> 45861 | AA3: =E3/F3*H3 -> 0 | AB3: =(E3/F3)*I3 -> 0 | AC3: =(E3/F3)*J3 -> 1060000 | AD3: =(E3/F3)*K3 -> 990000 | AE3: =(E3/F3)*L3 -> 0 | AF3: =(E3/F3)*M3 -> 0 | AG3: =(E3/F3)*N3 -> 0 | AH3: =(E3/F3)*O3 -> 0 | AI3: =(E3/F3)*P3 -> 0 | AJ3: =(E3/F3)*Q3 -> 162000 | AK3: =(E3/F3)*R3 -> 0 | AL3: =(E3/F3)*S3 -> 0 | AM3: =SUM(AC3:AL3)*0.08 -> 176960 | AN3: =SUM(AC3:AM3) -> 2388960 | AO3: =AN3 -> 2388960 | AP3: =W3 -> TCS | AQ3: AIR | AR3: 50H93043 | AS3: Từ Kho TCS, Hồ Chí Minh đến Bàu Xéo, Hồ Chí Minh | AT3: ADC
A4: PS254506 | B4: 0884325264 | C4: JWE4151001 | D4: 45861 | E4: 155 | F4: 155 | J4: =+IF(F4<=50,1060000, IF(F4<=200, 1210000, IF(F4<=500, 1230000, IF(F4<=1000, 1440000, IF(F4<=2000, 1990000, IF(F4>2000, 1990000+(F4-2000)*1464)))))) -> 1210000 | K4: =990000+70000 -> 1060000 | P4: 731987 | Q4: 220968 | T4: =SUM(J4:S4)*0.08 -> 257836.4 | U4: =SUM(J4:T4) -> 3480791.4 | V4: =U4 -> 3480791.4 | W4: TCS | X4: =A4 -> PS254506 | Y4: =B4 -> 0884325264 | Z4: =D4 -> 45861 | AA4: =E4/F4*H4 -> 0 | AB4: =(E4/F4)*I4 -> 0 | AC4: =(E4/F4)*J4 -> 1210000 | AD4: =(E4/F4)*K4 -> 1060000 | AE4: =(E4/F4)*L4 -> 0 | AF4: =(E4/F4)*M4 -> 0 | AG4: =(E4/F4)*N4 -> 0 | AH4: =(E4/F4)*O4 -> 0 | AI4: =(E4/F4)*P4 -> 731987 | AJ4: =(E4/F4)*Q4 -> 220968 | AK4: =(E4/F4)*R4 -> 0 | AL4: =(E4/F4)*S4 -> 0 | AM4: =SUM(AC4:AL4)*0.08 -> 257836.4 | AN4: =SUM(AC4:AM4) -> 3480791.4 | AO4: =AN4 -> 3480791.4 | AP4: =W4 -> TCS | AQ4: AIR | AR4: 50H93043 | AS4: Từ Kho TCS, Hồ Chí Minh đến Bàu Xéo, Hồ Chí Minh | AT4: ADC
A5: PS254506 | D5: 45861 | F5: 155 | J5: =+IF(F5<=50,1060000, IF(F5<=200, 1210000, IF(F5<=500, 1230000, IF(F5<=1000, 1440000, IF(F5<=2000, 1990000, IF(F5>2000, 1990000+(F5-2000)*1464)))))) -> 1210000 | K5: =990000+70000 -> 1060000 | P5: 731987 | Q5: 220968 | T5: =SUM(J5:S5)*0.08 -> 257836.4 | U5: =SUM(J5:T5) -> 3480791.4 | V5: =U5 -> 3480791.4 | W5: TCS | X5: =A5 -> PS254506 | Y5: =B5 -> 0 | Z5: =D5 -> 45861 | AA5: =E5/F5*H5 -> 0 | AB5: =(E5/F5)*I5 -> 0 | AC5: =(E5/F5)*J5 -> 0 | AD5: =(E5/F5)*K5 -> 0 | AE5: =(E5/F5)*L5 -> 0 | AF5: =(E5/F5)*M5 -> 0 | AG5: =(E5/F5)*N5 -> 0 | AH5: =(E5/F5)*O5 -> 0 | AI5: =(E5/F5)*P5 -> 0 | AJ5: =(E5/F5)*Q5 -> 0 | AK5: =(E5/F5)*R5 -> 0 | AL5: =(E5/F5)*S5 -> 0 | AM5: =SUM(AC5:AL5)*0.08 -> 0 | AN5: =SUM(AC5:AM5) -> 0 | AO5: =AN5 -> 0 | AP5: =W5 -> TCS | AQ5: AIR | AR5: 50H93043 | AS5: Từ Kho TCS, Hồ Chí Minh đến Bàu Xéo, Hồ Chí Minh | AT5: ADC
A6: PS254395 | B6: IE20250710103 | C6: XMNSGN25070195 | D6: 45861 | E6: 87.56 | F6: 87.56 | G6: 0.45 | J6: =+IF(F3=0, _xleta.T, IF(F3<=1000, 1260000, IF(F3<=2000, 1430000, IF(F3<=3000, 2120000, IF(F3<=4500, 2230000, ff))))) -> 1260000 | K6: 990000 | L6: 710910 | O6: 995274 | R6: 1314 | S6: =+IF(F6<=2000, 30000, IF(F6<5000, 66000, ff)) -> 30000 | T6: =SUM(J6:S6)*0.08 -> 318999.84 | U6: =SUM(J6:T6) -> 4306497.8 | V6: =U6 -> 4306497.8 | W6: CÁT LÁI | X6: =A6 -> PS254395 | Y6: =B6 -> IE20250710103 | Z6: =D6 -> 45861 | AA6: =E6/F6*H6 -> 0 | AB6: =(E6/F6)*I6 -> 0 | AC6: =(E6/F6)*J6 -> 1260000 | AD6: =(E6/F6)*K6 -> 990000 | AE6: =(E6/F6)*L6 -> 710910 | AF6: =(E6/F6)*M6 -> 0 | AG6: =(E6/F6)*N6 -> 0 | AH6: =(E6/F6)*O6 -> 995274 | AI6: =(E6/F6)*P6 -> 0 | AJ6: =(E6/F6)*Q6 -> 0 | AK6: =(E6/F6)*R6 -> 1314 | AL6: =(E6/F6)*S6 -> 30000 | AM6: =SUM(AC6:AL6)*0.08 -> 318999.84 | AN6: =SUM(AC6:AM6) -> 4306497.8 | AO6: =AN6 -> 4306497.8 | AP6: =W6 -> CÁT LÁI | AQ6: LCL | AR6: 50H66757 | AS6: Từ Cảng CÁT LÁI đến BÀU XÉO, Đồng Nai | AT6: ADC
A7: PS254381 | B7: T250713Y1 | C7: SPOE2507063 | D7: 45861 | E7: 179.94 | F7: 179.94 | G7: 1.1 | J7: =+IF(F4=0, _xleta.T, IF(F4<=1000, 1260000, IF(F4<=2000, 1430000, IF(F4<=3000, 2120000, IF(F4<=4500, 2230000, ff))))) -> 1260000 | K7: 990000 | L7: 969681 | O7: 1137456 | R7: 2699 | S7: =+IF(F7<=2000, 30000, IF(F7<5000, 66000, ff)) -> 30000 | T7: =SUM(J7:S7)*0.08 -> 351186.88 | U7: =SUM(J7:T7) -> 4741022.9 | V7: =U7 -> 4741022.9 | W7: CÁT LÁI | X7: =A7 -> PS254381 | Y7: =B7 -> T250713Y1 | Z7: =D7 -> 45861 | AA7: =E7/F7*H7 -> 0 | AB7: =(E7/F7)*I7 -> 0 | AC7: =(E7/F7)*J7 -> 1260000 | AD7: =(E7/F7)*K7 -> 990000 | AE7: =(E7/F7)*L7 -> 969681 | AF7: =(E7/F7)*M7 -> 0 | AG7: =(E7/F7)*N7 -> 0 | AH7: =(E7/F7)*O7 -> 1137456 | AI7: =(E7/F7)*P7 -> 0 | AJ7: =(E7/F7)*Q7 -> 0 | AK7: =(E7/F7)*R7 -> 2699 | AL7: =(E7/F7)*S7 -> 30000 | AM7: =SUM(AC7:AL7)*0.08 -> 351186.88 | AN7: =SUM(AC7:AM7) -> 4741022.9 | AO7: =AN7 -> 4741022.9 | AP7: =W7 -> CÁT LÁI | AQ7: LCL | AR7: 50H69181 | AS7: Từ Cảng CÁT LÁI đến BÀU XÉO, Đồng Nai | AT7: ADC
A8: PS254208 | B8: T250710Y1 | C8: SPOE2507049 | D8: 45861 | E8: 220 | F8: 220 | G8: 1.46 | J8: =+IF(F5=0, _xleta.T, IF(F5<=1000, 1260000, IF(F5<=2000, 1430000, IF(F5<=3000, 2120000, IF(F5<=4500, 2230000, ff))))) -> 1260000 | K8: 990000 | L8: 1287520 | O8: 1137888 | R8: 3300 | S8: =+IF(F8<=2000, 30000, IF(F8<5000, 66000, ff)) -> 30000 | T8: =SUM(J8:S8)*0.08 -> 376696.64 | U8: =SUM(J8:T8) -> 5085404.6 | V8: =U8 -> 5085404.6 | W8: CÁT LÁI | X8: =A8 -> PS254208 | Y8: =B8 -> T250710Y1 | Z8: =D8 -> 45861 | AA8: =E8/F8*H8 -> 0 | AB8: =(E8/F8)*I8 -> 0 | AC8: =(E8/F8)*J8 -> 1260000 | AD8: =(E8/F8)*K8 -> 990000 | AE8: =(E8/F8)*L8 -> 1287520 | AF8: =(E8/F8)*M8 -> 0 | AG8: =(E8/F8)*N8 -> 0 | AH8: =(E8/F8)*O8 -> 1137888 | AI8: =(E8/F8)*P8 -> 0 | AJ8: =(E8/F8)*Q8 -> 0 | AK8: =(E8/F8)*R8 -> 3300 | AL8: =(E8/F8)*S8 -> 30000 | AM8: =SUM(AC8:AL8)*0.08 -> 376696.64 | AN8: =SUM(AC8:AM8) -> 5085404.6 | AO8: =AN8 -> 5085404.6 | AP8: =W8 -> CÁT LÁI | AQ8: LCL | AR8: 50H69350 | AS8: Từ Cảng CÁT LÁI đến BÀU XÉO, Đồng Nai | AT8: ADC
A9: PS254496 | B9: INV25070795 | C9: SZVLE2500639 | D9: 45861 | E9: 36 | F9: 36 | G9: 0.12 | J9: =+IF(F6=0, _xleta.T, IF(F6<=1000, 1260000, IF(F6<=2000, 1430000, IF(F6<=3000, 2120000, IF(F6<=4500, 2230000, ff))))) -> 1260000 | K9: 990000 | L9: 512050 | M9: 142236 | N9: 199130 | O9: 853416 | P9: 711180 | R9: 540 | S9: =+IF(F9<=2000, 30000, IF(F9<5000, 66000, ff)) -> 30000 | T9: =SUM(J9:S9)*0.08 -> 375884.16 | U9: =SUM(J9:T9) -> 5074436.2 | V9: =U9 -> 5074436.2 | W9: CÁT LÁI | X9: =A9 -> PS254496 | Y9: =B9 -> INV25070795 | Z9: =D9 -> 45861 | AA9: =E9/F9*H9 -> 0 | AB9: =(E9/F9)*I9 -> 0 | AC9: =(E9/F9)*J9 -> 1260000 | AD9: =(E9/F9)*K9 -> 990000 | AE9: =(E9/F9)*L9 -> 512050 | AF9: =(E9/F9)*M9 -> 142236 | AG9: =(E9/F9)*N9 -> 199130 | AH9: =(E9/F9)*O9 -> 853416 | AI9: =(E9/F9)*P9 -> 711180 | AJ9: =(E9/F9)*Q9 -> 0 | AK9: =(E9/F9)*R9 -> 540 | AL9: =(E9/F9)*S9 -> 30000 | AM9: =SUM(AC9:AL9)*0.08 -> 375884.16 | AN9: =SUM(AC9:AM9) -> 5074436.2 | AO9: =AN9 -> 5074436.2 | AP9: =W9 -> CÁT LÁI | AQ9: LCL | AR9: 50H69181 | AS9: Từ Cảng CÁT LÁI đến BÀU XÉO, Đồng Nai | AT9: ADC
A10: PS254504 | B10: PS254504 | C10: MLHCM2507016 | D10: 45861 | E10: 5298.5 | F10: 5298.5 | G10: 14.402 | J10: =2230000*2 -> 4460000 | K10: 990000 | Q10: 254487 | R10: 79478 | S10: =66000*2 -> 132000 | T10: =SUM(J10:S10)*0.08 -> 473277.2 | U10: =SUM(J10:T10) -> 6389242.2 | V10: =U10 -> 6389242.2 | W10: CÁT LÁI | X10: =A10 -> PS254504 | Y10: =B10 -> PS254504 | Z10: =D10 -> 45861 | AA10: =E10/F10*H10 -> 0 | AB10: =(E10/F10)*I10 -> 0 | AC10: =(E10/F10)*J10 -> 4460000 | AD10: =(E10/F10)*K10 -> 990000 | AE10: =(E10/F10)*L10 -> 0 | AF10: =(E10/F10)*M10 -> 0 | AG10: =(E10/F10)*N10 -> 0 | AH10: =(E10/F10)*O10 -> 0 | AI10: =(E10/F10)*P10 -> 0 | AJ10: =(E10/F10)*Q10 -> 254487 | AK10: =(E10/F10)*R10 -> 79478 | AL10: =(E10/F10)*S10 -> 132000 | AM10: =SUM(AC10:AL10)*0.08 -> 473277.2 | AN10: =SUM(AC10:AM10) -> 6389242.2 | AO10: =AN10 -> 6389242.2 | AP10: =W10 -> CÁT LÁI | AQ10: LCL | AR10: 50H66757 | AS10: Từ Cảng CÁT LÁI đến BÀU XÉO, Đồng Nai | AT10: ADC
A11: PS254491 | B11: 250710JHJ05A | C11: SPOE2507058 | D11: 45861 | E11: 850 | F11: 850 | G11: 1.62 | J11: =+IF(F8=0, _xleta.T, IF(F8<=1000, 1260000, IF(F8<=2000, 1430000, IF(F8<=3000, 2120000, IF(F8<=4500, 2230000, ff))))) -> 1260000 | K11: 990000 | R11: 12750 | S11: =+IF(F11<=2000, 30000, IF(F11<5000, 66000, ff)) -> 30000 | T11: =SUM(J11:S11)*0.08 -> 183420 | U11: =SUM(J11:T11) -> 2476170 | V11: =U11 -> 2476170 | W11: CÁT LÁI | X11: =A11 -> PS254491 | Y11: =B11 -> 250710JHJ05A | Z11: =D11 -> 45861 | AA11: =E11/F11*H11 -> 0 | AB11: =(E11/F11)*I11 -> 0 | AC11: =(E11/F11)*J11 -> 1260000 | AD11: =(E11/F11)*K11 -> 990000 | AE11: =(E11/F11)*L11 -> 0 | AF11: =(E11/F11)*M11 -> 0 | AG11: =(E11/F11)*N11 -> 0 | AH11: =(E11/F11)*O11 -> 0 | AI11: =(E11/F11)*P11 -> 0 | AJ11: =(E11/F11)*Q11 -> 0 | AK11: =(E11/F11)*R11 -> 12750 | AL11: =(E11/F11)*S11 -> 30000 | AM11: =SUM(AC11:AL11)*0.08 -> 183420 | AN11: =SUM(AC11:AM11) -> 2476170 | AO11: =AN11 -> 2476170 | AP11: =W11 -> CÁT LÁI | AQ11: LCL | AR11: 50H69350 | AS11: Từ Cảng CÁT LÁI đến BÀU XÉO, Đồng Nai | AT11: ADC
A12: PS254536 | B12: PC250722VY | C12: JWE4151014 | D12: 45862 | E12: 27 | F12: 27 | J12: =+IF(F12<=50,1060000, IF(F12<=200, 1210000, IF(F12<=500, 1230000, IF(F12<=1000, 1440000, IF(F12<=2000, 1990000, IF(F12>2000, 1990000+(F12-2000)*1464)))))) -> 1060000 | K12: 990000 | P12: 603299 | Q12: 162000 | T12: =SUM(J12:S12)*0.08 -> 225223.92 | U12: =SUM(J12:T12) -> 3040522.9 | V12: =U12 -> 3040522.9 | W12: TCS | X12: =A12 -> PS254536 | Y12: =B12 -> PC250722VY | Z12: =D12 -> 45862 | AA12: =E12/F12*H12 -> 0 | AB12: =(E12/F12)*I12 -> 0 | AC12: =(E12/F12)*J12 -> 1060000 | AD12: =(E12/F12)*K12 -> 990000 | AE12: =(E12/F12)*L12 -> 0 | AF12: =(E12/F12)*M12 -> 0 | AG12: =(E12/F12)*N12 -> 0 | AH12: =(E12/F12)*O12 -> 0 | AI12: =(E12/F12)*P12 -> 603299 | AJ12: =(E12/F12)*Q12 -> 162000 | AK12: =(E12/F12)*R12 -> 0 | AL12: =(E12/F12)*S12 -> 0 | AM12: =SUM(AC12:AL12)*0.08 -> 225223.92 | AN12: =SUM(AC12:AM12) -> 3040522.9 | AO12: =AN12 -> 3040522.9 | AP12: =W12 -> TCS | AQ12: AIR | AR12: 50H69350 | AS12: Từ Kho TCS, Hồ Chí Minh đến Bàu Xéo, Hồ Chí Minh | AT12: ADC
A13: PS254508 | B13: PC250721VY | C13: JWE4151003 | D13: 45862 | E13: 39 | F13: 39 | J13: =+IF(F13<=50,1060000, IF(F13<=200, 1210000, IF(F13<=500, 1230000, IF(F13<=1000, 1440000, IF(F13<=2000, 1990000, IF(F13>2000, 1990000+(F13-2000)*1464)))))) -> 1060000 | K13: 990000 | P13: 624029 | Q13: 162000 | T13: =SUM(J13:S13)*0.08 -> 226882.32 | U13: =SUM(J13:T13) -> 3062911.3 | V13: =U13 -> 3062911.3 | W13: TCS | X13: =A13 -> PS254508 | Y13: =B13 -> PC250721VY | Z13: =D13 -> 45862 | AA13: =E13/F13*H13 -> 0 | AB13: =(E13/F13)*I13 -> 0 | AC13: =(E13/F13)*J13 -> 1060000 | AD13: =(E13/F13)*K13 -> 990000 | AE13: =(E13/F13)*L13 -> 0 | AF13: =(E13/F13)*M13 -> 0 | AG13: =(E13/F13)*N13 -> 0 | AH13: =(E13/F13)*O13 -> 0 | AI13: =(E13/F13)*P13 -> 624029 | AJ13: =(E13/F13)*Q13 -> 162000 | AK13: =(E13/F13)*R13 -> 0 | AL13: =(E13/F13)*S13 -> 0 | AM13: =SUM(AC13:AL13)*0.08 -> 226882.32 | AN13: =SUM(AC13:AM13) -> 3062911.3 | AO13: =AN13 -> 3062911.3 | AP13: =W13 -> TCS | AQ13: AIR | AR13: 50H69350 | AS13: Từ Kho TCS, Hồ Chí Minh đến Bàu Xéo, Hồ Chí Minh | AT13: ADC
A14: PS254507 | B14: G820250721 VY (B) | C14: JWE4150998 | D14: 45862 | E14: 2 | F14: 2 | J14: =+IF(F14<=50,1060000, IF(F14<=200, 1210000, IF(F14<=500, 1230000, IF(F14<=1000, 1440000, IF(F14<=2000, 1990000, IF(F14>2000, 1990000+(F14-2000)*1464)))))) -> 1060000 | K14: 990000 | P14: 564718 | Q14: 162000 | T14: =SUM(J14:S14)*0.08 -> 222137.44 | U14: =SUM(J14:T14) -> 2998855.4 | V14: =U14 -> 2998855.4 | W14: TCS | X14: =A14 -> PS254507 | Y14: =B14 -> G820250721 VY (B) | Z14: =D14 -> 45862 | AA14: =E14/F14*H14 -> 0 | AB14: =(E14/F14)*I14 -> 0 | AC14: =(E14/F14)*J14 -> 1060000 | AD14: =(E14/F14)*K14 -> 990000 | AE14: =(E14/F14)*L14 -> 0 | AF14: =(E14/F14)*M14 -> 0 | AG14: =(E14/F14)*N14 -> 0 | AH14: =(E14/F14)*O14 -> 0 | AI14: =(E14/F14)*P14 -> 564718 | AJ14: =(E14/F14)*Q14 -> 162000 | AK14: =(E14/F14)*R14 -> 0 | AL14: =(E14/F14)*S14 -> 0 | AM14: =SUM(AC14:AL14)*0.08 -> 222137.44 | AN14: =SUM(AC14:AM14) -> 2998855.4 | AO14: =AN14 -> 2998855.4 | AP14: =W14 -> TCS | AQ14: AIR | AR14: 50H69350 | AS14: Từ Kho TCS, Hồ Chí Minh đến Bàu Xéo, Hồ Chí Minh | AT14: ADC
A15: PS254537 | B15: G820250722 VY (B) | C15: JWE4151008 | D15: 45862 | E15: 5 | F15: 5 | J15: =+IF(F15<=50,1060000, IF(F15<=200, 1210000, IF(F15<=500, 1230000, IF(F15<=1000, 1440000, IF(F15<=2000, 1990000, IF(F15>2000, 1990000+(F15-2000)*1464)))))) -> 1060000 | K15: 990000 | P15: 569017 | Q15: 162000 | T15: =SUM(J15:S15)*0.08 -> 222481.36 | U15: =SUM(J15:T15) -> 3003498.4 | V15: =U15 -> 3003498.4 | W15: TCS | X15: =A15 -> PS254537 | Y15: =B15 -> G820250722 VY (B) | Z15: =D15 -> 45862 | AA15: =E15/F15*H15 -> 0 | AB15: =(E15/F15)*I15 -> 0 | AC15: =(E15/F15)*J15 -> 1060000 | AD15: =(E15/F15)*K15 -> 990000 | AE15: =(E15/F15)*L15 -> 0 | AF15: =(E15/F15)*M15 -> 0 | AG15: =(E15/F15)*N15 -> 0 | AH15: =(E15/F15)*O15 -> 0 | AI15: =(E15/F15)*P15 -> 569017 | AJ15: =(E15/F15)*Q15 -> 162000 | AK15: =(E15/F15)*R15 -> 0 | AL15: =(E15/F15)*S15 -> 0 | AM15: =SUM(AC15:AL15)*0.08 -> 222481.36 | AN15: =SUM(AC15:AM15) -> 3003498.4 | AO15: =AN15 -> 3003498.4 | AP15: =W15 -> TCS | AQ15: AIR | AR15: 50H69350 | AS15: Từ Kho TCS, Hồ Chí Minh đến Bàu Xéo, Hồ Chí Minh | AT15: ADC
A16: PS254500 | B16: 0001300107928 | C16: 6518707451 | D16: 45862 | E16: 22 | F16: 22 | K16: 600000 | T16: =SUM(J16:S16)*0.08 -> 48000 | U16: =SUM(J16:T16) -> 648000 | V16: =U16 -> 648000 | W16: DHL | X16: =A16 -> PS254500 | Y16: =B16 -> 0001300107928 | Z16: =D16 -> 45862 | AA16: =E16/F16*H16 -> 0 | AB16: =(E16/F16)*I16 -> 0 | AC16: =(E16/F16)*J16 -> 0 | AD16: =(E16/F16)*K16 -> 600000 | AE16: =(E16/F16)*L16 -> 0 | AF16: =(E16/F16)*M16 -> 0 | AG16: =(E16/F16)*N16 -> 0 | AH16: =(E16/F16)*O16 -> 0 | AI16: =(E16/F16)*P16 -> 0 | AJ16: =(E16/F16)*Q16 -> 0 | AK16: =(E16/F16)*R16 -> 0 | AL16: =(E16/F16)*S16 -> 0 | AM16: =SUM(AC16:AL16)*0.08 -> 48000 | AN16: =SUM(AC16:AM16) -> 648000 | AO16: =AN16 -> 648000 | AP16: =W16 -> DHL | AQ16: EXP
A17: PS254448 | B17: OHTY250894 | C17: 7671539315 | D17: 45862 | E17: 4.9 | F17: 4.9 | K17: 600000 | T17: =SUM(J17:S17)*0.08 -> 48000 | U17: =SUM(J17:T17) -> 648000 | V17: =U17 -> 648000 | W17: DHL | X17: =A17 -> PS254448 | Y17: =B17 -> OHTY250894 | Z17: =D17 -> 45862 | AA17: =E17/F17*H17 -> 0 | AB17: =(E17/F17)*I17 -> 0 | AC17: =(E17/F17)*J17 -> 0 | AD17: =(E17/F17)*K17 -> 600000 | AE17: =(E17/F17)*L17 -> 0 | AF17: =(E17/F17)*M17 -> 0 | AG17: =(E17/F17)*N17 -> 0 | AH17: =(E17/F17)*O17 -> 0 | AI17: =(E17/F17)*P17 -> 0 | AJ17: =(E17/F17)*Q17 -> 0 | AK17: =(E17/F17)*R17 -> 0 | AL17: =(E17/F17)*S17 -> 0 | AM17: =SUM(AC17:AL17)*0.08 -> 48000 | AN17: =SUM(AC17:AM17) -> 648000 | AO17: =AN17 -> 648000 | AP17: =W17 -> DHL | AQ17: EXP
A18: PS254449 | B18: ZSSCIPSO2507003 | C18: 7671846114 | D18: 45862 | E18: 8.5 | F18: 8.5 | K18: 600000 | T18: =SUM(J18:S18)*0.08 -> 48000 | U18: =SUM(J18:T18) -> 648000 | V18: =U18 -> 648000 | W18: DHL | X18: =A18 -> PS254449 | Y18: =B18 -> ZSSCIPSO2507003 | Z18: =D18 -> 45862 | AA18: =E18/F18*H18 -> 0 | AB18: =(E18/F18)*I18 -> 0 | AC18: =(E18/F18)*J18 -> 0 | AD18: =(E18/F18)*K18 -> 600000 | AE18: =(E18/F18)*L18 -> 0 | AF18: =(E18/F18)*M18 -> 0 | AG18: =(E18/F18)*N18 -> 0 | AH18: =(E18/F18)*O18 -> 0 | AI18: =(E18/F18)*P18 -> 0 | AJ18: =(E18/F18)*Q18 -> 0 | AK18: =(E18/F18)*R18 -> 0 | AL18: =(E18/F18)*S18 -> 0 | AM18: =SUM(AC18:AL18)*0.08 -> 48000 | AN18: =SUM(AC18:AM18) -> 648000 | AO18: =AN18 -> 648000 | AP18: =W18 -> DHL | AQ18: EXP
A19: PS254505 | B19: INV25070863 | C19: 7671273341 | D19: 45862 | E19: 6 | F19: 6 | K19: 600000 | T19: =SUM(J19:S19)*0.08 -> 48000 | U19: =SUM(J19:T19) -> 648000 | V19: =U19 -> 648000 | W19: DHL | X19: =A19 -> PS254505 | Y19: =B19 -> INV25070863 | Z19: =D19 -> 45862 | AA19: =E19/F19*H19 -> 0 | AB19: =(E19/F19)*I19 -> 0 | AC19: =(E19/F19)*J19 -> 0 | AD19: =(E19/F19)*K19 -> 600000 | AE19: =(E19/F19)*L19 -> 0 | AF19: =(E19/F19)*M19 -> 0 | AG19: =(E19/F19)*N19 -> 0 | AH19: =(E19/F19)*O19 -> 0 | AI19: =(E19/F19)*P19 -> 0 | AJ19: =(E19/F19)*Q19 -> 0 | AK19: =(E19/F19)*R19 -> 0 | AL19: =(E19/F19)*S19 -> 0 | AM19: =SUM(AC19:AL19)*0.08 -> 48000 | AN19: =SUM(AC19:AM19) -> 648000 | AO19: =AN19 -> 648000 | AP19: =W19 -> DHL | AQ19: EXP
A20: PS254503 | B20: DJL250718027 | C20: 7671997583 | D20: 45862 | E20: 16.7 | F20: 16.7 | J20: =+IF(F20<=50,1060000, IF(F20<=200, 1210000, IF(F20<=500, 1230000, IF(F20<=1000, 1440000, IF(F20<=2000, 1990000, IF(F20>2000, 1990000+(F20-2000)*1464)))))) -> 1060000 | K20: =600000+70000 -> 670000 | T20: =SUM(J20:S20)*0.08 -> 138400 | U20: =SUM(J20:T20) -> 1868400 | V20: =U20 -> 1868400 | W20: DHL | X20: =A20 -> PS254503 | Y20: =B20 -> DJL250718027 | Z20: =D20 -> 45862 | AA20: =E20/F20*H20 -> 0 | AB20: =(E20/F20)*I20 -> 0 | AC20: =(E20/F20)*J20 -> 1060000 | AD20: =(E20/F20)*K20 -> 670000 | AE20: =(E20/F20)*L20 -> 0 | AF20: =(E20/F20)*M20 -> 0 | AG20: =(E20/F20)*N20 -> 0 | AH20: =(E20/F20)*O20 -> 0 | AI20: =(E20/F20)*P20 -> 0 | AJ20: =(E20/F20)*Q20 -> 0 | AK20: =(E20/F20)*R20 -> 0 | AL20: =(E20/F20)*S20 -> 0 | AM20: =SUM(AC20:AL20)*0.08 -> 138400 | AN20: =SUM(AC20:AM20) -> 1868400 | AO20: =AN20 -> 1868400 | AP20: =W20 -> DHL | AQ20: EXP
A21: PS254503 | D21: 45862 | F21: 16.7 | J21: =+IF(F21<=50,1060000, IF(F21<=200, 1210000, IF(F21<=500, 1230000, IF(F21<=1000, 1440000, IF(F21<=2000, 1990000, IF(F21>2000, 1990000+(F21-2000)*1464)))))) -> 1060000 | K21: =600000+70000 -> 670000 | T21: =SUM(J21:S21)*0.08 -> 138400 | U21: =SUM(J21:T21) -> 1868400 | V21: =U21 -> 1868400 | W21: DHL | X21: =A21 -> PS254503 | Y21: =B21 -> 0 | Z21: =D21 -> 45862 | AA21: =E21/F21*H21 -> 0 | AB21: =(E21/F21)*I21 -> 0 | AC21: =(E21/F21)*J21 -> 0 | AD21: =(E21/F21)*K21 -> 0 | AE21: =(E21/F21)*L21 -> 0 | AF21: =(E21/F21)*M21 -> 0 | AG21: =(E21/F21)*N21 -> 0 | AH21: =(E21/F21)*O21 -> 0 | AI21: =(E21/F21)*P21 -> 0 | AJ21: =(E21/F21)*Q21 -> 0 | AK21: =(E21/F21)*R21 -> 0 | AL21: =(E21/F21)*S21 -> 0 | AM21: =SUM(AC21:AL21)*0.08 -> 0 | AN21: =SUM(AC21:AM21) -> 0 | AO21: =AN21 -> 0 | AP21: =W21 -> DHL | AQ21: EXP
A22: PS254527 | B22: EX25070108 | C22: 6037520510 | D22: 45862 | E22: 4.1 | F22: 4.1 | K22: 600000 | T22: =SUM(J22:S22)*0.08 -> 48000 | U22: =SUM(J22:T22) -> 648000 | V22: =U22 -> 648000 | W22: DHL | X22: =A22 -> PS254527 | Y22: =B22 -> EX25070108 | Z22: =D22 -> 45862 | AA22: =E22/F22*H22 -> 0 | AB22: =(E22/F22)*I22 -> 0 | AC22: =(E22/F22)*J22 -> 0 | AD22: =(E22/F22)*K22 -> 600000 | AE22: =(E22/F22)*L22 -> 0 | AF22: =(E22/F22)*M22 -> 0 | AG22: =(E22/F22)*N22 -> 0 | AH22: =(E22/F22)*O22 -> 0 | AI22: =(E22/F22)*P22 -> 0 | AJ22: =(E22/F22)*Q22 -> 0 | AK22: =(E22/F22)*R22 -> 0 | AL22: =(E22/F22)*S22 -> 0 | AM22: =SUM(AC22:AL22)*0.08 -> 48000 | AN22: =SUM(AC22:AM22) -> 648000 | AO22: =AN22 -> 648000 | AP22: =W22 -> DHL | AQ22: EXP
A23: PS254526 | B23: HF250719 | C23: 7672071606 | D23: 45862 | E23: 19.2 | F23: 19.2 | J23: =+IF(F23<=50,1060000, IF(F23<=200, 1210000, IF(F23<=500, 1230000, IF(F23<=1000, 1440000, IF(F23<=2000, 1990000, IF(F23>2000, 1990000+(F23-2000)*1464)))))) -> 1060000 | K23: =600000+70000 -> 670000 | T23: =SUM(J23:S23)*0.08 -> 138400 | U23: =SUM(J23:T23) -> 1868400 | V23: =U23 -> 1868400 | W23: DHL | X23: =A23 -> PS254526 | Y23: =B23 -> HF250719 | Z23: =D23 -> 45862 | AA23: =E23/F23*H23 -> 0 | AB23: =(E23/F23)*I23 -> 0 | AC23: =(E23/F23)*J23 -> 1060000 | AD23: =(E23/F23)*K23 -> 670000 | AE23: =(E23/F23)*L23 -> 0 | AF23: =(E23/F23)*M23 -> 0 | AG23: =(E23/F23)*N23 -> 0 | AH23: =(E23/F23)*O23 -> 0 | AI23: =(E23/F23)*P23 -> 0 | AJ23: =(E23/F23)*Q23 -> 0 | AK23: =(E23/F23)*R23 -> 0 | AL23: =(E23/F23)*S23 -> 0 | AM23: =SUM(AC23:AL23)*0.08 -> 138400 | AN23: =SUM(AC23:AM23) -> 1868400 | AO23: =AN23 -> 1868400 | AP23: =W23 -> DHL | AQ23: EXP
A24: PS254526 | D24: 45862 | F24: 19.2 | J24: =+IF(F24<=50,1060000, IF(F24<=200, 1210000, IF(F24<=500, 1230000, IF(F24<=1000, 1440000, IF(F24<=2000, 1990000, IF(F24>2000, 1990000+(F24-2000)*1464)))))) -> 1060000 | K24: =600000+70000 -> 670000 | T24: =SUM(J24:S24)*0.08 -> 138400 | U24: =SUM(J24:T24) -> 1868400 | V24: =U24 -> 1868400 | W24: DHL | X24: =A24 -> PS254526 | Y24: =B24 -> 0 | Z24: =D24 -> 45862 | AA24: =E24/F24*H24 -> 0 | AB24: =(E24/F24)*I24 -> 0 | AC24: =(E24/F24)*J24 -> 0 | AD24: =(E24/F24)*K24 -> 0 | AE24: =(E24/F24)*L24 -> 0 | AF24: =(E24/F24)*M24 -> 0 | AG24: =(E24/F24)*N24 -> 0 | AH24: =(E24/F24)*O24 -> 0 | AI24: =(E24/F24)*P24 -> 0 | AJ24: =(E24/F24)*Q24 -> 0 | AK24: =(E24/F24)*R24 -> 0 | AL24: =(E24/F24)*S24 -> 0 | AM24: =SUM(AC24:AL24)*0.08 -> 0 | AN24: =SUM(AC24:AM24) -> 0 | AO24: =AN24 -> 0 | AP24: =W24 -> DHL | AQ24: EXP
A25: PS254543 | B25: SO42008 | C25: 7672182372 | D25: 45862 | E25: 9.3 | F25: 9.3 | K25: 600000 | T25: =SUM(J25:S25)*0.08 -> 48000 | U25: =SUM(J25:T25) -> 648000 | V25: =U25 -> 648000 | W25: DHL | X25: =A25 -> PS254543 | Y25: =B25 -> SO42008 | Z25: =D25 -> 45862 | AA25: =E25/F25*H25 -> 0 | AB25: =(E25/F25)*I25 -> 0 | AC25: =(E25/F25)*J25 -> 0 | AD25: =(E25/F25)*K25 -> 600000 | AE25: =(E25/F25)*L25 -> 0 | AF25: =(E25/F25)*M25 -> 0 | AG25: =(E25/F25)*N25 -> 0 | AH25: =(E25/F25)*O25 -> 0 | AI25: =(E25/F25)*P25 -> 0 | AJ25: =(E25/F25)*Q25 -> 0 | AK25: =(E25/F25)*R25 -> 0 | AL25: =(E25/F25)*S25 -> 0 | AM25: =SUM(AC25:AL25)*0.08 -> 48000 | AN25: =SUM(AC25:AM25) -> 648000 | AO25: =AN25 -> 648000 | AP25: =W25 -> DHL | AQ25: EXP
A26: PS254545 | B26: 4794463 | C26: 6674889852 | D26: 45862 | E26: 55 | F26: 55 | K26: 600000 | T26: =SUM(J26:S26)*0.08 -> 48000 | U26: =SUM(J26:T26) -> 648000 | V26: =U26 -> 648000 | W26: DHL | X26: =A26 -> PS254545 | Y26: =B26 -> 4794463 | Z26: =D26 -> 45862 | AA26: =E26/F26*H26 -> 0 | AB26: =(E26/F26)*I26 -> 0 | AC26: =(E26/F26)*J26 -> 0 | AD26: =(E26/F26)*K26 -> 600000 | AE26: =(E26/F26)*L26 -> 0 | AF26: =(E26/F26)*M26 -> 0 | AG26: =(E26/F26)*N26 -> 0 | AH26: =(E26/F26)*O26 -> 0 | AI26: =(E26/F26)*P26 -> 0 | AJ26: =(E26/F26)*Q26 -> 0 | AK26: =(E26/F26)*R26 -> 0 | AL26: =(E26/F26)*S26 -> 0 | AM26: =SUM(AC26:AL26)*0.08 -> 48000 | AN26: =SUM(AC26:AM26) -> 648000 | AO26: =AN26 -> 648000 | AP26: =W26 -> DHL | AQ26: EXP
A27: PS254493 | B27: INJF250709 | C27: DGPE25070055 | D27: 45862 | E27: 1410 | F27: 1410 | G27: 4.76 | J27: =+IF(F24=0, _xleta.T, IF(F24<=1000, 1260000, IF(F24<=2000, 1430000, IF(F24<=3000, 2120000, IF(F24<=4500, 2230000, ff))))) -> 1260000 | K27: 990000 | L27: 17596444 | M27: 3383931.6 | N27: 5414291.6 | O27: 1421820 | R27: 21150 | S27: =+IF(F27<=2000, 30000, IF(F27<5000, 66000, ff)) -> 30000 | T27: =SUM(J27:S27)*0.08 -> 2409411 | U27: =SUM(J27:T27) -> 32527048 | V27: =U27 -> 32527048 | W27: CÁT LÁI | X27: =A27 -> PS254493 | Y27: =B27 -> INJF250709 | Z27: =D27 -> 45862 | AA27: =E27/F27*H27 -> 0 | AB27: =(E27/F27)*I27 -> 0 | AC27: =(E27/F27)*J27 -> 1260000 | AD27: =(E27/F27)*K27 -> 990000 | AE27: =(E27/F27)*L27 -> 17596444 | AF27: =(E27/F27)*M27 -> 3383931.6 | AG27: =(E27/F27)*N27 -> 5414291.6 | AH27: =(E27/F27)*O27 -> 1421820 | AI27: =(E27/F27)*P27 -> 0 | AJ27: =(E27/F27)*Q27 -> 0 | AK27: =(E27/F27)*R27 -> 21150 | AL27: =(E27/F27)*S27 -> 30000 | AM27: =SUM(AC27:AL27)*0.08 -> 2409411 | AN27: =SUM(AC27:AM27) -> 32527048 | AO27: =AN27 -> 32527048 | AP27: =W27 -> CÁT LÁI | AQ27: LCL | AR27: 50H93234 | AS27: Từ Cảng CÁT LÁI đến BÀU XÉO, Đồng Nai | AT27: ADC
A28: PS254492 | B28: 4780698 | C28: 112500034967156 | D28: 45862 | E28: 521.96 | F28: 521.96 | K28: 410000 | T28: =SUM(J28:S28)*0.08 -> 32800 | U28: =SUM(J28:T28) -> 442800 | V28: =U28 -> 442800 | W28: KNQ TBS | X28: =A28 -> PS254492 | Y28: =B28 -> 4780698 | Z28: =D28 -> 45862 | AA28: =E28/F28*H28 -> 0 | AB28: =(E28/F28)*I28 -> 0 | AC28: =(E28/F28)*J28 -> 0 | AD28: =(E28/F28)*K28 -> 410000 | AE28: =(E28/F28)*L28 -> 0 | AF28: =(E28/F28)*M28 -> 0 | AG28: =(E28/F28)*N28 -> 0 | AH28: =(E28/F28)*O28 -> 0 | AI28: =(E28/F28)*P28 -> 0 | AJ28: =(E28/F28)*Q28 -> 0 | AK28: =(E28/F28)*R28 -> 0 | AL28: =(E28/F28)*S28 -> 0 | AM28: =SUM(AC28:AL28)*0.08 -> 32800 | AN28: =SUM(AC28:AM28) -> 442800 | AO28: =AN28 -> 442800 | AP28: =W28 -> KNQ TBS | AQ28: LCL-KNQ
A29: PS254540 | B29: A25060676 | C29: 112500035315500 | D29: 45862 | E29: 4957.72 | F29: 4957.72 | K29: 410000 | T29: =SUM(J29:S29)*0.08 -> 32800 | U29: =SUM(J29:T29) -> 442800 | V29: =U29 -> 442800 | W29: KNQ CANG DN | X29: =A29 -> PS254540 | Y29: =B29 -> A25060676 | Z29: =D29 -> 45862 | AA29: =E29/F29*H29 -> 0 | AB29: =(E29/F29)*I29 -> 0 | AC29: =(E29/F29)*J29 -> 0 | AD29: =(E29/F29)*K29 -> 410000 | AE29: =(E29/F29)*L29 -> 0 | AF29: =(E29/F29)*M29 -> 0 | AG29: =(E29/F29)*N29 -> 0 | AH29: =(E29/F29)*O29 -> 0 | AI29: =(E29/F29)*P29 -> 0 | AJ29: =(E29/F29)*Q29 -> 0 | AK29: =(E29/F29)*R29 -> 0 | AL29: =(E29/F29)*S29 -> 0 | AM29: =SUM(AC29:AL29)*0.08 -> 32800 | AN29: =SUM(AC29:AM29) -> 442800 | AO29: =AN29 -> 442800 | AP29: =W29 -> KNQ CANG DN | AQ29: LCL-KNQ
A30: PS254566 | B30: 0884335886 | C30: JWE4151018 | D30: 45863 | E30: 76 | F30: 76 | J30: =+IF(F30<=50,1060000, IF(F30<=200, 1210000, IF(F30<=500, 1230000, IF(F30<=1000, 1440000, IF(F30<=2000, 1990000, IF(F30>2000, 1990000+(F30-2000)*1464)))))) -> 1210000 | K30: =990000+70000 -> 1060000 | P30: 617284 | Q30: 162000 | T30: =SUM(J30:S30)*0.08 -> 243942.72 | U30: =SUM(J30:T30) -> 3293226.7 | V30: =U30 -> 3293226.7 | W30: TCS | X30: =A30 -> PS254566 | Y30: =B30 -> 0884335886 | Z30: =D30 -> 45863 | AA30: =E30/F30*H30 -> 0 | AB30: =(E30/F30)*I30 -> 0 | AC30: =(E30/F30)*J30 -> 1210000 | AD30: =(E30/F30)*K30 -> 1060000 | AE30: =(E30/F30)*L30 -> 0 | AF30: =(E30/F30)*M30 -> 0 | AG30: =(E30/F30)*N30 -> 0 | AH30: =(E30/F30)*O30 -> 0 | AI30: =(E30/F30)*P30 -> 617284 | AJ30: =(E30/F30)*Q30 -> 162000 | AK30: =(E30/F30)*R30 -> 0 | AL30: =(E30/F30)*S30 -> 0 | AM30: =SUM(AC30:AL30)*0.08 -> 243942.72 | AN30: =SUM(AC30:AM30) -> 3293226.7 | AO30: =AN30 -> 3293226.7 | AP30: =W30 -> TCS | AQ30: AIR | AR30: 50H93043 | AS30: Từ Kho TCS, Hồ Chí Minh đến Bàu Xéo, Hồ Chí Minh | AT30: ADC
A31: PS254566 | D31: 45863 | F31: 76 | J31: =+IF(F31<=50,1060000, IF(F31<=200, 1210000, IF(F31<=500, 1230000, IF(F31<=1000, 1440000, IF(F31<=2000, 1990000, IF(F31>2000, 1990000+(F31-2000)*1464)))))) -> 1210000 | K31: =990000+70000 -> 1060000 | P31: 617284 | Q31: 162000 | T31: =SUM(J31:S31)*0.08 -> 243942.72 | U31: =SUM(J31:T31) -> 3293226.7 | V31: =U31 -> 3293226.7 | W31: TCS | X31: =A31 -> PS254566 | Y31: =B31 -> 0 | Z31: =D31 -> 45863 | AA31: =E31/F31*H31 -> 0 | AB31: =(E31/F31)*I31 -> 0 | AC31: =(E31/F31)*J31 -> 0 | AD31: =(E31/F31)*K31 -> 0 | AE31: =(E31/F31)*L31 -> 0 | AF31: =(E31/F31)*M31 -> 0 | AG31: =(E31/F31)*N31 -> 0 | AH31: =(E31/F31)*O31 -> 0 | AI31: =(E31/F31)*P31 -> 0 | AJ31: =(E31/F31)*Q31 -> 0 | AK31: =(E31/F31)*R31 -> 0 | AL31: =(E31/F31)*S31 -> 0 | AM31: =SUM(AC31:AL31)*0.08 -> 0 | AN31: =SUM(AC31:AM31) -> 0 | AO31: =AN31 -> 0 | AP31: =W31 -> TCS | AQ31: AIR | AR31: 50H93043 | AS31: Từ Kho TCS, Hồ Chí Minh đến Bàu Xéo, Hồ Chí Minh | AT31: ADC
A32: PS254565 | B32: PC250723VY | C32: JWE4151020 | D32: 45863 | E32: 6 | F32: 6 | J32: =+IF(F32<=50,1060000, IF(F32<=200, 1210000, IF(F32<=500, 1230000, IF(F32<=1000, 1440000, IF(F32<=2000, 1990000, IF(F32>2000, 1990000+(F32-2000)*1464)))))) -> 1060000 | K32: 990000 | P32: 570467 | Q32: 162000 | T32: =SUM(J32:S32)*0.08 -> 222597.36 | U32: =SUM(J32:T32) -> 3005064.4 | V32: =U32 -> 3005064.4 | W32: TCS | X32: =A32 -> PS254565 | Y32: =B32 -> PC250723VY | Z32: =D32 -> 45863 | AA32: =E32/F32*H32 -> 0 | AB32: =(E32/F32)*I32 -> 0 | AC32: =(E32/F32)*J32 -> 1060000 | AD32: =(E32/F32)*K32 -> 990000 | AE32: =(E32/F32)*L32 -> 0 | AF32: =(E32/F32)*M32 -> 0 | AG32: =(E32/F32)*N32 -> 0 | AH32: =(E32/F32)*O32 -> 0 | AI32: =(E32/F32)*P32 -> 570467 | AJ32: =(E32/F32)*Q32 -> 162000 | AK32: =(E32/F32)*R32 -> 0 | AL32: =(E32/F32)*S32 -> 0 | AM32: =SUM(AC32:AL32)*0.08 -> 222597.36 | AN32: =SUM(AC32:AM32) -> 3005064.4 | AO32: =AN32 -> 3005064.4 | AP32: =W32 -> TCS | AQ32: AIR | AR32: 50H93043 | AS32: Từ Kho TCS, Hồ Chí Minh đến Bàu Xéo, Hồ Chí Minh | AT32: ADC
A33: PS254564 | B33: G820250723 VY (B) | C33: JWE4151017 | D33: 45863 | E33: 3 | F33: 3 | J33: =+IF(F33<=50,1060000, IF(F33<=200, 1210000, IF(F33<=500, 1230000, IF(F33<=1000, 1440000, IF(F33<=2000, 1990000, IF(F33>2000, 1990000+(F33-2000)*1464)))))) -> 1060000 | K33: 990000 | P33: 566118 | Q33: 162000 | T33: =SUM(J33:S33)*0.08 -> 222249.44 | U33: =SUM(J33:T33) -> 3000367.4 | V33: =U33 -> 3000367.4 | W33: TCS | X33: =A33 -> PS254564 | Y33: =B33 -> G820250723 VY (B) | Z33: =D33 -> 45863 | AA33: =E33/F33*H33 -> 0 | AB33: =(E33/F33)*I33 -> 0 | AC33: =(E33/F33)*J33 -> 1060000 | AD33: =(E33/F33)*K33 -> 990000 | AE33: =(E33/F33)*L33 -> 0 | AF33: =(E33/F33)*M33 -> 0 | AG33: =(E33/F33)*N33 -> 0 | AH33: =(E33/F33)*O33 -> 0 | AI33: =(E33/F33)*P33 -> 566118 | AJ33: =(E33/F33)*Q33 -> 162000 | AK33: =(E33/F33)*R33 -> 0 | AL33: =(E33/F33)*S33 -> 0 | AM33: =SUM(AC33:AL33)*0.08 -> 222249.44 | AN33: =SUM(AC33:AM33) -> 3000367.4 | AO33: =AN33 -> 3000367.4 | AP33: =W33 -> TCS | AQ33: AIR | AR33: 50H93043 | AS33: Từ Kho TCS, Hồ Chí Minh đến Bàu Xéo, Hồ Chí Minh | AT33: ADC
A34: PS254520 | B34: D214530 | C34: GXSAG25070765 | D34: 45863 | E34: 1558 | F34: 1558 | G34: 6.1 | J34: =+IF(F31=0, _xleta.T, IF(F31<=1000, 1260000, IF(F31<=2000, 1430000, IF(F31<=3000, 2120000, IF(F31<=4500, 2230000, ff))))) -> 1260000 | K34: 990000 | L34: 1767559.4 | M34: 1767560.4 | N34: 1414048.3 | O34: 724410 | P34: 579528 | R34: 23370 | S34: =+IF(F34<=2000, 30000, IF(F34<5000, 66000, ff)) -> 30000 | T34: =SUM(J34:S34)*0.08 -> 684518.09 | U34: =SUM(J34:T34) -> 9240994.2 | V34: =U34 -> 9240994.2 | W34: CÁT LÁI | X34: =A34 -> PS254520 | Y34: =B34 -> D214530 | Z34: =D34 -> 45863 | AA34: =E34/F34*H34 -> 0 | AB34: =(E34/F34)*I34 -> 0 | AC34: =(E34/F34)*J34 -> 1260000 | AD34: =(E34/F34)*K34 -> 990000 | AE34: =(E34/F34)*L34 -> 1767559.4 | AF34: =(E34/F34)*M34 -> 1767560.4 | AG34: =(E34/F34)*N34 -> 1414048.3 | AH34: =(E34/F34)*O34 -> 724410 | AI34: =(E34/F34)*P34 -> 579528 | AJ34: =(E34/F34)*Q34 -> 0 | AK34: =(E34/F34)*R34 -> 23370 | AL34: =(E34/F34)*S34 -> 30000 | AM34: =SUM(AC34:AL34)*0.08 -> 684518.09 | AN34: =SUM(AC34:AM34) -> 9240994.2 | AO34: =AN34 -> 9240994.2 | AP34: =W34 -> CÁT LÁI | AQ34: LCL | AR34: 50H66757 | AS34: Từ Cảng CÁT LÁI đến BÀU XÉO, Đồng Nai | AT34: ADC
A35: PS254598 | B35: T250723Y2 | C35: SPX2507028 | D35: 45864 | E35: 41 | F35: 41 | J35: =+IF(F35<=50,1060000, IF(F35<=200, 1210000, IF(F35<=500, 1230000, IF(F35<=1000, 1440000, IF(F35<=2000, 1990000, IF(F35>2000, 1990000+(F35-2000)*1464)))))) -> 1060000 | K35: 990000 | Q35: 162000 | T35: =SUM(J35:S35)*0.08 -> 176960 | U35: =SUM(J35:T35) -> 2388960 | V35: =U35 -> 2388960 | W35: TCS | X35: =A35 -> PS254598 | Y35: =B35 -> T250723Y2 | Z35: =D35 -> 45864 | AA35: =E35/F35*H35 -> 0 | AB35: =(E35/F35)*I35 -> 0 | AC35: =(E35/F35)*J35 -> 1060000 | AD35: =(E35/F35)*K35 -> 990000 | AE35: =(E35/F35)*L35 -> 0 | AF35: =(E35/F35)*M35 -> 0 | AG35: =(E35/F35)*N35 -> 0 | AH35: =(E35/F35)*O35 -> 0 | AI35: =(E35/F35)*P35 -> 0 | AJ35: =(E35/F35)*Q35 -> 162000 | AK35: =(E35/F35)*R35 -> 0 | AL35: =(E35/F35)*S35 -> 0 | AM35: =SUM(AC35:AL35)*0.08 -> 176960 | AN35: =SUM(AC35:AM35) -> 2388960 | AO35: =AN35 -> 2388960 | AP35: =W35 -> TCS | AQ35: AIR | AR35: 50H69350 | AS35: Từ Kho TCS, Hồ Chí Minh đến Bàu Xéo, Hồ Chí Minh | AT35: ADC
A36: PS254591 | B36: PC250724VY | C36: JWE4151027 | D36: 45864 | E36: 22 | F36: 22 | J36: =+IF(F36<=50,1060000, IF(F36<=200, 1210000, IF(F36<=500, 1230000, IF(F36<=1000, 1440000, IF(F36<=2000, 1990000, IF(F36>2000, 1990000+(F36-2000)*1464)))))) -> 1060000 | K36: 990000 | P36: 592497 | Q36: 162000 | T36: =SUM(J36:S36)*0.08 -> 224359.76 | U36: =SUM(J36:T36) -> 3028856.8 | V36: =U36 -> 3028856.8 | W36: TCS | X36: =A36 -> PS254591 | Y36: =B36 -> PC250724VY | Z36: =D36 -> 45864 | AA36: =E36/F36*H36 -> 0 | AB36: =(E36/F36)*I36 -> 0 | AC36: =(E36/F36)*J36 -> 1060000 | AD36: =(E36/F36)*K36 -> 990000 | AE36: =(E36/F36)*L36 -> 0 | AF36: =(E36/F36)*M36 -> 0 | AG36: =(E36/F36)*N36 -> 0 | AH36: =(E36/F36)*O36 -> 0 | AI36: =(E36/F36)*P36 -> 592497 | AJ36: =(E36/F36)*Q36 -> 162000 | AK36: =(E36/F36)*R36 -> 0 | AL36: =(E36/F36)*S36 -> 0 | AM36: =SUM(AC36:AL36)*0.08 -> 224359.76 | AN36: =SUM(AC36:AM36) -> 3028856.8 | AO36: =AN36 -> 3028856.8 | AP36: =W36 -> TCS | AQ36: AIR | AR36: 50H69350 | AS36: Từ Kho TCS, Hồ Chí Minh đến Bàu Xéo, Hồ Chí Minh | AT36: ADC
A37: PS254592 | B37: G820250724VY (B) | C37: JWE4151029 | D37: 45864 | E37: 4 | F37: 4 | J37: =+IF(F37<=50,1060000, IF(F37<=200, 1210000, IF(F37<=500, 1230000, IF(F37<=1000, 1440000, IF(F37<=2000, 1990000, IF(F37>2000, 1990000+(F37-2000)*1464)))))) -> 1060000 | K37: 990000 | P37: 567170 | Q37: 162000 | T37: =SUM(J37:S37)*0.08 -> 222333.6 | U37: =SUM(J37:T37) -> 3001503.6 | V37: =U37 -> 3001503.6 | W37: TCS | X37: =A37 -> PS254592 | Y37: =B37 -> G820250724VY (B) | Z37: =D37 -> 45864 | AA37: =E37/F37*H37 -> 0 | AB37: =(E37/F37)*I37 -> 0 | AC37: =(E37/F37)*J37 -> 1060000 | AD37: =(E37/F37)*K37 -> 990000 | AE37: =(E37/F37)*L37 -> 0 | AF37: =(E37/F37)*M37 -> 0 | AG37: =(E37/F37)*N37 -> 0 | AH37: =(E37/F37)*O37 -> 0 | AI37: =(E37/F37)*P37 -> 567170 | AJ37: =(E37/F37)*Q37 -> 162000 | AK37: =(E37/F37)*R37 -> 0 | AL37: =(E37/F37)*S37 -> 0 | AM37: =SUM(AC37:AL37)*0.08 -> 222333.6 | AN37: =SUM(AC37:AM37) -> 3001503.6 | AO37: =AN37 -> 3001503.6 | AP37: =W37 -> TCS | AQ37: AIR | AR37: 50H69350 | AS37: Từ Kho TCS, Hồ Chí Minh đến Bàu Xéo, Hồ Chí Minh | AT37: ADC
A38: PS254544 | B38: DJL250721028 | C38: 7672150485 | E38: 0.2 | F38: 0.2 | K38: 600000 | T38: =SUM(J38:S38)*0.08 -> 48000 | U38: =SUM(J38:T38) -> 648000 | V38: =U38 -> 648000 | W38: DHL | X38: =A38 -> PS254544 | Y38: =B38 -> DJL250721028 | Z38: =D38 -> 0 | AA38: =E38/F38*H38 -> 0 | AB38: =(E38/F38)*I38 -> 0 | AC38: =(E38/F38)*J38 -> 0 | AD38: =(E38/F38)*K38 -> 600000 | AE38: =(E38/F38)*L38 -> 0 | AF38: =(E38/F38)*M38 -> 0 | AG38: =(E38/F38)*N38 -> 0 | AH38: =(E38/F38)*O38 -> 0 | AI38: =(E38/F38)*P38 -> 0 | AJ38: =(E38/F38)*Q38 -> 0 | AK38: =(E38/F38)*R38 -> 0 | AL38: =(E38/F38)*S38 -> 0 | AM38: =SUM(AC38:AL38)*0.08 -> 48000 | AN38: =SUM(AC38:AM38) -> 648000 | AO38: =AN38 -> 648000 | AP38: =W38 -> DHL | AQ38: EXP
A39: PS254556 | B39: 1045/2025 | C39: 5597048995 | E39: 27 | F39: 27 | K39: 600000 | T39: =SUM(J39:S39)*0.08 -> 48000 | U39: =SUM(J39:T39) -> 648000 | V39: =U39 -> 648000 | W39: DHL | X39: =A39 -> PS254556 | Y39: =B39 -> 1045/2025 | Z39: =D39 -> 0 | AA39: =E39/F39*H39 -> 0 | AB39: =(E39/F39)*I39 -> 0 | AC39: =(E39/F39)*J39 -> 0 | AD39: =(E39/F39)*K39 -> 600000 | AE39: =(E39/F39)*L39 -> 0 | AF39: =(E39/F39)*M39 -> 0 | AG39: =(E39/F39)*N39 -> 0 | AH39: =(E39/F39)*O39 -> 0 | AI39: =(E39/F39)*P39 -> 0 | AJ39: =(E39/F39)*Q39 -> 0 | AK39: =(E39/F39)*R39 -> 0 | AL39: =(E39/F39)*S39 -> 0 | AM39: =SUM(AC39:AL39)*0.08 -> 48000 | AN39: =SUM(AC39:AM39) -> 648000 | AO39: =AN39 -> 648000 | AP39: =W39 -> DHL | AQ39: EXP
A40: PS254569 | B40: INV25071002 | C40: 610971955290 | E40: 339.8 | F40: 339.8 | K40: 600000 | T40: =SUM(J40:S40)*0.08 -> 48000 | U40: =SUM(J40:T40) -> 648000 | V40: =U40 -> 648000 | W40: FEDEX | X40: =A40 -> PS254569 | Y40: =B40 -> INV25071002 | Z40: =D40 -> 0 | AA40: =E40/F40*H40 -> 0 | AB40: =(E40/F40)*I40 -> 0 | AC40: =(E40/F40)*J40 -> 0 | AD40: =(E40/F40)*K40 -> 600000 | AE40: =(E40/F40)*L40 -> 0 | AF40: =(E40/F40)*M40 -> 0 | AG40: =(E40/F40)*N40 -> 0 | AH40: =(E40/F40)*O40 -> 0 | AI40: =(E40/F40)*P40 -> 0 | AJ40: =(E40/F40)*Q40 -> 0 | AK40: =(E40/F40)*R40 -> 0 | AL40: =(E40/F40)*S40 -> 0 | AM40: =SUM(AC40:AL40)*0.08 -> 48000 | AN40: =SUM(AC40:AM40) -> 648000 | AO40: =AN40 -> 648000 | AP40: =W40 -> FEDEX | AQ40: EXP
A41: PS254570 | B41: 25072201 | C41: 7672394402 | E41: 2.1 | F41: 2.1 | K41: 600000 | T41: =SUM(J41:S41)*0.08 -> 48000 | U41: =SUM(J41:T41) -> 648000 | V41: =U41 -> 648000 | W41: DHL | X41: =A41 -> PS254570 | Y41: =B41 -> 25072201 | Z41: =D41 -> 0 | AA41: =E41/F41*H41 -> 0 | AB41: =(E41/F41)*I41 -> 0 | AC41: =(E41/F41)*J41 -> 0 | AD41: =(E41/F41)*K41 -> 600000 | AE41: =(E41/F41)*L41 -> 0 | AF41: =(E41/F41)*M41 -> 0 | AG41: =(E41/F41)*N41 -> 0 | AH41: =(E41/F41)*O41 -> 0 | AI41: =(E41/F41)*P41 -> 0 | AJ41: =(E41/F41)*Q41 -> 0 | AK41: =(E41/F41)*R41 -> 0 | AL41: =(E41/F41)*S41 -> 0 | AM41: =SUM(AC41:AL41)*0.08 -> 48000 | AN41: =SUM(AC41:AM41) -> 648000 | AO41: =AN41 -> 648000 | AP41: =W41 -> DHL | AQ41: EXP
A42: PS254568 | B42: 0001300108358 | C42: 3764914414 | E42: 3 | F42: 3 | K42: 600000 | T42: =SUM(J42:S42)*0.08 -> 48000 | U42: =SUM(J42:T42) -> 648000 | V42: =U42 -> 648000 | W42: DHL | X42: =A42 -> PS254568 | Y42: =B42 -> 0001300108358 | Z42: =D42 -> 0 | AA42: =E42/F42*H42 -> 0 | AB42: =(E42/F42)*I42 -> 0 | AC42: =(E42/F42)*J42 -> 0 | AD42: =(E42/F42)*K42 -> 600000 | AE42: =(E42/F42)*L42 -> 0 | AF42: =(E42/F42)*M42 -> 0 | AG42: =(E42/F42)*N42 -> 0 | AH42: =(E42/F42)*O42 -> 0 | AI42: =(E42/F42)*P42 -> 0 | AJ42: =(E42/F42)*Q42 -> 0 | AK42: =(E42/F42)*R42 -> 0 | AL42: =(E42/F42)*S42 -> 0 | AM42: =SUM(AC42:AL42)*0.08 -> 48000 | AN42: =SUM(AC42:AM42) -> 648000 | AO42: =AN42 -> 648000 | AP42: =W42 -> DHL | AQ42: EXP
A43: PS254581 | B43: INV25071003 | C43: 1164173275 | E43: 1.4 | F43: 1.4 | K43: 600000 | T43: =SUM(J43:S43)*0.08 -> 48000 | U43: =SUM(J43:T43) -> 648000 | V43: =U43 -> 648000 | W43: DHL | X43: =A43 -> PS254581 | Y43: =B43 -> INV25071003 | Z43: =D43 -> 0 | AA43: =E43/F43*H43 -> 0 | AB43: =(E43/F43)*I43 -> 0 | AC43: =(E43/F43)*J43 -> 0 | AD43: =(E43/F43)*K43 -> 600000 | AE43: =(E43/F43)*L43 -> 0 | AF43: =(E43/F43)*M43 -> 0 | AG43: =(E43/F43)*N43 -> 0 | AH43: =(E43/F43)*O43 -> 0 | AI43: =(E43/F43)*P43 -> 0 | AJ43: =(E43/F43)*Q43 -> 0 | AK43: =(E43/F43)*R43 -> 0 | AL43: =(E43/F43)*S43 -> 0 | AM43: =SUM(AC43:AL43)*0.08 -> 48000 | AN43: =SUM(AC43:AM43) -> 648000 | AO43: =AN43 -> 648000 | AP43: =W43 -> DHL | AQ43: EXP
A44: PS254582 | B44: INV25070978 | C44: 7672138574 | E44: 3 | F44: 3 | K44: 600000 | T44: =SUM(J44:S44)*0.08 -> 48000 | U44: =SUM(J44:T44) -> 648000 | V44: =U44 -> 648000 | W44: DHL | X44: =A44 -> PS254582 | Y44: =B44 -> INV25070978 | Z44: =D44 -> 0 | AA44: =E44/F44*H44 -> 0 | AB44: =(E44/F44)*I44 -> 0 | AC44: =(E44/F44)*J44 -> 0 | AD44: =(E44/F44)*K44 -> 600000 | AE44: =(E44/F44)*L44 -> 0 | AF44: =(E44/F44)*M44 -> 0 | AG44: =(E44/F44)*N44 -> 0 | AH44: =(E44/F44)*O44 -> 0 | AI44: =(E44/F44)*P44 -> 0 | AJ44: =(E44/F44)*Q44 -> 0 | AK44: =(E44/F44)*R44 -> 0 | AL44: =(E44/F44)*S44 -> 0 | AM44: =SUM(AC44:AL44)*0.08 -> 48000 | AN44: =SUM(AC44:AM44) -> 648000 | AO44: =AN44 -> 648000 | AP44: =W44 -> DHL | AQ44: EXP
A45: PS254583 | B45: INV25070997 | C45: 7672315556 | E45: 2 | F45: 2 | K45: 600000 | T45: =SUM(J45:S45)*0.08 -> 48000 | U45: =SUM(J45:T45) -> 648000 | V45: =U45 -> 648000 | W45: DHL | X45: =A45 -> PS254583 | Y45: =B45 -> INV25070997 | Z45: =D45 -> 0 | AA45: =E45/F45*H45 -> 0 | AB45: =(E45/F45)*I45 -> 0 | AC45: =(E45/F45)*J45 -> 0 | AD45: =(E45/F45)*K45 -> 600000 | AE45: =(E45/F45)*L45 -> 0 | AF45: =(E45/F45)*M45 -> 0 | AG45: =(E45/F45)*N45 -> 0 | AH45: =(E45/F45)*O45 -> 0 | AI45: =(E45/F45)*P45 -> 0 | AJ45: =(E45/F45)*Q45 -> 0 | AK45: =(E45/F45)*R45 -> 0 | AL45: =(E45/F45)*S45 -> 0 | AM45: =SUM(AC45:AL45)*0.08 -> 48000 | AN45: =SUM(AC45:AM45) -> 648000 | AO45: =AN45 -> 648000 | AP45: =W45 -> DHL | AQ45: EXP
A46: PS254563 | B46: SL2025071101 | C46: HTHC25072424 | D46: 45864 | E46: 1474.1 | F46: 1474.1 | G46: 5.5 | J46: =+IF(F43=0, _xleta.T, IF(F43<=1000, 1260000, IF(F43<=2000, 1430000, IF(F43<=3000, 2120000, IF(F43<=4500, 2230000, ff))))) -> 1260000 | K46: 990000 | L46: 20324304 | M46: 3908520 | N46: 6253632 | O46: 710640 | P46: 710640 | R46: 22112 | S46: =+IF(F46<=2000, 30000, IF(F46<5000, 66000, ff)) -> 30000 | T46: =SUM(J46:S46)*0.08 -> 2736787.8 | U46: =SUM(J46:T46) -> 36946636 | V46: =U46 -> 36946636 | W46: CÁT LÁI | X46: =A46 -> PS254563 | Y46: =B46 -> SL2025071101 | Z46: =D46 -> 45864 | AA46: =E46/F46*H46 -> 0 | AB46: =(E46/F46)*I46 -> 0 | AC46: =(E46/F46)*J46 -> 1260000 | AD46: =(E46/F46)*K46 -> 990000 | AE46: =(E46/F46)*L46 -> 20324304 | AF46: =(E46/F46)*M46 -> 3908520 | AG46: =(E46/F46)*N46 -> 6253632 | AH46: =(E46/F46)*O46 -> 710640 | AI46: =(E46/F46)*P46 -> 710640 | AJ46: =(E46/F46)*Q46 -> 0 | AK46: =(E46/F46)*R46 -> 22112 | AL46: =(E46/F46)*S46 -> 30000 | AM46: =SUM(AC46:AL46)*0.08 -> 2736787.8 | AN46: =SUM(AC46:AM46) -> 36946636 | AO46: =AN46 -> 36946636 | AP46: =W46 -> CÁT LÁI | AQ46: LCL | AR46: 50H69181 | AS46: Từ Cảng CÁT LÁI đến BÀU XÉO, Đồng Nai | AT46: ADC
A47: PS254485 | B47: 0884302206 | C47: TXGCLI2507T00025 | D47: 45864 | E47: 23.8 | F47: 23.8 | G47: 0.13 | J47: =+IF(F44=0, _xleta.T, IF(F44<=1000, 1260000, IF(F44<=2000, 1430000, IF(F44<=3000, 2120000, IF(F44<=4500, 2230000, ff))))) -> 1260000 | K47: 990000 | L47: 455155.2 | M47: 85341.6 | N47: 170683.2 | O47: 853416 | R47: 357 | S47: =+IF(F47<=2000, 30000, IF(F47<5000, 66000, ff)) -> 30000 | T47: =SUM(J47:S47)*0.08 -> 307596.24 | U47: =SUM(J47:T47) -> 4152549.2 | V47: =U47 -> 4152549.2 | W47: CÁT LÁI | X47: =A47 -> PS254485 | Y47: =B47 -> 0884302206 | Z47: =D47 -> 45864 | AA47: =E47/F47*H47 -> 0 | AB47: =(E47/F47)*I47 -> 0 | AC47: =(E47/F47)*J47 -> 1260000 | AD47: =(E47/F47)*K47 -> 990000 | AE47: =(E47/F47)*L47 -> 455155.2 | AF47: =(E47/F47)*M47 -> 85341.6 | AG47: =(E47/F47)*N47 -> 170683.2 | AH47: =(E47/F47)*O47 -> 853416 | AI47: =(E47/F47)*P47 -> 0 | AJ47: =(E47/F47)*Q47 -> 0 | AK47: =(E47/F47)*R47 -> 357 | AL47: =(E47/F47)*S47 -> 30000 | AM47: =SUM(AC47:AL47)*0.08 -> 307596.24 | AN47: =SUM(AC47:AM47) -> 4152549.2 | AO47: =AN47 -> 4152549.2 | AP47: =W47 -> CÁT LÁI | AQ47: LCL | AR47: 50H69181 | AS47: Từ Cảng CÁT LÁI đến BÀU XÉO, Đồng Nai | AT47: ADC
A48: PS254541 | B48: MAYAS25050710 | C48: HTHC25072457 | D48: 45864 | E48: 856.1 | F48: 856.1 | G48: 3.2 | J48: =+IF(F45=0, _xleta.T, IF(F45<=1000, 1260000, IF(F45<=2000, 1430000, IF(F45<=3000, 2120000, IF(F45<=4500, 2230000, ff))))) -> 1260000 | K48: 990000 | L48: 1637315 | M48: 454810 | N48: 636733 | O48: 852768 | P48: 710640 | R48: 12842 | S48: =+IF(F48<=2000, 30000, IF(F48<5000, 66000, ff)) -> 30000 | T48: =SUM(J48:S48)*0.08 -> 526808.64 | U48: =SUM(J48:T48) -> 7111916.6 | V48: =U48 -> 7111916.6 | W48: CÁT LÁI | X48: =A48 -> PS254541 | Y48: =B48 -> MAYAS25050710 | Z48: =D48 -> 45864 | AA48: =E48/F48*H48 -> 0 | AB48: =(E48/F48)*I48 -> 0 | AC48: =(E48/F48)*J48 -> 1260000 | AD48: =(E48/F48)*K48 -> 990000 | AE48: =(E48/F48)*L48 -> 1637315 | AF48: =(E48/F48)*M48 -> 454810 | AG48: =(E48/F48)*N48 -> 636733 | AH48: =(E48/F48)*O48 -> 852768 | AI48: =(E48/F48)*P48 -> 710640 | AJ48: =(E48/F48)*Q48 -> 0 | AK48: =(E48/F48)*R48 -> 12842 | AL48: =(E48/F48)*S48 -> 30000 | AM48: =SUM(AC48:AL48)*0.08 -> 526808.64 | AN48: =SUM(AC48:AM48) -> 7111916.6 | AO48: =AN48 -> 7111916.6 | AP48: =W48 -> CÁT LÁI | AQ48: LCL | AR48: 50H69181 | AS48: Từ Cảng CÁT LÁI đến BÀU XÉO, Đồng Nai | AT48: ADC
A49: PS254528 | B49: INV25070886 | C49: SZVLE2500661 | D49: 45864 | E49: 37 | F49: 37 | G49: 0.12 | J49: =+IF(F46=0, _xleta.T, IF(F46<=1000, 1260000, IF(F46<=2000, 1430000, IF(F46<=3000, 2120000, IF(F46<=4500, 2230000, ff))))) -> 1430000 | K49: 990000 | L49: 512050 | M49: 142236 | N49: 199130 | O49: 853416 | P49: 711180 | R49: 555 | S49: =+IF(F49<=2000, 30000, IF(F49<5000, 66000, ff)) -> 30000 | T49: =SUM(J49:S49)*0.08 -> 389485.36 | U49: =SUM(J49:T49) -> 5258052.4 | V49: =U49 -> 5258052.4 | W49: CÁT LÁI | X49: =A49 -> PS254528 | Y49: =B49 -> INV25070886 | Z49: =D49 -> 45864 | AA49: =E49/F49*H49 -> 0 | AB49: =(E49/F49)*I49 -> 0 | AC49: =(E49/F49)*J49 -> 1430000 | AD49: =(E49/F49)*K49 -> 990000 | AE49: =(E49/F49)*L49 -> 512050 | AF49: =(E49/F49)*M49 -> 142236 | AG49: =(E49/F49)*N49 -> 199130 | AH49: =(E49/F49)*O49 -> 853416 | AI49: =(E49/F49)*P49 -> 711180 | AJ49: =(E49/F49)*Q49 -> 0 | AK49: =(E49/F49)*R49 -> 555 | AL49: =(E49/F49)*S49 -> 30000 | AM49: =SUM(AC49:AL49)*0.08 -> 389485.36 | AN49: =SUM(AC49:AM49) -> 5258052.4 | AO49: =AN49 -> 5258052.4 | AP49: =W49 -> CÁT LÁI | AQ49: LCL | AR49: 50H69104 | AS49: Từ Cảng CÁT LÁI đến BÀU XÉO, Đồng Nai | AT49: ADC
A50: PS254557 | B50: XR20250716001 | C50: DGPE25070076 | D50: 45866 | E50: 168.2 | F50: 168.2 | G50: 0.88 | J50: =+IF(F47=0, _xleta.T, IF(F47<=1000, 1260000, IF(F47<=2000, 1430000, IF(F47<=3000, 2120000, IF(F47<=4500, 2230000, ff))))) -> 1260000 | K50: 990000 | L50: 4548096 | M50: 1421280 | N50: 2274048 | O50: 1421280 | R50: 2523 | S50: =+IF(F50<=2000, 30000, IF(F50<5000, 66000, ff)) -> 30000 | T50: =SUM(J50:S50)*0.08 -> 955778.16 | U50: =SUM(J50:T50) -> 12903005 | V50: =U50 -> 12903005 | W50: CÁT LÁI | X50: =A50 -> PS254557 | Y50: =B50 -> XR20250716001 | Z50: =D50 -> 45866 | AA50: =E50/F50*H50 -> 0 | AB50: =(E50/F50)*I50 -> 0 | AC50: =(E50/F50)*J50 -> 1260000 | AD50: =(E50/F50)*K50 -> 990000 | AE50: =(E50/F50)*L50 -> 4548096 | AF50: =(E50/F50)*M50 -> 1421280 | AG50: =(E50/F50)*N50 -> 2274048 | AH50: =(E50/F50)*O50 -> 1421280 | AI50: =(E50/F50)*P50 -> 0 | AJ50: =(E50/F50)*Q50 -> 0 | AK50: =(E50/F50)*R50 -> 2523 | AL50: =(E50/F50)*S50 -> 30000 | AM50: =SUM(AC50:AL50)*0.08 -> 955778.16 | AN50: =SUM(AC50:AM50) -> 12903005 | AO50: =AN50 -> 12903005 | AP50: =W50 -> CÁT LÁI | AQ50: LCL | AR50: 50H69181 | AS50: Từ Cảng CÁT LÁI đến BÀU XÉO, Đồng Nai | AT50: ADC
A51: PS254558 | B51: DL202507141 | C51: DGPE25070079 | D51: 45866 | E51: 1016.03 | F51: 1016.03 | G51: 5.349 | J51: =+IF(F48=0, _xleta.T, IF(F48<=1000, 1260000, IF(F48<=2000, 1430000, IF(F48<=3000, 2120000, IF(F48<=4500, 2230000, ff))))) -> 1260000 | K51: 990000 | L51: 19006067 | M51: 3040971.1 | N51: 6081941.2 | O51: 1421279 | R51: 15240 | S51: =+IF(F51<=2000, 30000, IF(F51<5000, 66000, ff)) -> 30000 | T51: =SUM(J51:S51)*0.08 -> 2547639.8 | U51: =SUM(J51:T51) -> 34393138 | V51: =U51 -> 34393138 | W51: CÁT LÁI | X51: =A51 -> PS254558 | Y51: =B51 -> DL202507141 | Z51: =D51 -> 45866 | AA51: =E51/F51*H51 -> 0 | AB51: =(E51/F51)*I51 -> 0 | AC51: =(E51/F51)*J51 -> 1260000 | AD51: =(E51/F51)*K51 -> 990000 | AE51: =(E51/F51)*L51 -> 19006067 | AF51: =(E51/F51)*M51 -> 3040971.1 | AG51: =(E51/F51)*N51 -> 6081941.2 | AH51: =(E51/F51)*O51 -> 1421279 | AI51: =(E51/F51)*P51 -> 0 | AJ51: =(E51/F51)*Q51 -> 0 | AK51: =(E51/F51)*R51 -> 15240 | AL51: =(E51/F51)*S51 -> 30000 | AM51: =SUM(AC51:AL51)*0.08 -> 2547639.8 | AN51: =SUM(AC51:AM51) -> 34393138 | AO51: =AN51 -> 34393138 | AP51: =W51 -> CÁT LÁI | AQ51: LCL | AR51: 50H69181 | AS51: Từ Cảng CÁT LÁI đến BÀU XÉO, Đồng Nai | AT51: ADC
A52: PS254559 | B52: DL20250714 | C52: DGPE25070078 | D52: 45866 | E52: 1239.07 | F52: 1239.07 | G52: 6.047 | J52: =+IF(F49=0, _xleta.T, IF(F49<=1000, 1260000, IF(F49<=2000, 1430000, IF(F49<=3000, 2120000, IF(F49<=4500, 2230000, ff))))) -> 1260000 | K52: 990000 | L52: 22345648 | M52: 4297240.1 | N52: 6875584.6 | O52: 1421280 | R52: 18587 | S52: =+IF(F52<=2000, 30000, IF(F52<5000, 66000, ff)) -> 30000 | T52: =SUM(J52:S52)*0.08 -> 2979067.2 | U52: =SUM(J52:T52) -> 40217407 | V52: =U52 -> 40217407 | W52: CÁT LÁI | X52: =A52 -> PS254559 | Y52: =B52 -> DL20250714 | Z52: =D52 -> 45866 | AA52: =E52/F52*H52 -> 0 | AB52: =(E52/F52)*I52 -> 0 | AC52: =(E52/F52)*J52 -> 1260000 | AD52: =(E52/F52)*K52 -> 990000 | AE52: =(E52/F52)*L52 -> 22345648 | AF52: =(E52/F52)*M52 -> 4297240.1 | AG52: =(E52/F52)*N52 -> 6875584.6 | AH52: =(E52/F52)*O52 -> 1421280 | AI52: =(E52/F52)*P52 -> 0 | AJ52: =(E52/F52)*Q52 -> 0 | AK52: =(E52/F52)*R52 -> 18587 | AL52: =(E52/F52)*S52 -> 30000 | AM52: =SUM(AC52:AL52)*0.08 -> 2979067.2 | AN52: =SUM(AC52:AM52) -> 40217407 | AO52: =AN52 -> 40217407 | AP52: =W52 -> CÁT LÁI | AQ52: LCL | AR52: 50H69181 | AS52: Từ Cảng CÁT LÁI đến BÀU XÉO, Đồng Nai | AT52: ADC
A53: PS254567 | B53: DL20250717 | C53: DGPE25070090 | D53: 45866 | E53: 381.5 | F53: 381.5 | G53: 2.128 | J53: =+IF(F50=0, _xleta.T, IF(F50<=1000, 1260000, IF(F50<=2000, 1430000, IF(F50<=3000, 2120000, IF(F50<=4500, 2230000, ff))))) -> 1260000 | K53: 990000 | L53: 9678348.7 | M53: 2419586.6 | N53: 2419586.6 | O53: 1421281 | R53: 5723 | S53: =+IF(F53<=2000, 30000, IF(F53<5000, 66000, ff)) -> 30000 | T53: =SUM(J53:S53)*0.08 -> 1457962.1 | U53: =SUM(J53:T53) -> 19682488 | V53: =U53 -> 19682488 | W53: CÁT LÁI | X53: =A53 -> PS254567 | Y53: =B53 -> DL20250717 | Z53: =D53 -> 45866 | AA53: =E53/F53*H53 -> 0 | AB53: =(E53/F53)*I53 -> 0 | AC53: =(E53/F53)*J53 -> 1260000 | AD53: =(E53/F53)*K53 -> 990000 | AE53: =(E53/F53)*L53 -> 9678348.7 | AF53: =(E53/F53)*M53 -> 2419586.6 | AG53: =(E53/F53)*N53 -> 2419586.6 | AH53: =(E53/F53)*O53 -> 1421281 | AI53: =(E53/F53)*P53 -> 0 | AJ53: =(E53/F53)*Q53 -> 0 | AK53: =(E53/F53)*R53 -> 5723 | AL53: =(E53/F53)*S53 -> 30000 | AM53: =SUM(AC53:AL53)*0.08 -> 1457962.1 | AN53: =SUM(AC53:AM53) -> 19682488 | AO53: =AN53 -> 19682488 | AP53: =W53 -> CÁT LÁI | AQ53: LCL | AR53: 50H69181 | AS53: Từ Cảng CÁT LÁI đến BÀU XÉO, Đồng Nai | AT53: ADC
A54: PS254578 | B54: D215978 | C54: GXSAG25071361 | D54: 45866 | E54: 1485 | F54: 1485 | G54: 6.3 | J54: =+IF(F51=0, _xleta.T, IF(F51<=1000, 1260000, IF(F51<=2000, 1430000, IF(F51<=3000, 2120000, IF(F51<=4500, 2230000, ff))))) -> 1430000 | K54: 990000 | L54: 1824152.4 | M54: 1824152.4 | N54: 1459321.9 | O54: 723870 | P54: 579096 | R54: 22275 | S54: =+IF(F54<=2000, 30000, IF(F54<5000, 66000, ff)) -> 30000 | T54: =SUM(J54:S54)*0.08 -> 710629.42 | U54: =SUM(J54:T54) -> 9593497.1 | V54: =U54 -> 9593497.1 | W54: CÁT LÁI | X54: =A54 -> PS254578 | Y54: =B54 -> D215978 | Z54: =D54 -> 45866 | AA54: =E54/F54*H54 -> 0 | AB54: =(E54/F54)*I54 -> 0 | AC54: =(E54/F54)*J54 -> 1430000 | AD54: =(E54/F54)*K54 -> 990000 | AE54: =(E54/F54)*L54 -> 1824152.4 | AF54: =(E54/F54)*M54 -> 1824152.4 | AG54: =(E54/F54)*N54 -> 1459321.9 | AH54: =(E54/F54)*O54 -> 723870 | AI54: =(E54/F54)*P54 -> 579096 | AJ54: =(E54/F54)*Q54 -> 0 | AK54: =(E54/F54)*R54 -> 22275 | AL54: =(E54/F54)*S54 -> 30000 | AM54: =SUM(AC54:AL54)*0.08 -> 710629.42 | AN54: =SUM(AC54:AM54) -> 9593497.1 | AO54: =AN54 -> 9593497.1 | AP54: =W54 -> CÁT LÁI | AQ54: LCL | AR54: 50H69181 | AS54: Từ Cảng CÁT LÁI đến BÀU XÉO, Đồng Nai | AT54: ADC
A55: PS254616 | B55: INV25070069 | C55: HOEX25070199 | D55: 45866 | E55: 189 | F55: 189 | G55: 0.751 | J55: =+IF(F52=0, _xleta.T, IF(F52<=1000, 1260000, IF(F52<=2000, 1430000, IF(F52<=3000, 2120000, IF(F52<=4500, 2230000, ff))))) -> 1430000 | K55: 990000 | L55: 881194 | O55: 568512 | R55: 2835 | S55: =+IF(F55<=2000, 30000, IF(F55<5000, 66000, ff)) -> 30000 | T55: =SUM(J55:S55)*0.08 -> 312203.28 | U55: =SUM(J55:T55) -> 4214744.3 | V55: =U55 -> 4214744.3 | W55: CÁT LÁI | X55: =A55 -> PS254616 | Y55: =B55 -> INV25070069 | Z55: =D55 -> 45866 | AA55: =E55/F55*H55 -> 0 | AB55: =(E55/F55)*I55 -> 0 | AC55: =(E55/F55)*J55 -> 1430000 | AD55: =(E55/F55)*K55 -> 990000 | AE55: =(E55/F55)*L55 -> 881194 | AF55: =(E55/F55)*M55 -> 0 | AG55: =(E55/F55)*N55 -> 0 | AH55: =(E55/F55)*O55 -> 568512 | AI55: =(E55/F55)*P55 -> 0 | AJ55: =(E55/F55)*Q55 -> 0 | AK55: =(E55/F55)*R55 -> 2835 | AL55: =(E55/F55)*S55 -> 30000 | AM55: =SUM(AC55:AL55)*0.08 -> 312203.28 | AN55: =SUM(AC55:AM55) -> 4214744.3 | AO55: =AN55 -> 4214744.3 | AP55: =W55 -> CÁT LÁI | AQ55: LCL | AR55: 50H93043 | AS55: Từ Cảng CÁT LÁI đến BÀU XÉO, Đồng Nai | AT55: ADC
A56: PS254612 | B56: PC250725VY | C56: JWE4151032 | D56: 45866 | E56: 13 | F56: 13 | J56: =+IF(F56<=50,1060000, IF(F56<=200, 1210000, IF(F56<=500, 1230000, IF(F56<=1000, 1440000, IF(F56<=2000, 1990000, IF(F56>2000, 1990000+(F56-2000)*1464)))))) -> 1060000 | K56: 990000 | P56: 668819 | Q56: 162000 | T56: =SUM(J56:S56)*0.08 -> 230465.52 | U56: =SUM(J56:T56) -> 3111284.5 | V56: =U56 -> 3111284.5 | W56: TCS | X56: =A56 -> PS254612 | Y56: =B56 -> PC250725VY | Z56: =D56 -> 45866 | AA56: =E56/F56*H56 -> 0 | AB56: =(E56/F56)*I56 -> 0 | AC56: =(E56/F56)*J56 -> 1060000 | AD56: =(E56/F56)*K56 -> 990000 | AE56: =(E56/F56)*L56 -> 0 | AF56: =(E56/F56)*M56 -> 0 | AG56: =(E56/F56)*N56 -> 0 | AH56: =(E56/F56)*O56 -> 0 | AI56: =(E56/F56)*P56 -> 668819 | AJ56: =(E56/F56)*Q56 -> 162000 | AK56: =(E56/F56)*R56 -> 0 | AL56: =(E56/F56)*S56 -> 0 | AM56: =SUM(AC56:AL56)*0.08 -> 230465.52 | AN56: =SUM(AC56:AM56) -> 3111284.5 | AO56: =AN56 -> 3111284.5 | AP56: =W56 -> TCS | AQ56: AIR | AR56: 51D17284 | AS56: Từ Kho TCS, Hồ Chí Minh đến Bàu Xéo, Hồ Chí Minh | AT56: ADC
A57: PS254613 | B57: G820250725 VY(B) | C57: JWE4151034 | D57: 45866 | E57: 9 | F57: 9 | J57: =+IF(F57<=50,1060000, IF(F57<=200, 1210000, IF(F57<=500, 1230000, IF(F57<=1000, 1440000, IF(F57<=2000, 1990000, IF(F57>2000, 1990000+(F57-2000)*1464)))))) -> 1060000 | K57: 990000 | P57: 598096 | Q57: 162000 | T57: =SUM(J57:S57)*0.08 -> 224807.68 | U57: =SUM(J57:T57) -> 3034903.7 | V57: =U57 -> 3034903.7 | W57: TCS | X57: =A57 -> PS254613 | Y57: =B57 -> G820250725 VY(B) | Z57: =D57 -> 45866 | AA57: =E57/F57*H57 -> 0 | AB57: =(E57/F57)*I57 -> 0 | AC57: =(E57/F57)*J57 -> 1060000 | AD57: =(E57/F57)*K57 -> 990000 | AE57: =(E57/F57)*L57 -> 0 | AF57: =(E57/F57)*M57 -> 0 | AG57: =(E57/F57)*N57 -> 0 | AH57: =(E57/F57)*O57 -> 0 | AI57: =(E57/F57)*P57 -> 598096 | AJ57: =(E57/F57)*Q57 -> 162000 | AK57: =(E57/F57)*R57 -> 0 | AL57: =(E57/F57)*S57 -> 0 | AM57: =SUM(AC57:AL57)*0.08 -> 224807.68 | AN57: =SUM(AC57:AM57) -> 3034903.7 | AO57: =AN57 -> 3034903.7 | AP57: =W57 -> TCS | AQ57: AIR | AR57: 51D17284 | AS57: Từ Kho TCS, Hồ Chí Minh đến Bàu Xéo, Hồ Chí Minh | AT57: ADC
A58: PS254629 | B58: T250725Y4 | C58: SPX2507033 | D58: 45866 | E58: 56 | F58: 56 | J58: =+IF(F58<=50,1060000, IF(F58<=200, 1210000, IF(F58<=500, 1230000, IF(F58<=1000, 1440000, IF(F58<=2000, 1990000, IF(F58>2000, 1990000+(F58-2000)*1464)))))) -> 1210000 | K58: 990000 | Q58: 162000 | T58: =SUM(J58:S58)*0.08 -> 188960 | U58: =SUM(J58:T58) -> 2550960 | V58: =U58 -> 2550960 | W58: TCS | X58: =A58 -> PS254629 | Y58: =B58 -> T250725Y4 | Z58: =D58 -> 45866 | AA58: =E58/F58*H58 -> 0 | AB58: =(E58/F58)*I58 -> 0 | AC58: =(E58/F58)*J58 -> 1210000 | AD58: =(E58/F58)*K58 -> 990000 | AE58: =(E58/F58)*L58 -> 0 | AF58: =(E58/F58)*M58 -> 0 | AG58: =(E58/F58)*N58 -> 0 | AH58: =(E58/F58)*O58 -> 0 | AI58: =(E58/F58)*P58 -> 0 | AJ58: =(E58/F58)*Q58 -> 162000 | AK58: =(E58/F58)*R58 -> 0 | AL58: =(E58/F58)*S58 -> 0 | AM58: =SUM(AC58:AL58)*0.08 -> 188960 | AN58: =SUM(AC58:AM58) -> 2550960 | AO58: =AN58 -> 2550960 | AP58: =W58 -> TCS | AQ58: AIR | AR58: 51D17284 | AS58: Từ Kho TCS, Hồ Chí Minh đến Bàu Xéo, Hồ Chí Minh | AT58: ADC
A59: PS254626 | B59: T250725Y2 | C59: SPX2507034 | D59: 45866 | E59: 130 | F59: 130 | J59: =+IF(F59<=50,1060000, IF(F59<=200, 1210000, IF(F59<=500, 1230000, IF(F59<=1000, 1440000, IF(F59<=2000, 1990000, IF(F59>2000, 1990000+(F59-2000)*1464)))))) -> 1210000 | K59: 990000 | Q59: 185328 | T59: =SUM(J59:S59)*0.08 -> 190826.24 | U59: =SUM(J59:T59) -> 2576154.2 | V59: =U59 -> 2576154.2 | W59: TCS | X59: =A59 -> PS254626 | Y59: =B59 -> T250725Y2 | Z59: =D59 -> 45866 | AA59: =E59/F59*H59 -> 0 | AB59: =(E59/F59)*I59 -> 0 | AC59: =(E59/F59)*J59 -> 1210000 | AD59: =(E59/F59)*K59 -> 990000 | AE59: =(E59/F59)*L59 -> 0 | AF59: =(E59/F59)*M59 -> 0 | AG59: =(E59/F59)*N59 -> 0 | AH59: =(E59/F59)*O59 -> 0 | AI59: =(E59/F59)*P59 -> 0 | AJ59: =(E59/F59)*Q59 -> 185328 | AK59: =(E59/F59)*R59 -> 0 | AL59: =(E59/F59)*S59 -> 0 | AM59: =SUM(AC59:AL59)*0.08 -> 190826.24 | AN59: =SUM(AC59:AM59) -> 2576154.2 | AO59: =AN59 -> 2576154.2 | AP59: =W59 -> TCS | AQ59: AIR | AR59: 51D17284 | AS59: Từ Kho TCS, Hồ Chí Minh đến Bàu Xéo, Hồ Chí Minh | AT59: ADC
A60: PS254577 | B60: LW25061 | C60: SWF25079624 | D60: 45867 | E60: 273 | F60: 273 | G60: 2.1 | J60: =+IF(F57=0, _xleta.T, IF(F57<=1000, 1260000, IF(F57<=2000, 1430000, IF(F57<=3000, 2120000, IF(F57<=4500, 2230000, ff))))) -> 1260000 | K60: 990000 | L60: 1731119 | M60: 596937.6 | N60: 596937.6 | O60: 852768 | P60: 852768 | Q60: 12371 | R60: 4095 | S60: =+IF(F60<=2000, 30000, IF(F60<5000, 66000, ff)) -> 30000 | T60: =SUM(J60:S60)*0.08 -> 554159.7 | U60: =SUM(J60:T60) -> 7481155.9 | V60: =U60 -> 7481155.9 | W60: CÁT LÁI | X60: =A60 -> PS254577 | Y60: =B60 -> LW25061 | Z60: =D60 -> 45867 | AA60: =E60/F60*H60 -> 0 | AB60: =(E60/F60)*I60 -> 0 | AC60: =(E60/F60)*J60 -> 1260000 | AD60: =(E60/F60)*K60 -> 990000 | AE60: =(E60/F60)*L60 -> 1731119 | AF60: =(E60/F60)*M60 -> 596937.6 | AG60: =(E60/F60)*N60 -> 596937.6 | AH60: =(E60/F60)*O60 -> 852768 | AI60: =(E60/F60)*P60 -> 852768 | AJ60: =(E60/F60)*Q60 -> 12371 | AK60: =(E60/F60)*R60 -> 4095 | AL60: =(E60/F60)*S60 -> 30000 | AM60: =SUM(AC60:AL60)*0.08 -> 554159.7 | AN60: =SUM(AC60:AM60) -> 7481155.9 | AO60: =AN60 -> 7481155.9 | AP60: =W60 -> CÁT LÁI | AQ60: LCL | AR60: 50H69350 | AS60: Từ Cảng CÁT LÁI đến BÀU XÉO, Đồng Nai | AT60: ADC
A61: PS254665 | B61: PC250728VY | C61: JWE4151044 | D61: 45868 | E61: 7 | F61: 7 | J61: =+IF(F61<=50,1060000, IF(F61<=200, 1210000, IF(F61<=500, 1230000, IF(F61<=1000, 1440000, IF(F61<=2000, 1990000, IF(F61>2000, 1990000+(F61-2000)*1464)))))) -> 1060000 | K61: 990000 | P61: 572080 | Q61: 162000 | T61: =SUM(J61:S61)*0.08 -> 222726.4 | U61: =SUM(J61:T61) -> 3006806.4 | V61: =U61 -> 3006806.4 | W61: TCS | X61: =A61 -> PS254665 | Y61: =B61 -> PC250728VY | Z61: =D61 -> 45868 | AA61: =E61/F61*H61 -> 0 | AB61: =(E61/F61)*I61 -> 0 | AC61: =(E61/F61)*J61 -> 1060000 | AD61: =(E61/F61)*K61 -> 990000 | AE61: =(E61/F61)*L61 -> 0 | AF61: =(E61/F61)*M61 -> 0 | AG61: =(E61/F61)*N61 -> 0 | AH61: =(E61/F61)*O61 -> 0 | AI61: =(E61/F61)*P61 -> 572080 | AJ61: =(E61/F61)*Q61 -> 162000 | AK61: =(E61/F61)*R61 -> 0 | AL61: =(E61/F61)*S61 -> 0 | AM61: =SUM(AC61:AL61)*0.08 -> 222726.4 | AN61: =SUM(AC61:AM61) -> 3006806.4 | AO61: =AN61 -> 3006806.4 | AP61: =W61 -> TCS | AQ61: AIR | AR61: 51D17709 | AS61: Từ Kho TCS, Hồ Chí Minh đến Bàu Xéo, Hồ Chí Minh | AT61: ADC
A62: PS254668 | B62: PS254668 | C62: 7672947590 | D62: 45868 | E62: 11.5 | F62: 11.5 | K62: 600000 | T62: =SUM(J62:S62)*0.08 -> 48000 | U62: =SUM(J62:T62) -> 648000 | V62: =U62 -> 648000 | W62: DHL | X62: =A62 -> PS254668 | Y62: =B62 -> PS254668 | Z62: =D62 -> 45868 | AA62: =E62/F62*H62 -> 0 | AB62: =(E62/F62)*I62 -> 0 | AC62: =(E62/F62)*J62 -> 0 | AD62: =(E62/F62)*K62 -> 600000 | AE62: =(E62/F62)*L62 -> 0 | AF62: =(E62/F62)*M62 -> 0 | AG62: =(E62/F62)*N62 -> 0 | AH62: =(E62/F62)*O62 -> 0 | AI62: =(E62/F62)*P62 -> 0 | AJ62: =(E62/F62)*Q62 -> 0 | AK62: =(E62/F62)*R62 -> 0 | AL62: =(E62/F62)*S62 -> 0 | AM62: =SUM(AC62:AL62)*0.08 -> 48000 | AN62: =SUM(AC62:AM62) -> 648000 | AO62: =AN62 -> 648000 | AP62: =W62 -> DHL | AQ62: EXP
A63: PS254608 | B63: INJF2507141 | C63: DGPE25070072 | D63: 45868 | E63: 1268 | F63: 1268 | G63: 4.76 | J63: =+IF(F60=0, _xleta.T, IF(F60<=1000, 1260000, IF(F60<=2000, 1430000, IF(F60<=3000, 2120000, IF(F60<=4500, 2230000, ff))))) -> 1260000 | K63: 990000 | L63: 17589761 | M63: 3382646.4 | N63: 5412234.2 | O63: 1421279 | R63: 19020 | S63: =+IF(F63<=2000, 30000, IF(F63<5000, 66000, ff)) -> 30000 | T63: =SUM(J63:S63)*0.08 -> 2408395.3 | U63: =SUM(J63:T63) -> 32513336 | V63: =U63 -> 32513336 | W63: CÁT LÁI | X63: =A63 -> PS254608 | Y63: =B63 -> INJF2507141 | Z63: =D63 -> 45868 | AA63: =E63/F63*H63 -> 0 | AB63: =(E63/F63)*I63 -> 0 | AC63: =(E63/F63)*J63 -> 1260000 | AD63: =(E63/F63)*K63 -> 990000 | AE63: =(E63/F63)*L63 -> 17589761 | AF63: =(E63/F63)*M63 -> 3382646.4 | AG63: =(E63/F63)*N63 -> 5412234.2 | AH63: =(E63/F63)*O63 -> 1421279 | AI63: =(E63/F63)*P63 -> 0 | AJ63: =(E63/F63)*Q63 -> 0 | AK63: =(E63/F63)*R63 -> 19020 | AL63: =(E63/F63)*S63 -> 30000 | AM63: =SUM(AC63:AL63)*0.08 -> 2408395.3 | AN63: =SUM(AC63:AM63) -> 32513336 | AO63: =AN63 -> 32513336 | AP63: =W63 -> CÁT LÁI | AQ63: LCL | AR63: 50H69181 | AS63: Từ Cảng CÁT LÁI đến BÀU XÉO, Đồng Nai | AT63: ADC
A64: PS254607 | B64: INJF250714 | C64: DGPE25070071 | D64: 45868 | E64: 1392 | F64: 1392 | G64: 4.76 | J64: =+IF(F61=0, _xleta.T, IF(F61<=1000, 1260000, IF(F61<=2000, 1430000, IF(F61<=3000, 2120000, IF(F61<=4500, 2230000, ff))))) -> 1260000 | K64: 990000 | L64: 17589761 | M64: 3382645.4 | N64: 5412234.2 | O64: 1421280 | R64: 20880 | S64: =+IF(F64<=2000, 30000, IF(F64<5000, 66000, ff)) -> 30000 | T64: =SUM(J64:S64)*0.08 -> 2408544.1 | U64: =SUM(J64:T64) -> 32515345 | V64: =U64 -> 32515345 | W64: CÁT LÁI | X64: =A64 -> PS254607 | Y64: =B64 -> INJF250714 | Z64: =D64 -> 45868 | AA64: =E64/F64*H64 -> 0 | AB64: =(E64/F64)*I64 -> 0 | AC64: =(E64/F64)*J64 -> 1260000 | AD64: =(E64/F64)*K64 -> 990000 | AE64: =(E64/F64)*L64 -> 17589761 | AF64: =(E64/F64)*M64 -> 3382645.4 | AG64: =(E64/F64)*N64 -> 5412234.2 | AH64: =(E64/F64)*O64 -> 1421280 | AI64: =(E64/F64)*P64 -> 0 | AJ64: =(E64/F64)*Q64 -> 0 | AK64: =(E64/F64)*R64 -> 20880 | AL64: =(E64/F64)*S64 -> 30000 | AM64: =SUM(AC64:AL64)*0.08 -> 2408544.1 | AN64: =SUM(AC64:AM64) -> 32515345 | AO64: =AN64 -> 32515345 | AP64: =W64 -> CÁT LÁI | AQ64: LCL | AR64: 50H69181 | AS64: Từ Cảng CÁT LÁI đến BÀU XÉO, Đồng Nai | AT64: ADC
A65: PS254604 | B65: 1813728094 | C65: 08SEA2507062 | D65: 45868 | E65: 11.9 | F65: 11.9 | G65: 0.034 | J65: =+IF(F62=0, _xleta.T, IF(F62<=1000, 1260000, IF(F62<=2000, 1430000, IF(F62<=3000, 2120000, IF(F62<=4500, 2230000, ff))))) -> 1260000 | K65: 990000 | L65: 880859 | O65: 1989036 | R65: 179 | S65: =+IF(F65<=2000, 30000, IF(F65<5000, 66000, ff)) -> 30000 | T65: =SUM(J65:S65)*0.08 -> 412005.92 | U65: =SUM(J65:T65) -> 5562079.9 | V65: =U65 -> 5562079.9 | W65: CÁT LÁI | X65: =A65 -> PS254604 | Y65: =B65 -> 1813728094 | Z65: =D65 -> 45868 | AA65: =E65/F65*H65 -> 0 | AB65: =(E65/F65)*I65 -> 0 | AC65: =(E65/F65)*J65 -> 1260000 | AD65: =(E65/F65)*K65 -> 990000 | AE65: =(E65/F65)*L65 -> 880859 | AF65: =(E65/F65)*M65 -> 0 | AG65: =(E65/F65)*N65 -> 0 | AH65: =(E65/F65)*O65 -> 1989036 | AI65: =(E65/F65)*P65 -> 0 | AJ65: =(E65/F65)*Q65 -> 0 | AK65: =(E65/F65)*R65 -> 179 | AL65: =(E65/F65)*S65 -> 30000 | AM65: =SUM(AC65:AL65)*0.08 -> 412005.92 | AN65: =SUM(AC65:AM65) -> 5562079.9 | AO65: =AN65 -> 5562079.9 | AP65: =W65 -> CÁT LÁI | AQ65: LCL | AR65: 50H69181 | AS65: Từ Cảng CÁT LÁI đến BÀU XÉO, Đồng Nai | AT65: ADC
A66: PS254606 | B66: IE20250718095 | C66: AWSXMLCL25070661 | D66: 45868 | E66: 997.3 | F66: 997.3 | G66: 4 | J66: =+IF(F63=0, _xleta.T, IF(F63<=1000, 1260000, IF(F63<=2000, 1430000, IF(F63<=3000, 2120000, IF(F63<=4500, 2230000, ff))))) -> 1430000 | K66: 990000 | L66: 3922733 | M66: 795917 | N66: 2274048 | O66: 710640 | P66: 1421280 | Q66: 47127 | R66: 14960 | S66: =+IF(F66<=2000, 30000, IF(F66<5000, 66000, ff)) -> 30000 | T66: =SUM(J66:S66)*0.08 -> 930936.4 | U66: =SUM(J66:T66) -> 12567641 | V66: =U66 -> 12567641 | W66: CÁT LÁI | X66: =A66 -> PS254606 | Y66: =B66 -> IE20250718095 | Z66: =D66 -> 45868 | AA66: =E66/F66*H66 -> 0 | AB66: =(E66/F66)*I66 -> 0 | AC66: =(E66/F66)*J66 -> 1430000 | AD66: =(E66/F66)*K66 -> 990000 | AE66: =(E66/F66)*L66 -> 3922733 | AF66: =(E66/F66)*M66 -> 795917 | AG66: =(E66/F66)*N66 -> 2274048 | AH66: =(E66/F66)*O66 -> 710640 | AI66: =(E66/F66)*P66 -> 1421280 | AJ66: =(E66/F66)*Q66 -> 47127 | AK66: =(E66/F66)*R66 -> 14960 | AL66: =(E66/F66)*S66 -> 30000 | AM66: =SUM(AC66:AL66)*0.08 -> 930936.4 | AN66: =SUM(AC66:AM66) -> 12567641 | AO66: =AN66 -> 12567641 | AP66: =W66 -> CÁT LÁI | AQ66: LCL | AR66: 50H69181 | AS66: Từ Cảng CÁT LÁI đến BÀU XÉO, Đồng Nai | AT66: ADC
A67: PS254671 | B67: IE20250723108 | C67: XMNA006249 | D67: 45868 | E67: 118 | F67: 118 | J67: =+IF(F67<=50,1060000, IF(F67<=200, 1210000, IF(F67<=500, 1230000, IF(F67<=1000, 1440000, IF(F67<=2000, 1990000, IF(F67>2000, 1990000+(F67-2000)*1464)))))) -> 1210000 | K67: 990000 | P67: 1705536 | Q67: 1006928 | T67: =SUM(J67:S67)*0.08 -> 392997.12 | U67: =SUM(J67:T67) -> 5305461.1 | V67: =U67 -> 5305461.1 | W67: SCSC | X67: =A67 -> PS254671 | Y67: =B67 -> IE20250723108 | Z67: =D67 -> 45868 | AA67: =E67/F67*H67 -> 0 | AB67: =(E67/F67)*I67 -> 0 | AC67: =(E67/F67)*J67 -> 1210000 | AD67: =(E67/F67)*K67 -> 990000 | AE67: =(E67/F67)*L67 -> 0 | AF67: =(E67/F67)*M67 -> 0 | AG67: =(E67/F67)*N67 -> 0 | AH67: =(E67/F67)*O67 -> 0 | AI67: =(E67/F67)*P67 -> 1705536 | AJ67: =(E67/F67)*Q67 -> 1006928 | AK67: =(E67/F67)*R67 -> 0 | AL67: =(E67/F67)*S67 -> 0 | AM67: =SUM(AC67:AL67)*0.08 -> 392997.12 | AN67: =SUM(AC67:AM67) -> 5305461.1 | AO67: =AN67 -> 5305461.1 | AP67: =W67 -> SCSC | AQ67: AIR | AR67: 50H69104 | AS67: Từ Kho TCS, Hồ Chí Minh đến Bàu Xéo, Hồ Chí Minh | AT67: ADC
A68: PS254605 | B68: HP2284G | C68: SZHTHCM2507079 | D68: 45868 | E68: 1435.5 | F68: 1435.5 | G68: 3.05 | J68: =+IF(F65=0, _xleta.T, IF(F65<=1000, 1260000, IF(F65<=2000, 1430000, IF(F65<=3000, 2120000, IF(F65<=4500, 2230000, ff))))) -> 1260000 | K68: 990000 | L68: 6155563.7 | M68: 1733961.6 | N68: 780283.72 | O68: 852768 | P68: 1137024 | R68: 21533 | S68: =+IF(F68<=2000, 30000, IF(F68<5000, 66000, ff)) -> 30000 | T68: =SUM(J68:S68)*0.08 -> 1036890.7 | U68: =SUM(J68:T68) -> 13998025 | V68: =U68 -> 13998025 | W68: CÁT LÁI | X68: =A68 -> PS254605 | Y68: =B68 -> HP2284G | Z68: =D68 -> 45868 | AA68: =E68/F68*H68 -> 0 | AB68: =(E68/F68)*I68 -> 0 | AC68: =(E68/F68)*J68 -> 1260000 | AD68: =(E68/F68)*K68 -> 990000 | AE68: =(E68/F68)*L68 -> 6155563.7 | AF68: =(E68/F68)*M68 -> 1733961.6 | AG68: =(E68/F68)*N68 -> 780283.72 | AH68: =(E68/F68)*O68 -> 852768 | AI68: =(E68/F68)*P68 -> 1137024 | AJ68: =(E68/F68)*Q68 -> 0 | AK68: =(E68/F68)*R68 -> 21533 | AL68: =(E68/F68)*S68 -> 30000 | AM68: =SUM(AC68:AL68)*0.08 -> 1036890.7 | AN68: =SUM(AC68:AM68) -> 13998025 | AO68: =AN68 -> 13998025 | AP68: =W68 -> CÁT LÁI | AQ68: LCL | AR68: 51D17709 | AS68: Từ Cảng CÁT LÁI đến BÀU XÉO, Đồng Nai | AT68: ADC
A69: PS254597 | B69: T250720Y1 | C69: SPOE2507120 | D69: 45868 | E69: 972.72 | F69: 972.72 | G69: 4.04 | J69: =+IF(F66=0, _xleta.T, IF(F66<=1000, 1260000, IF(F66<=2000, 1430000, IF(F66<=3000, 2120000, IF(F66<=4500, 2230000, ff))))) -> 1260000 | K69: =990000+70000 -> 1060000 | L69: 3560022 | O69: 1137024 | R69: 14591 | S69: =+IF(F69<=2000, 30000, IF(F69<5000, 66000, ff)) -> 30000 | T69: =SUM(J69:S69)*0.08 -> 564930.96 | U69: =SUM(J69:T69) -> 7626568 | V69: =U69 -> 7626568 | W69: CÁT LÁI | X69: =A69 -> PS254597 | Y69: =B69 -> T250720Y1 | Z69: =D69 -> 45868 | AA69: =E69/F69*H69 -> 0 | AB69: =(E69/F69)*I69 -> 0 | AC69: =(E69/F69)*J69 -> 1260000 | AD69: =(E69/F69)*K69 -> 1060000 | AE69: =(E69/F69)*L69 -> 3560022 | AF69: =(E69/F69)*M69 -> 0 | AG69: =(E69/F69)*N69 -> 0 | AH69: =(E69/F69)*O69 -> 1137024 | AI69: =(E69/F69)*P69 -> 0 | AJ69: =(E69/F69)*Q69 -> 0 | AK69: =(E69/F69)*R69 -> 14591 | AL69: =(E69/F69)*S69 -> 30000 | AM69: =SUM(AC69:AL69)*0.08 -> 564930.96 | AN69: =SUM(AC69:AM69) -> 7626568 | AO69: =AN69 -> 7626568 | AP69: =W69 -> CÁT LÁI | AQ69: LCL | AR69: 60H11265 | AS69: Từ Cảng CÁT LÁI đến BÀU XÉO, Đồng Nai | AT69: ADC
A70: PS254597 | D70: 45868 | F70: 972.72 | J70: =+IF(F67=0, _xleta.T, IF(F67<=1000, 1260000, IF(F67<=2000, 1430000, IF(F67<=3000, 2120000, IF(F67<=4500, 2230000, ff))))) -> 1260000 | K70: =990000+70000 -> 1060000 | L70: 3560022 | O70: 1137024 | R70: 14591 | S70: =+IF(F70<=2000, 30000, IF(F70<5000, 66000, ff)) -> 30000 | T70: =SUM(J70:S70)*0.08 -> 564930.96 | U70: =SUM(J70:T70) -> 7626568 | V70: =U70 -> 7626568 | W70: CÁT LÁI | X70: =A70 -> PS254597 | Y70: =B70 -> 0 | Z70: =D70 -> 45868 | AA70: =E70/F70*H70 -> 0 | AB70: =(E70/F70)*I70 -> 0 | AC70: =(E70/F70)*J70 -> 0 | AD70: =(E70/F70)*K70 -> 0 | AE70: =(E70/F70)*L70 -> 0 | AF70: =(E70/F70)*M70 -> 0 | AG70: =(E70/F70)*N70 -> 0 | AH70: =(E70/F70)*O70 -> 0 | AI70: =(E70/F70)*P70 -> 0 | AJ70: =(E70/F70)*Q70 -> 0 | AK70: =(E70/F70)*R70 -> 0 | AL70: =(E70/F70)*S70 -> 0 | AM70: =SUM(AC70:AL70)*0.08 -> 0 | AN70: =SUM(AC70:AM70) -> 0 | AO70: =AN70 -> 0 | AP70: =W70 -> CÁT LÁI | AQ70: LCL | AR70: 60H11265 | AS70: Từ Cảng CÁT LÁI đến BÀU XÉO, Đồng Nai | AT70: ADC
A71: PS254600 | B71: 250715JHJ03A | C71: SPOE2507088 | D71: 45868 | E71: 420 | F71: 420 | G71: 0.64 | J71: =+IF(F68=0, _xleta.T, IF(F68<=1000, 1260000, IF(F68<=2000, 1430000, IF(F68<=3000, 2120000, IF(F68<=4500, 2230000, ff))))) -> 1430000 | K71: 990000 | R71: 6300 | S71: =+IF(F71<=2000, 30000, IF(F71<5000, 66000, ff)) -> 30000 | T71: =SUM(J71:S71)*0.08 -> 196504 | U71: =SUM(J71:T71) -> 2652804 | V71: =U71 -> 2652804 | W71: CÁT LÁI | X71: =A71 -> PS254600 | Y71: =B71 -> 250715JHJ03A | Z71: =D71 -> 45868 | AA71: =E71/F71*H71 -> 0 | AB71: =(E71/F71)*I71 -> 0 | AC71: =(E71/F71)*J71 -> 1430000 | AD71: =(E71/F71)*K71 -> 990000 | AE71: =(E71/F71)*L71 -> 0 | AF71: =(E71/F71)*M71 -> 0 | AG71: =(E71/F71)*N71 -> 0 | AH71: =(E71/F71)*O71 -> 0 | AI71: =(E71/F71)*P71 -> 0 | AJ71: =(E71/F71)*Q71 -> 0 | AK71: =(E71/F71)*R71 -> 6300 | AL71: =(E71/F71)*S71 -> 30000 | AM71: =SUM(AC71:AL71)*0.08 -> 196504 | AN71: =SUM(AC71:AM71) -> 2652804 | AO71: =AN71 -> 2652804 | AP71: =W71 -> CÁT LÁI | AQ71: LCL | AR71: 60H11265 | AS71: Từ Cảng CÁT LÁI đến BÀU XÉO, Đồng Nai | AT71: ADC
A72: PS254644 | B72: T250717Y1 | C72: SPOE2507091 | D72: 45868 | E72: 1692.37 | F72: 1692.37 | G72: 7.85 | J72: =+IF(F69=0, _xleta.T, IF(F69<=1000, 1260000, IF(F69<=2000, 1430000, IF(F69<=3000, 2120000, IF(F69<=4500, 2230000, ff))))) -> 1260000 | K72: 990000 | L72: 6914742 | O72: 1136592 | R72: 25386 | S72: =+IF(F72<=2000, 30000, IF(F72<5000, 66000, ff)) -> 30000 | T72: =SUM(J72:S72)*0.08 -> 828537.6 | U72: =SUM(J72:T72) -> 11185258 | V72: =U72 -> 11185258 | W72: CÁT LÁI | X72: =A72 -> PS254644 | Y72: =B72 -> T250717Y1 | Z72: =D72 -> 45868 | AA72: =E72/F72*H72 -> 0 | AB72: =(E72/F72)*I72 -> 0 | AC72: =(E72/F72)*J72 -> 1260000 | AD72: =(E72/F72)*K72 -> 990000 | AE72: =(E72/F72)*L72 -> 6914742 | AF72: =(E72/F72)*M72 -> 0 | AG72: =(E72/F72)*N72 -> 0 | AH72: =(E72/F72)*O72 -> 1136592 | AI72: =(E72/F72)*P72 -> 0 | AJ72: =(E72/F72)*Q72 -> 0 | AK72: =(E72/F72)*R72 -> 25386 | AL72: =(E72/F72)*S72 -> 30000 | AM72: =SUM(AC72:AL72)*0.08 -> 828537.6 | AN72: =SUM(AC72:AM72) -> 11185258 | AO72: =AN72 -> 11185258 | AP72: =W72 -> CÁT LÁI | AQ72: LCL | AR72: 60H11265 | AS72: Từ Cảng CÁT LÁI đến BÀU XÉO, Đồng Nai | AT72: ADC
A73: PS254649 | B73: DJL250711025 | C73: 20SEA25070113 | D73: 45868 | E73: 327.2 | F73: 327.2 | G73: 0.984 | J73: =+IF(F70=0, _xleta.T, IF(F70<=1000, 1260000, IF(F70<=2000, 1430000, IF(F70<=3000, 2120000, IF(F70<=4500, 2230000, ff))))) -> 1260000 | K73: 990000 | L73: 881194 | O73: 1847664 | R73: 4908 | S73: =+IF(F73<=2000, 30000, IF(F73<5000, 66000, ff)) -> 30000 | T73: =SUM(J73:S73)*0.08 -> 401101.28 | U73: =SUM(J73:T73) -> 5414867.3 | V73: =U73 -> 5414867.3 | W73: CÁT LÁI | X73: =A73 -> PS254649 | Y73: =B73 -> DJL250711025 | Z73: =D73 -> 45868 | AA73: =E73/F73*H73 -> 0 | AB73: =(E73/F73)*I73 -> 0 | AC73: =(E73/F73)*J73 -> 1260000 | AD73: =(E73/F73)*K73 -> 990000 | AE73: =(E73/F73)*L73 -> 881194 | AF73: =(E73/F73)*M73 -> 0 | AG73: =(E73/F73)*N73 -> 0 | AH73: =(E73/F73)*O73 -> 1847664 | AI73: =(E73/F73)*P73 -> 0 | AJ73: =(E73/F73)*Q73 -> 0 | AK73: =(E73/F73)*R73 -> 4908 | AL73: =(E73/F73)*S73 -> 30000 | AM73: =SUM(AC73:AL73)*0.08 -> 401101.28 | AN73: =SUM(AC73:AM73) -> 5414867.3 | AO73: =AN73 -> 5414867.3 | AP73: =W73 -> CÁT LÁI | AQ73: LCL | AR73: 60H11265 | AS73: Từ Cảng CÁT LÁI đến BÀU XÉO, Đồng Nai | AT73: ADC
A74: PS254646 | B74: OHTY250861 | C74: 08SEA2507054 | D74: 45868 | E74: 946 | F74: 946 | G74: 8.226 | J74: =+IF(F71=0, _xleta.T, IF(F71<=1000, 1260000, IF(F71<=2000, 1430000, IF(F71<=3000, 2120000, IF(F71<=4500, 2230000, ff))))) -> 1260000 | K74: 990000 | L74: 7246058 | O74: 1989036 | R74: 14190 | S74: =+IF(F74<=2000, 30000, IF(F74<5000, 66000, ff)) -> 30000 | T74: =SUM(J74:S74)*0.08 -> 922342.72 | U74: =SUM(J74:T74) -> 12451627 | V74: =U74 -> 12451627 | W74: CÁT LÁI | X74: =A74 -> PS254646 | Y74: =B74 -> OHTY250861 | Z74: =D74 -> 45868 | AA74: =E74/F74*H74 -> 0 | AB74: =(E74/F74)*I74 -> 0 | AC74: =(E74/F74)*J74 -> 1260000 | AD74: =(E74/F74)*K74 -> 990000 | AE74: =(E74/F74)*L74 -> 7246058 | AF74: =(E74/F74)*M74 -> 0 | AG74: =(E74/F74)*N74 -> 0 | AH74: =(E74/F74)*O74 -> 1989036 | AI74: =(E74/F74)*P74 -> 0 | AJ74: =(E74/F74)*Q74 -> 0 | AK74: =(E74/F74)*R74 -> 14190 | AL74: =(E74/F74)*S74 -> 30000 | AM74: =SUM(AC74:AL74)*0.08 -> 922342.72 | AN74: =SUM(AC74:AM74) -> 12451627 | AO74: =AN74 -> 12451627 | AP74: =W74 -> CÁT LÁI | AQ74: LCL | AR74: 60H11265 | AS74: Từ Cảng CÁT LÁI đến BÀU XÉO, Đồng Nai | AT74: ADC
A75: PS254689 | B75: G820250729 VY (B) | C75: JWE4151047 | D75: 45869 | E75: 10 | F75: 10 | J75: =+IF(F75<=50,1060000, IF(F75<=200, 1210000, IF(F75<=500, 1230000, IF(F75<=1000, 1440000, IF(F75<=2000, 1990000, IF(F75>2000, 1990000+(F75-2000)*1464)))))) -> 1060000 | K75: 990000 | P75: 576497 | Q75: 162000 | T75: =SUM(J75:S75)*0.08 -> 223079.76 | U75: =SUM(J75:T75) -> 3011576.8 | V75: =U75 -> 3011576.8 | W75: TCS | X75: =A75 -> PS254689 | Y75: =B75 -> G820250729 VY (B) | Z75: =D75 -> 45869 | AA75: =E75/F75*H75 -> 0 | AB75: =(E75/F75)*I75 -> 0 | AC75: =(E75/F75)*J75 -> 1060000 | AD75: =(E75/F75)*K75 -> 990000 | AE75: =(E75/F75)*L75 -> 0 | AF75: =(E75/F75)*M75 -> 0 | AG75: =(E75/F75)*N75 -> 0 | AH75: =(E75/F75)*O75 -> 0 | AI75: =(E75/F75)*P75 -> 576497 | AJ75: =(E75/F75)*Q75 -> 162000 | AK75: =(E75/F75)*R75 -> 0 | AL75: =(E75/F75)*S75 -> 0 | AM75: =SUM(AC75:AL75)*0.08 -> 223079.76 | AN75: =SUM(AC75:AM75) -> 3011576.8 | AO75: =AN75 -> 3011576.8 | AP75: =W75 -> TCS | AQ75: AIR | AR75: 51D17709 | AS75: Từ Kho TCS, Hồ Chí Minh đến Bàu Xéo, Hồ Chí Minh | AT75: ADC
A76: PS254687 | B76: PC250729VY | C76: JWE4151052 | D76: 45869 | E76: 23 | F76: 23 | J76: =+IF(F76<=50,1060000, IF(F76<=200, 1210000, IF(F76<=500, 1230000, IF(F76<=1000, 1440000, IF(F76<=2000, 1990000, IF(F76>2000, 1990000+(F76-2000)*1464)))))) -> 1060000 | K76: 990000 | P76: 596713 | Q76: 162000 | T76: =SUM(J76:S76)*0.08 -> 224697.04 | U76: =SUM(J76:T76) -> 3033410 | V76: =U76 -> 3033410 | W76: TCS | X76: =A76 -> PS254687 | Y76: =B76 -> PC250729VY | Z76: =D76 -> 45869 | AA76: =E76/F76*H76 -> 0 | AB76: =(E76/F76)*I76 -> 0 | AC76: =(E76/F76)*J76 -> 1060000 | AD76: =(E76/F76)*K76 -> 990000 | AE76: =(E76/F76)*L76 -> 0 | AF76: =(E76/F76)*M76 -> 0 | AG76: =(E76/F76)*N76 -> 0 | AH76: =(E76/F76)*O76 -> 0 | AI76: =(E76/F76)*P76 -> 596713 | AJ76: =(E76/F76)*Q76 -> 162000 | AK76: =(E76/F76)*R76 -> 0 | AL76: =(E76/F76)*S76 -> 0 | AM76: =SUM(AC76:AL76)*0.08 -> 224697.04 | AN76: =SUM(AC76:AM76) -> 3033410 | AO76: =AN76 -> 3033410 | AP76: =W76 -> TCS | AQ76: AIR | AR76: 51D17709 | AS76: Từ Kho TCS, Hồ Chí Minh đến Bàu Xéo, Hồ Chí Minh | AT76: ADC
A77: PS254654 | B77: VY250724TTICD | C77: 112500035573280 | D77: 45869 | E77: 1545.6 | F77: 1545.6 | J77: =+IF(F74=0, _xleta.T, IF(F74<=1000, 1260000, IF(F74<=2000, 1430000, IF(F74<=3000, 2120000, IF(F74<=4500, 2230000, ff))))) -> 1260000 | K77: 990000 | S77: =+IF(F77<=2000, 30000, IF(F77<5000, 66000, ff)) -> 30000 | T77: =SUM(J77:S77)*0.08 -> 182400 | U77: =SUM(J77:T77) -> 2462400 | V77: =U77 -> 2462400 | W77: ICD BIEN HOA | X77: =A77 -> PS254654 | Y77: =B77 -> VY250724TTICD | Z77: =D77 -> 45869 | AA77: =E77/F77*H77 -> 0 | AB77: =(E77/F77)*I77 -> 0 | AC77: =(E77/F77)*J77 -> 1260000 | AD77: =(E77/F77)*K77 -> 990000 | AE77: =(E77/F77)*L77 -> 0 | AF77: =(E77/F77)*M77 -> 0 | AG77: =(E77/F77)*N77 -> 0 | AH77: =(E77/F77)*O77 -> 0 | AI77: =(E77/F77)*P77 -> 0 | AJ77: =(E77/F77)*Q77 -> 0 | AK77: =(E77/F77)*R77 -> 0 | AL77: =(E77/F77)*S77 -> 30000 | AM77: =SUM(AC77:AL77)*0.08 -> 182400 | AN77: =SUM(AC77:AM77) -> 2462400 | AO77: =AN77 -> 2462400 | AP77: =W77 -> ICD BIEN HOA | AQ77: LCL | AR77: 51D17284 | AS77: Từ KNQ ICD Biên Hòa đến Bàu Xéo, Đồng Nai | AT77: ADC
A78: PS254580 | B78: BE25070002 | C78: AMIGL250301445A | D78: 45869 | E78: 946 | F78: 946 | G78: 2 | J78: =+IF(F75=0, _xleta.T, IF(F75<=1000, 1260000, IF(F75<=2000, 1430000, IF(F75<=3000, 2120000, IF(F75<=4500, 2230000, ff))))) -> 1260000 | K78: 990000 | L78: 5884099 | M78: 284256 | N78: 568512 | O78: 710640 | P78: 710640 | Q78: 260918 | R78: 14190 | S78: =+IF(F78<=2000, 30000, IF(F78<5000, 66000, ff)) -> 30000 | T78: =SUM(J78:S78)*0.08 -> 857060.4 | U78: =SUM(J78:T78) -> 11570315 | V78: =U78 -> 11570315 | W78: CÁT LÁI | X78: =A78 -> PS254580 | Y78: =B78 -> BE25070002 | Z78: =D78 -> 45869 | AA78: =E78/F78*H78 -> 0 | AB78: =(E78/F78)*I78 -> 0 | AC78: =(E78/F78)*J78 -> 1260000 | AD78: =(E78/F78)*K78 -> 990000 | AE78: =(E78/F78)*L78 -> 5884099 | AF78: =(E78/F78)*M78 -> 284256 | AG78: =(E78/F78)*N78 -> 568512 | AH78: =(E78/F78)*O78 -> 710640 | AI78: =(E78/F78)*P78 -> 710640 | AJ78: =(E78/F78)*Q78 -> 260918 | AK78: =(E78/F78)*R78 -> 14190 | AL78: =(E78/F78)*S78 -> 30000 | AM78: =SUM(AC78:AL78)*0.08 -> 857060.4 | AN78: =SUM(AC78:AM78) -> 11570315 | AO78: =AN78 -> 11570315 | AP78: =W78 -> CÁT LÁI | AQ78: LCL | AR78: 50E14909 | AS78: Từ Cảng CÁT LÁI đến BÀU XÉO, Đồng Nai | AT78: NGỌC HẠNH
A79: PS254684 | B79: PS254684 | C79: MLHCM2507023 | D79: 45869 | E79: 1485 | F79: 1485 | G79: 3.529 | J79: =+IF(F76=0, _xleta.T, IF(F76<=1000, 1260000, IF(F76<=2000, 1430000, IF(F76<=3000, 2120000, IF(F76<=4500, 2230000, ff))))) -> 1260000 | K79: 990000 | R79: 22275 | S79: =+IF(F79<=2000, 30000, IF(F79<5000, 66000, ff)) -> 30000 | T79: =SUM(J79:S79)*0.08 -> 184182 | U79: =SUM(J79:T79) -> 2486457 | V79: =U79 -> 2486457 | W79: CÁT LÁI | X79: =A79 -> PS254684 | Y79: =B79 -> PS254684 | Z79: =D79 -> 45869 | AA79: =E79/F79*H79 -> 0 | AB79: =(E79/F79)*I79 -> 0 | AC79: =(E79/F79)*J79 -> 1260000 | AD79: =(E79/F79)*K79 -> 990000 | AE79: =(E79/F79)*L79 -> 0 | AF79: =(E79/F79)*M79 -> 0 | AG79: =(E79/F79)*N79 -> 0 | AH79: =(E79/F79)*O79 -> 0 | AI79: =(E79/F79)*P79 -> 0 | AJ79: =(E79/F79)*Q79 -> 0 | AK79: =(E79/F79)*R79 -> 22275 | AL79: =(E79/F79)*S79 -> 30000 | AM79: =SUM(AC79:AL79)*0.08 -> 184182 | AN79: =SUM(AC79:AM79) -> 2486457 | AO79: =AN79 -> 2486457 | AP79: =W79 -> CÁT LÁI | AQ79: LCL | AR79: 50H69350 | AS79: Từ Cảng CÁT LÁI đến BÀU XÉO, Đồng Nai | AT79: ADC
A80: PS254690 | B80: PS254690 | C80: 08SEA2507044 | D80: 45869 | E80: 1614.6 | F80: 1614.6 | G80: 6.215 | J80: =+IF(F77=0, _xleta.T, IF(F77<=1000, 1260000, IF(F77<=2000, 1430000, IF(F77<=3000, 2120000, IF(F77<=4500, 2230000, ff))))) -> 1430000 | K80: 990000 | L80: 5476760 | O80: 1989792 | R80: 24219 | S80: =+IF(F80<=2000, 30000, IF(F80<5000, 66000, ff)) -> 30000 | T80: =SUM(J80:S80)*0.08 -> 795261.68 | U80: =SUM(J80:T80) -> 10736033 | V80: =U80 -> 10736033 | W80: CÁT LÁI | X80: =A80 -> PS254690 | Y80: =B80 -> PS254690 | Z80: =D80 -> 45869 | AA80: =E80/F80*H80 -> 0 | AB80: =(E80/F80)*I80 -> 0 | AC80: =(E80/F80)*J80 -> 1430000 | AD80: =(E80/F80)*K80 -> 990000 | AE80: =(E80/F80)*L80 -> 5476760 | AF80: =(E80/F80)*M80 -> 0 | AG80: =(E80/F80)*N80 -> 0 | AH80: =(E80/F80)*O80 -> 1989792 | AI80: =(E80/F80)*P80 -> 0 | AJ80: =(E80/F80)*Q80 -> 0 | AK80: =(E80/F80)*R80 -> 24219 | AL80: =(E80/F80)*S80 -> 30000 | AM80: =SUM(AC80:AL80)*0.08 -> 795261.68 | AN80: =SUM(AC80:AM80) -> 10736033 | AO80: =AN80 -> 10736033 | AP80: =W80 -> CÁT LÁI | AQ80: LCL | AR80: 50H69104 | AS80: Từ Cảng CÁT LÁI đến BÀU XÉO, Đồng Nai | AT80: ADC
A81: PS254718 | B81: 1817727374 | C81: CEI228713 | D81: 45869 | E81: 365 | F81: 365 | J81: =+IF(F81<=50,1060000, IF(F81<=200, 1210000, IF(F81<=500, 1230000, IF(F81<=1000, 1440000, IF(F81<=2000, 1990000, IF(F81>2000, 1990000+(F81-2000)*1464)))))) -> 1230000 | K81: 990000 | P81: 1710720 | Q81: 520344 | T81: =SUM(J81:S81)*0.08 -> 356085.12 | U81: =SUM(J81:T81) -> 4807149.1 | V81: =U81 -> 4807149.1 | W81: TCS | X81: =A81 -> PS254718 | Y81: =B81 -> 1817727374 | Z81: =D81 -> 45869 | AA81: =E81/F81*H81 -> 0 | AB81: =(E81/F81)*I81 -> 0 | AC81: =(E81/F81)*J81 -> 1230000 | AD81: =(E81/F81)*K81 -> 990000 | AE81: =(E81/F81)*L81 -> 0 | AF81: =(E81/F81)*M81 -> 0 | AG81: =(E81/F81)*N81 -> 0 | AH81: =(E81/F81)*O81 -> 0 | AI81: =(E81/F81)*P81 -> 1710720 | AJ81: =(E81/F81)*Q81 -> 520344 | AK81: =(E81/F81)*R81 -> 0 | AL81: =(E81/F81)*S81 -> 0 | AM81: =SUM(AC81:AL81)*0.08 -> 356085.12 | AN81: =SUM(AC81:AM81) -> 4807149.1 | AO81: =AN81 -> 4807149.1 | AP81: =W81 -> TCS | AQ81: AIR | AR81: 50H70505 | AS81: Từ Kho TCS, Hồ Chí Minh đến Bàu Xéo, Hồ Chí Minh | AT81: ADC
A82: PS254726 | B82: PC250730VY | C82: JWE4151056 | D82: 45870 | E82: 19 | F82: 19 | J82: =+IF(F82<=50,1060000, IF(F82<=200, 1210000, IF(F82<=500, 1230000, IF(F82<=1000, 1440000, IF(F82<=2000, 1990000, IF(F82>2000, 1990000+(F82-2000)*1464)))))) -> 1060000 | K82: 990000 | P82: 589779 | Q82: 162000 | T82: =SUM(J82:S82)*0.08 -> 224142.32 | U82: =SUM(J82:T82) -> 3025921.3 | V82: =U82 -> 3025921.3 | W82: TCS | X82: =A82 -> PS254726 | Y82: =B82 -> PC250730VY | Z82: =D82 -> 45870 | AA82: =E82/F82*H82 -> 0 | AB82: =(E82/F82)*I82 -> 0 | AC82: =(E82/F82)*J82 -> 1060000 | AD82: =(E82/F82)*K82 -> 990000 | AE82: =(E82/F82)*L82 -> 0 | AF82: =(E82/F82)*M82 -> 0 | AG82: =(E82/F82)*N82 -> 0 | AH82: =(E82/F82)*O82 -> 0 | AI82: =(E82/F82)*P82 -> 589779 | AJ82: =(E82/F82)*Q82 -> 162000 | AK82: =(E82/F82)*R82 -> 0 | AL82: =(E82/F82)*S82 -> 0 | AM82: =SUM(AC82:AL82)*0.08 -> 224142.32 | AN82: =SUM(AC82:AM82) -> 3025921.3 | AO82: =AN82 -> 3025921.3 | AP82: =W82 -> TCS | AQ82: AIR | AR82: 50H69350 | AS82: Từ Kho TCS, Hồ Chí Minh đến Bàu Xéo, Hồ Chí Minh | AT82: ADC
A83: PS254727 | B83: PC2507302VY | C83: JWE4151057 | D83: 45870 | E83: 1 | F83: 1 | J83: =+IF(F83<=50,1060000, IF(F83<=200, 1210000, IF(F83<=500, 1230000, IF(F83<=1000, 1440000, IF(F83<=2000, 1990000, IF(F83>2000, 1990000+(F83-2000)*1464)))))) -> 1060000 | K83: 990000 | P83: 563386 | Q83: 162000 | T83: =SUM(J83:S83)*0.08 -> 222030.88 | U83: =SUM(J83:T83) -> 2997416.9 | V83: =U83 -> 2997416.9 | W83: TCS | X83: =A83 -> PS254727 | Y83: =B83 -> PC2507302VY | Z83: =D83 -> 45870 | AA83: =E83/F83*H83 -> 0 | AB83: =(E83/F83)*I83 -> 0 | AC83: =(E83/F83)*J83 -> 1060000 | AD83: =(E83/F83)*K83 -> 990000 | AE83: =(E83/F83)*L83 -> 0 | AF83: =(E83/F83)*M83 -> 0 | AG83: =(E83/F83)*N83 -> 0 | AH83: =(E83/F83)*O83 -> 0 | AI83: =(E83/F83)*P83 -> 563386 | AJ83: =(E83/F83)*Q83 -> 162000 | AK83: =(E83/F83)*R83 -> 0 | AL83: =(E83/F83)*S83 -> 0 | AM83: =SUM(AC83:AL83)*0.08 -> 222030.88 | AN83: =SUM(AC83:AM83) -> 2997416.9 | AO83: =AN83 -> 2997416.9 | AP83: =W83 -> TCS | AQ83: AIR | AR83: 50H69350 | AS83: Từ Kho TCS, Hồ Chí Minh đến Bàu Xéo, Hồ Chí Minh | AT83: ADC
A84: PS254667 | B84: DSHK2025071701 | C84: 20SEA25070161 | D84: 45870 | E84: 175 | F84: 175 | G84: 0.243 | J84: =+IF(F81=0, _xleta.T, IF(F81<=1000, 1260000, IF(F81<=2000, 1430000, IF(F81<=3000, 2120000, IF(F81<=4500, 2230000, ff))))) -> 1260000 | K84: 990000 | L84: 882533 | O84: 1850472 | R84: 2625 | S84: =+IF(F84<=2000, 30000, IF(F84<5000, 66000, ff)) -> 30000 | T84: =SUM(J84:S84)*0.08 -> 401250.4 | U84: =SUM(J84:T84) -> 5416880.4 | V84: =U84 -> 5416880.4 | W84: CÁT LÁI | X84: =A84 -> PS254667 | Y84: =B84 -> DSHK2025071701 | Z84: =D84 -> 45870 | AA84: =E84/F84*H84 -> 0 | AB84: =(E84/F84)*I84 -> 0 | AC84: =(E84/F84)*J84 -> 1260000 | AD84: =(E84/F84)*K84 -> 990000 | AE84: =(E84/F84)*L84 -> 882533 | AF84: =(E84/F84)*M84 -> 0 | AG84: =(E84/F84)*N84 -> 0 | AH84: =(E84/F84)*O84 -> 1850472 | AI84: =(E84/F84)*P84 -> 0 | AJ84: =(E84/F84)*Q84 -> 0 | AK84: =(E84/F84)*R84 -> 2625 | AL84: =(E84/F84)*S84 -> 30000 | AM84: =SUM(AC84:AL84)*0.08 -> 401250.4 | AN84: =SUM(AC84:AM84) -> 5416880.4 | AO84: =AN84 -> 5416880.4 | AP84: =W84 -> CÁT LÁI | AQ84: LCL | AR84: 50H24363 | AS84: Từ Cảng CÁT LÁI đến BÀU XÉO, Đồng Nai | AT84: ADC
A85: PS254666 | B85: DJL250718026 | C85: 20SEA25070162 | D85: 45870 | E85: 167.4 | F85: 167.4 | G85: 0.48 | J85: =+IF(F82=0, _xleta.T, IF(F82<=1000, 1260000, IF(F82<=2000, 1430000, IF(F82<=3000, 2120000, IF(F82<=4500, 2230000, ff))))) -> 1260000 | K85: 990000 | L85: 882533 | O85: 1850472 | R85: 2511 | S85: =+IF(F85<=2000, 30000, IF(F85<5000, 66000, ff)) -> 30000 | T85: =SUM(J85:S85)*0.08 -> 401241.28 | U85: =SUM(J85:T85) -> 5416757.3 | V85: =U85 -> 5416757.3 | W85: CÁT LÁI | X85: =A85 -> PS254666 | Y85: =B85 -> DJL250718026 | Z85: =D85 -> 45870 | AA85: =E85/F85*H85 -> 0 | AB85: =(E85/F85)*I85 -> 0 | AC85: =(E85/F85)*J85 -> 1260000 | AD85: =(E85/F85)*K85 -> 990000 | AE85: =(E85/F85)*L85 -> 882533 | AF85: =(E85/F85)*M85 -> 0 | AG85: =(E85/F85)*N85 -> 0 | AH85: =(E85/F85)*O85 -> 1850472 | AI85: =(E85/F85)*P85 -> 0 | AJ85: =(E85/F85)*Q85 -> 0 | AK85: =(E85/F85)*R85 -> 2511 | AL85: =(E85/F85)*S85 -> 30000 | AM85: =SUM(AC85:AL85)*0.08 -> 401241.28 | AN85: =SUM(AC85:AM85) -> 5416757.3 | AO85: =AN85 -> 5416757.3 | AP85: =W85 -> CÁT LÁI | AQ85: LCL | AR85: 50H69559 | AS85: Từ Cảng CÁT LÁI đến BÀU XÉO, Đồng Nai | AT85: ADC
A86: PS254636 | B86: PS254636 | C86: 08SEA2507059 | D86: 45870 | E86: 369.8 | F86: 369.8 | G86: 1.531 | J86: =+IF(F83=0, _xleta.T, IF(F83<=1000, 1260000, IF(F83<=2000, 1430000, IF(F83<=3000, 2120000, IF(F83<=4500, 2230000, ff))))) -> 1260000 | K86: 990000 | L86: 1348567 | O86: 1989036 | Q86: 11782 | R86: 5547 | S86: =+IF(F86<=2000, 30000, IF(F86<5000, 66000, ff)) -> 30000 | T86: =SUM(J86:S86)*0.08 -> 450794.56 | U86: =SUM(J86:T86) -> 6085726.6 | V86: =U86 -> 6085726.6 | W86: CÁT LÁI | X86: =A86 -> PS254636 | Y86: =B86 -> PS254636 | Z86: =D86 -> 45870 | AA86: =E86/F86*H86 -> 0 | AB86: =(E86/F86)*I86 -> 0 | AC86: =(E86/F86)*J86 -> 1260000 | AD86: =(E86/F86)*K86 -> 990000 | AE86: =(E86/F86)*L86 -> 1348567 | AF86: =(E86/F86)*M86 -> 0 | AG86: =(E86/F86)*N86 -> 0 | AH86: =(E86/F86)*O86 -> 1989036 | AI86: =(E86/F86)*P86 -> 0 | AJ86: =(E86/F86)*Q86 -> 11782 | AK86: =(E86/F86)*R86 -> 5547 | AL86: =(E86/F86)*S86 -> 30000 | AM86: =SUM(AC86:AL86)*0.08 -> 450794.56 | AN86: =SUM(AC86:AM86) -> 6085726.6 | AO86: =AN86 -> 6085726.6 | AP86: =W86 -> CÁT LÁI | AQ86: LCL | AR86: 50H24363 | AS86: Từ Cảng CÁT LÁI đến BÀU XÉO, Đồng Nai | AT86: ADC
A87: PS254691 | B87: IE25070618 | C87: 08SEA2507073 | D87: 45870 | E87: 102 | F87: 102 | G87: 0.598 | J87: =+IF(F84=0, _xleta.T, IF(F84<=1000, 1260000, IF(F84<=2000, 1430000, IF(F84<=3000, 2120000, IF(F84<=4500, 2230000, ff))))) -> 1260000 | K87: 990000 | L87: 882533 | O87: 1992816 | R87: 1530 | S87: =+IF(F87<=2000, 30000, IF(F87<5000, 66000, ff)) -> 30000 | T87: =SUM(J87:S87)*0.08 -> 412550.32 | U87: =SUM(J87:T87) -> 5569429.3 | V87: =U87 -> 5569429.3 | W87: CÁT LÁI | X87: =A87 -> PS254691 | Y87: =B87 -> IE25070618 | Z87: =D87 -> 45870 | AA87: =E87/F87*H87 -> 0 | AB87: =(E87/F87)*I87 -> 0 | AC87: =(E87/F87)*J87 -> 1260000 | AD87: =(E87/F87)*K87 -> 990000 | AE87: =(E87/F87)*L87 -> 882533 | AF87: =(E87/F87)*M87 -> 0 | AG87: =(E87/F87)*N87 -> 0 | AH87: =(E87/F87)*O87 -> 1992816 | AI87: =(E87/F87)*P87 -> 0 | AJ87: =(E87/F87)*Q87 -> 0 | AK87: =(E87/F87)*R87 -> 1530 | AL87: =(E87/F87)*S87 -> 30000 | AM87: =SUM(AC87:AL87)*0.08 -> 412550.32 | AN87: =SUM(AC87:AM87) -> 5569429.3 | AO87: =AN87 -> 5569429.3 | AP87: =W87 -> CÁT LÁI | AQ87: LCL | AR87: 50H69559 | AS87: Từ Cảng CÁT LÁI đến BÀU XÉO, Đồng Nai | AT87: ADC
A88: PS254645 | B88: PS254645 | C88: MLHCM2507018 | D88: 45870 | E88: 3429.4 | F88: 3429.4 | G88: 7.616 | J88: =+IF(F85=0, _xleta.T, IF(F85<=1000, 1260000, IF(F85<=2000, 1430000, IF(F85<=3000, 2120000, IF(F85<=4500, 2230000, ff))))) -> 1260000 | K88: 990000 | R88: 51441 | S88: =+IF(F88<=2000, 30000, IF(F88<5000, 66000, ff)) -> 66000 | T88: =SUM(J88:S88)*0.08 -> 189395.28 | U88: =SUM(J88:T88) -> 2556836.3 | V88: =U88 -> 2556836.3 | W88: CÁT LÁI | X88: =A88 -> PS254645 | Y88: =B88 -> PS254645 | Z88: =D88 -> 45870 | AA88: =E88/F88*H88 -> 0 | AB88: =(E88/F88)*I88 -> 0 | AC88: =(E88/F88)*J88 -> 1260000 | AD88: =(E88/F88)*K88 -> 990000 | AE88: =(E88/F88)*L88 -> 0 | AF88: =(E88/F88)*M88 -> 0 | AG88: =(E88/F88)*N88 -> 0 | AH88: =(E88/F88)*O88 -> 0 | AI88: =(E88/F88)*P88 -> 0 | AJ88: =(E88/F88)*Q88 -> 0 | AK88: =(E88/F88)*R88 -> 51441 | AL88: =(E88/F88)*S88 -> 66000 | AM88: =SUM(AC88:AL88)*0.08 -> 189395.28 | AN88: =SUM(AC88:AM88) -> 2556836.3 | AO88: =AN88 -> 2556836.3 | AP88: =W88 -> CÁT LÁI | AQ88: LCL | AR88: 50H24363 | AS88: Từ Cảng CÁT LÁI đến BÀU XÉO, Đồng Nai | AT88: ADC
A89: PS254722 | B89: 1004/2025 | C89: MLHCM2507019 | D89: 45870 | E89: 412.9 | F89: 412.9 | G89: 1.228 | J89: =+IF(F86=0, _xleta.T, IF(F86<=1000, 1260000, IF(F86<=2000, 1430000, IF(F86<=3000, 2120000, IF(F86<=4500, 2230000, ff))))) -> 1260000 | K89: 990000 | R89: 6194 | S89: =+IF(F89<=2000, 30000, IF(F89<5000, 66000, ff)) -> 30000 | T89: =SUM(J89:S89)*0.08 -> 182895.52 | U89: =SUM(J89:T89) -> 2469089.5 | V89: =U89 -> 2469089.5 | W89: CÁT LÁI | X89: =A89 -> PS254722 | Y89: =B89 -> 1004/2025 | Z89: =D89 -> 45870 | AA89: =E89/F89*H89 -> 0 | AB89: =(E89/F89)*I89 -> 0 | AC89: =(E89/F89)*J89 -> 1260000 | AD89: =(E89/F89)*K89 -> 990000 | AE89: =(E89/F89)*L89 -> 0 | AF89: =(E89/F89)*M89 -> 0 | AG89: =(E89/F89)*N89 -> 0 | AH89: =(E89/F89)*O89 -> 0 | AI89: =(E89/F89)*P89 -> 0 | AJ89: =(E89/F89)*Q89 -> 0 | AK89: =(E89/F89)*R89 -> 6194 | AL89: =(E89/F89)*S89 -> 30000 | AM89: =SUM(AC89:AL89)*0.08 -> 182895.52 | AN89: =SUM(AC89:AM89) -> 2469089.5 | AO89: =AN89 -> 2469089.5 | AP89: =W89 -> CÁT LÁI | AQ89: LCL | AR89: 50H69559 | AS89: Từ Cảng CÁT LÁI đến BÀU XÉO, Đồng Nai | AT89: ADC
A90: PS254664 | B90: APSV0201021 | C90: HPSCL25071565 | D90: 45870 | E90: 2440 | F90: 2440 | G90: 2.11 | J90: =+IF(F87=0, _xleta.T, IF(F87<=1000, 1260000, IF(F87<=2000, 1430000, IF(F87<=3000, 2120000, IF(F87<=4500, 2230000, ff))))) -> 1260000 | K90: 990000 | L90: 2292307.6 | M90: 555710.76 | N90: 555710.76 | O90: 711720 | P90: 996408 | R90: 36600 | S90: =+IF(F90<=2000, 30000, IF(F90<5000, 66000, ff)) -> 66000 | T90: =SUM(J90:S90)*0.08 -> 597156.57 | U90: =SUM(J90:T90) -> 8061613.6 | V90: =U90 -> 8061613.6 | W90: CÁT LÁI | X90: =A90 -> PS254664 | Y90: =B90 -> APSV0201021 | Z90: =D90 -> 45870 | AA90: =E90/F90*H90 -> 0 | AB90: =(E90/F90)*I90 -> 0 | AC90: =(E90/F90)*J90 -> 1260000 | AD90: =(E90/F90)*K90 -> 990000 | AE90: =(E90/F90)*L90 -> 2292307.6 | AF90: =(E90/F90)*M90 -> 555710.76 | AG90: =(E90/F90)*N90 -> 555710.76 | AH90: =(E90/F90)*O90 -> 711720 | AI90: =(E90/F90)*P90 -> 996408 | AJ90: =(E90/F90)*Q90 -> 0 | AK90: =(E90/F90)*R90 -> 36600 | AL90: =(E90/F90)*S90 -> 66000 | AM90: =SUM(AC90:AL90)*0.08 -> 597156.57 | AN90: =SUM(AC90:AM90) -> 8061613.6 | AO90: =AN90 -> 8061613.6 | AP90: =W90 -> CÁT LÁI | AQ90: LCL | AR90: 50H69181 | AS90: Từ Cảng CÁT LÁI đến BÀU XÉO, Đồng Nai | AT90: ADC
A91: PS254655 | B91: OR20250712 | C91: HTHC25072425 | D91: 45870 | E91: 125 | F91: 125 | G91: 0.2 | J91: =+IF(F88=0, _xleta.T, IF(F88<=1000, 1260000, IF(F88<=2000, 1430000, IF(F88<=3000, 2120000, IF(F88<=4500, 2230000, ff))))) -> 2230000 | K91: 990000 | L91: 4555008 | M91: 1423440 | N91: 2277504 | O91: 711720 | P91: 711720 | R91: 1875 | S91: =+IF(F91<=2000, 30000, IF(F91<5000, 66000, ff)) -> 30000 | T91: =SUM(J91:S91)*0.08 -> 1034501.4 | U91: =SUM(J91:T91) -> 13965768 | V91: =U91 -> 13965768 | W91: CÁT LÁI | X91: =A91 -> PS254655 | Y91: =B91 -> OR20250712 | Z91: =D91 -> 45870 | AA91: =E91/F91*H91 -> 0 | AB91: =(E91/F91)*I91 -> 0 | AC91: =(E91/F91)*J91 -> 2230000 | AD91: =(E91/F91)*K91 -> 990000 | AE91: =(E91/F91)*L91 -> 4555008 | AF91: =(E91/F91)*M91 -> 1423440 | AG91: =(E91/F91)*N91 -> 2277504 | AH91: =(E91/F91)*O91 -> 711720 | AI91: =(E91/F91)*P91 -> 711720 | AJ91: =(E91/F91)*Q91 -> 0 | AK91: =(E91/F91)*R91 -> 1875 | AL91: =(E91/F91)*S91 -> 30000 | AM91: =SUM(AC91:AL91)*0.08 -> 1034501.4 | AN91: =SUM(AC91:AM91) -> 13965768 | AO91: =AN91 -> 13965768 | AP91: =W91 -> CÁT LÁI | AQ91: LCL | AR91: 50H69181 | AS91: Từ Cảng CÁT LÁI đến BÀU XÉO, Đồng Nai | AT91: ADC
A92: PS254620 | B92: 2510/SLTWPS | C92: 112500035511849 | D92: 45870 | E92: 3329 | F92: 3329 | J92: =+IF(F89=0, _xleta.T, IF(F89<=1000, 1260000, IF(F89<=2000, 1430000, IF(F89<=3000, 2120000, IF(F89<=4500, 2230000, ff))))) -> 1260000 | K92: 990000 | Q92: 594000 | R92: 49935 | S92: =+IF(F92<=2000, 30000, IF(F92<5000, 66000, ff)) -> 66000 | T92: =SUM(J92:S92)*0.08 -> 236794.8 | U92: =SUM(J92:T92) -> 3196729.8 | V92: =U92 -> 3196729.8 | W92: KNQ TÂN THUẬN | X92: =A92 -> PS254620 | Y92: =B92 -> 2510/SLTWPS | Z92: =D92 -> 45870 | AA92: =E92/F92*H92 -> 0 | AB92: =(E92/F92)*I92 -> 0 | AC92: =(E92/F92)*J92 -> 1260000 | AD92: =(E92/F92)*K92 -> 990000 | AE92: =(E92/F92)*L92 -> 0 | AF92: =(E92/F92)*M92 -> 0 | AG92: =(E92/F92)*N92 -> 0 | AH92: =(E92/F92)*O92 -> 0 | AI92: =(E92/F92)*P92 -> 0 | AJ92: =(E92/F92)*Q92 -> 594000 | AK92: =(E92/F92)*R92 -> 49935 | AL92: =(E92/F92)*S92 -> 66000 | AM92: =SUM(AC92:AL92)*0.08 -> 236794.8 | AN92: =SUM(AC92:AM92) -> 3196729.8 | AO92: =AN92 -> 3196729.8 | AP92: =W92 -> KNQ TÂN THUẬN | AQ92: LCL | AR92: 60H11265 | AS92: Từ kho Tân Thuận đến Bàu Xéo, Đồng Nai | AT92: ADC
A93: PS254693 | B93: EX25070145 | C93: 6865623402 | D93: 45870 | E93: 22.1 | F93: 22.1 | J93: =+IF(F93<=50,1060000, IF(F93<=200, 1210000, IF(F93<=500, 1230000, IF(F93<=1000, 1440000, IF(F93<=2000, 1990000, IF(F93>2000, 1990000+(F93-2000)*1464)))))) -> 1060000 | K93: 600000 | T93: =SUM(J93:S93)*0.08 -> 132800 | U93: =SUM(J93:T93) -> 1792800 | V93: =U93 -> 1792800 | W93: DHL | X93: =A93 -> PS254693 | Y93: =B93 -> EX25070145 | Z93: =D93 -> 45870 | AA93: =E93/F93*H93 -> 0 | AB93: =(E93/F93)*I93 -> 0 | AC93: =(E93/F93)*J93 -> 1060000 | AD93: =(E93/F93)*K93 -> 600000 | AE93: =(E93/F93)*L93 -> 0 | AF93: =(E93/F93)*M93 -> 0 | AG93: =(E93/F93)*N93 -> 0 | AH93: =(E93/F93)*O93 -> 0 | AI93: =(E93/F93)*P93 -> 0 | AJ93: =(E93/F93)*Q93 -> 0 | AK93: =(E93/F93)*R93 -> 0 | AL93: =(E93/F93)*S93 -> 0 | AM93: =SUM(AC93:AL93)*0.08 -> 132800 | AN93: =SUM(AC93:AM93) -> 1792800 | AO93: =AN93 -> 1792800 | AP93: =W93 -> DHL | AQ93: EXP | AR93: 51D17284 | AS93: Từ Kho DHL, Hồ Chí Minh đến Bàu Xéo, Đồng Nai | AT93: ADC
A94: PS254694 | B94: CHDG2025072901 | C94: 4743339521 | D94: 45870 | E94: 4.7 | F94: 4.7 | J94: =+IF(F94<=50,1060000, IF(F94<=200, 1210000, IF(F94<=500, 1230000, IF(F94<=1000, 1440000, IF(F94<=2000, 1990000, IF(F94>2000, 1990000+(F94-2000)*1464)))))) -> 1060000 | K94: 600000 | T94: =SUM(J94:S94)*0.08 -> 132800 | U94: =SUM(J94:T94) -> 1792800 | V94: =U94 -> 1792800 | W94: DHL | X94: =A94 -> PS254694 | Y94: =B94 -> CHDG2025072901 | Z94: =D94 -> 45870 | AA94: =E94/F94*H94 -> 0 | AB94: =(E94/F94)*I94 -> 0 | AC94: =(E94/F94)*J94 -> 1060000 | AD94: =(E94/F94)*K94 -> 600000 | AE94: =(E94/F94)*L94 -> 0 | AF94: =(E94/F94)*M94 -> 0 | AG94: =(E94/F94)*N94 -> 0 | AH94: =(E94/F94)*O94 -> 0 | AI94: =(E94/F94)*P94 -> 0 | AJ94: =(E94/F94)*Q94 -> 0 | AK94: =(E94/F94)*R94 -> 0 | AL94: =(E94/F94)*S94 -> 0 | AM94: =SUM(AC94:AL94)*0.08 -> 132800 | AN94: =SUM(AC94:AM94) -> 1792800 | AO94: =AN94 -> 1792800 | AP94: =W94 -> DHL | AQ94: EXP | AR94: 51D17284 | AS94: Từ Kho DHL, Hồ Chí Minh đến Bàu Xéo, Đồng Nai | AT94: ADC
A95: PS254721 | B95: IE20250728075 | C95: 7673307865 | D95: 45870 | E95: 20 | F95: 20 | J95: =+IF(F95<=50,1060000, IF(F95<=200, 1210000, IF(F95<=500, 1230000, IF(F95<=1000, 1440000, IF(F95<=2000, 1990000, IF(F95>2000, 1990000+(F95-2000)*1464)))))) -> 1060000 | K95: 600000 | T95: =SUM(J95:S95)*0.08 -> 132800 | U95: =SUM(J95:T95) -> 1792800 | V95: =U95 -> 1792800 | W95: DHL | X95: =A95 -> PS254721 | Y95: =B95 -> IE20250728075 | Z95: =D95 -> 45870 | AA95: =E95/F95*H95 -> 0 | AB95: =(E95/F95)*I95 -> 0 | AC95: =(E95/F95)*J95 -> 1060000 | AD95: =(E95/F95)*K95 -> 600000 | AE95: =(E95/F95)*L95 -> 0 | AF95: =(E95/F95)*M95 -> 0 | AG95: =(E95/F95)*N95 -> 0 | AH95: =(E95/F95)*O95 -> 0 | AI95: =(E95/F95)*P95 -> 0 | AJ95: =(E95/F95)*Q95 -> 0 | AK95: =(E95/F95)*R95 -> 0 | AL95: =(E95/F95)*S95 -> 0 | AM95: =SUM(AC95:AL95)*0.08 -> 132800 | AN95: =SUM(AC95:AM95) -> 1792800 | AO95: =AN95 -> 1792800 | AP95: =W95 -> DHL | AQ95: EXP | AR95: 51D17284 | AS95: Từ Kho DHL, Hồ Chí Minh đến Bàu Xéo, Đồng Nai | AT95: ADC
A96: PS254695 | B96: 25ESMVNPJ511 | C96: 7672546615 | D96: 45870 | E96: 0.5 | F96: 0.5 | J96: =+IF(F96<=50,1060000, IF(F96<=200, 1210000, IF(F96<=500, 1230000, IF(F96<=1000, 1440000, IF(F96<=2000, 1990000, IF(F96>2000, 1990000+(F96-2000)*1464)))))) -> 1060000 | K96: 600000 | T96: =SUM(J96:S96)*0.08 -> 132800 | U96: =SUM(J96:T96) -> 1792800 | V96: =U96 -> 1792800 | W96: DHL | X96: =A96 -> PS254695 | Y96: =B96 -> 25ESMVNPJ511 | Z96: =D96 -> 45870 | AA96: =E96/F96*H96 -> 0 | AB96: =(E96/F96)*I96 -> 0 | AC96: =(E96/F96)*J96 -> 1060000 | AD96: =(E96/F96)*K96 -> 600000 | AE96: =(E96/F96)*L96 -> 0 | AF96: =(E96/F96)*M96 -> 0 | AG96: =(E96/F96)*N96 -> 0 | AH96: =(E96/F96)*O96 -> 0 | AI96: =(E96/F96)*P96 -> 0 | AJ96: =(E96/F96)*Q96 -> 0 | AK96: =(E96/F96)*R96 -> 0 | AL96: =(E96/F96)*S96 -> 0 | AM96: =SUM(AC96:AL96)*0.08 -> 132800 | AN96: =SUM(AC96:AM96) -> 1792800 | AO96: =AN96 -> 1792800 | AP96: =W96 -> DHL | AQ96: EXP | AR96: 51D17284 | AS96: Từ Kho DHL, Hồ Chí Minh đến Bàu Xéo, Đồng Nai | AT96: ADC
A97: PS254751 | B97: T250730Y2 | C97: SPX2507038 | D97: 45871 | E97: 221 | F97: 221 | J97: =+IF(F97<=50,1060000, IF(F97<=200, 1210000, IF(F97<=500, 1230000, IF(F97<=1000, 1440000, IF(F97<=2000, 1990000, IF(F97>2000, 1990000+(F97-2000)*1464)))))) -> 1230000 | K97: 990000 | Q97: 315058 | T97: =SUM(J97:S97)*0.08 -> 202804.64 | U97: =SUM(J97:T97) -> 2737862.6 | V97: =U97 -> 2737862.6 | W97: TCS | X97: =A97 -> PS254751 | Y97: =B97 -> T250730Y2 | Z97: =D97 -> 45871 | AA97: =E97/F97*H97 -> 0 | AB97: =(E97/F97)*I97 -> 0 | AC97: =(E97/F97)*J97 -> 1230000 | AD97: =(E97/F97)*K97 -> 990000 | AE97: =(E97/F97)*L97 -> 0 | AF97: =(E97/F97)*M97 -> 0 | AG97: =(E97/F97)*N97 -> 0 | AH97: =(E97/F97)*O97 -> 0 | AI97: =(E97/F97)*P97 -> 0 | AJ97: =(E97/F97)*Q97 -> 315058 | AK97: =(E97/F97)*R97 -> 0 | AL97: =(E97/F97)*S97 -> 0 | AM97: =SUM(AC97:AL97)*0.08 -> 202804.64 | AN97: =SUM(AC97:AM97) -> 2737862.6 | AO97: =AN97 -> 2737862.6 | AP97: =W97 -> TCS | AQ97: AIR | AR97: 51D17284 | AS97: Từ Kho TCS, Hồ Chí Minh đến Bàu Xéo, Hồ Chí Minh | AT97: ADC
A98: PS254752 | B98: T250730Y4 | C98: SPX2507039 | D98: 45871 | E98: 7 | F98: 7 | J98: =+IF(F98<=50,1060000, IF(F98<=200, 1210000, IF(F98<=500, 1230000, IF(F98<=1000, 1440000, IF(F98<=2000, 1990000, IF(F98>2000, 1990000+(F98-2000)*1464)))))) -> 1060000 | K98: 990000 | Q98: 162000 | T98: =SUM(J98:S98)*0.08 -> 176960 | U98: =SUM(J98:T98) -> 2388960 | V98: =U98 -> 2388960 | W98: TCS | X98: =A98 -> PS254752 | Y98: =B98 -> T250730Y4 | Z98: =D98 -> 45871 | AA98: =E98/F98*H98 -> 0 | AB98: =(E98/F98)*I98 -> 0 | AC98: =(E98/F98)*J98 -> 1060000 | AD98: =(E98/F98)*K98 -> 990000 | AE98: =(E98/F98)*L98 -> 0 | AF98: =(E98/F98)*M98 -> 0 | AG98: =(E98/F98)*N98 -> 0 | AH98: =(E98/F98)*O98 -> 0 | AI98: =(E98/F98)*P98 -> 0 | AJ98: =(E98/F98)*Q98 -> 162000 | AK98: =(E98/F98)*R98 -> 0 | AL98: =(E98/F98)*S98 -> 0 | AM98: =SUM(AC98:AL98)*0.08 -> 176960 | AN98: =SUM(AC98:AM98) -> 2388960 | AO98: =AN98 -> 2388960 | AP98: =W98 -> TCS | AQ98: AIR | AR98: 51D17284 | AS98: Từ Kho TCS, Hồ Chí Minh đến Bàu Xéo, Hồ Chí Minh | AT98: ADC
A99: PS254756 | B99: PC2507312VY | C99: JWE4151066 | D99: 45871 | E99: 3 | F99: 3 | J99: =+IF(F99<=50,1060000, IF(F99<=200, 1210000, IF(F99<=500, 1230000, IF(F99<=1000, 1440000, IF(F99<=2000, 1990000, IF(F99>2000, 1990000+(F99-2000)*1464)))))) -> 1060000 | K99: 990000 | P99: 566269 | Q99: 162000 | T99: =SUM(J99:S99)*0.08 -> 222261.52 | U99: =SUM(J99:T99) -> 3000530.5 | V99: =U99 -> 3000530.5 | W99: TCS | X99: =A99 -> PS254756 | Y99: =B99 -> PC2507312VY | Z99: =D99 -> 45871 | AA99: =E99/F99*H99 -> 0 | AB99: =(E99/F99)*I99 -> 0 | AC99: =(E99/F99)*J99 -> 1060000 | AD99: =(E99/F99)*K99 -> 990000 | AE99: =(E99/F99)*L99 -> 0 | AF99: =(E99/F99)*M99 -> 0 | AG99: =(E99/F99)*N99 -> 0 | AH99: =(E99/F99)*O99 -> 0 | AI99: =(E99/F99)*P99 -> 566269 | AJ99: =(E99/F99)*Q99 -> 162000 | AK99: =(E99/F99)*R99 -> 0 | AL99: =(E99/F99)*S99 -> 0 | AM99: =SUM(AC99:AL99)*0.08 -> 222261.52 | AN99: =SUM(AC99:AM99) -> 3000530.5 | AO99: =AN99 -> 3000530.5 | AP99: =W99 -> TCS | AQ99: AIR | AR99: 51D17284 | AS99: Từ Kho TCS, Hồ Chí Minh đến Bàu Xéo, Hồ Chí Minh | AT99: ADC
A100: PS254757 | B100: G820250731 VY (B) | C100: JWE4151065 | D100: 45871 | E100: 10 | F100: 10 | J100: =+IF(F100<=50,1060000, IF(F100<=200, 1210000, IF(F100<=500, 1230000, IF(F100<=1000, 1440000, IF(F100<=2000, 1990000, IF(F100>2000, 1990000+(F100-2000)*1464)))))) -> 1060000 | K100: 990000 | P100: 576440 | Q100: 162000 | T100: =SUM(J100:S100)*0.08 -> 223075.2 | U100: =SUM(J100:T100) -> 3011515.2 | V100: =U100 -> 3011515.2 | W100: TCS | X100: =A100 -> PS254757 | Y100: =B100 -> G820250731 VY (B) | Z100: =D100 -> 45871 | AA100: =E100/F100*H100 -> 0 | AB100: =(E100/F100)*I100 -> 0 | AC100: =(E100/F100)*J100 -> 1060000 | AD100: =(E100/F100)*K100 -> 990000 | AE100: =(E100/F100)*L100 -> 0 | AF100: =(E100/F100)*M100 -> 0 | AG100: =(E100/F100)*N100 -> 0 | AH100: =(E100/F100)*O100 -> 0 | AI100: =(E100/F100)*P100 -> 576440 | AJ100: =(E100/F100)*Q100 -> 162000 | AK100: =(E100/F100)*R100 -> 0 | AL100: =(E100/F100)*S100 -> 0 | AM100: =SUM(AC100:AL100)*0.08 -> 223075.2 | AN100: =SUM(AC100:AM100) -> 3011515.2 | AO100: =AN100 -> 3011515.2 | AP100: =W100 -> TCS | AQ100: AIR | AR100: 51D17284 | AS100: Từ Kho TCS, Hồ Chí Minh đến Bàu Xéo, Hồ Chí Minh | AT100: ADC
...

Sheet LCL+LOCAL - IMPORT   (2)
A1: LCL + LOCAL
A2: No | B2: INVOICE No | C2: AWB,B/L No | D2: DATE C/D | E2: Declaration | F2: Number of CD | G2: KGS | H2: KGS OF BL | I2: CBM | J2: FREIGHT AIR | K2: FREIGHT SEA | L2: TRUCKING FEE | M2: SERVICE FEE | N2: CFS | O2: CIC | P2: THC | Q2: D/O | R2: HANDLING | S2: STORAGE | T2: CSHT | U2: TOLL FEE | V2: INCURRED | W2: VAT PASS THROUGH | X2: CLEARING EXPENSE | Y2: TOTAL | Z2: SỐ XE | AA2: PORT | AB2: No | AC2: INVOICE No | AD2: DATE | AE2: FREIGHT AIR PER P/L | AF2: FREIGHT SEA PER P/L | AG2: TRUCKING FEE | AH2: SERVICE FEE | AI2: CFS | AJ2: CIC | AK2: THC | AL2: D/O | AM2: HANDLING | AN2: STORAGE | AO2: CSHT | AP2: TOLL FEE | AQ2: INCURRED | AR2: VAT PASS THROUGH | AS2: CLEARING EXPENSE PER P/L | AT2: TOTAL | AU2: PORT | AW2: SỐ JOB FILE OF ADC | AX2: Nơi đi - Nơi đến | AY2: NGÀY GIAO HÀNG
A3: PS260717 | B3: EX-26010076 | C3: SE26010032/003 | D3: 46051 | E3: 107938104260 | F3: 1 | G3: 194.46 | H3: 194.46 | I3: 0.832 | L3: {=IF(H3=0, _xleta.T, IF(H3<=1000, 1290000, IF(H3<=2000, 1460000, IF(H3<=3000, 2186000, IF(H3<=5000, 2296000, ff)))))} -> 1290000 | M3: 940500 | Z3: 50H-69181 | AA3: CÁT LÁI | AB3: =A3 -> PS260717 | AC3: =B3 -> EX-26010076 | AD3: =D3 -> 46051 | AE3: =G3/H3*J3 -> 0 | AF3: =(G3/H3)*K3 -> 0 | AG3: =(G3/H3)*L3 -> 1290000 | AH3: =(G3/H3)*M3 -> 940500 | AI3: =(G3/H3)*N3 -> 0 | AJ3: =(G3/H3)*O3 -> 0 | AK3: =(G3/H3)*P3 -> 0 | AL3: =(G3/H3)*Q3 -> 0 | AM3: =(G3/H3)*R3 -> 0 | AN3: =(G3/H3)*S3 -> 0 | AO3: =(G3/H3)*T3 -> 0 | AP3: =(G3/H3)*U3 -> 0 | AQ3: =(G3/H3)*V3 -> 0 | AR3: =SUM(AG3:AQ3)*0.08 -> 178440 | AS3: =SUM(AG3:AR3) -> 2408940 | AT3: =AS3 -> 2408940 | AU3: =AA3 -> CÁT LÁI | AV3: LCL | AW3: ADCDNB-26.01-004426 | AX3: , từ Cảng Cát Lái đến KCN Bàu Xéo, Đồng Nai | AY3: 46055 | AZ3: 50H-69181 50H-66757 | BA3: 2 X 5MT
A4: PS260508 | B4: OHTY260012 | C4: 08SEA2601035 | D4: 46052 | E4: 107942880510 | F4: 1 | G4: 666 | H4: 666 | I4: 5.032 | L4: {=IF(H4=0, _xleta.T, IF(H4<=1000, 1290000, IF(H4<=2000, 1460000, IF(H4<=3000, 2186000, IF(H4<=5000, 2296000, ff)))))} -> 1290000 | M4: 940500 | AA4: CÁT LÁI | AB4: =A4 -> PS260508 | AC4: =B4 -> OHTY260012 | AD4: =D4 -> 46052 | AE4: =G4/H4*J4 -> 0 | AF4: =(G4/H4)*K4 -> 0 | AG4: =(G4/H4)*L4 -> 1290000 | AH4: =(G4/H4)*M4 -> 940500 | AI4: =(G4/H4)*N4 -> 0 | AJ4: =(G4/H4)*O4 -> 0 | AK4: =(G4/H4)*P4 -> 0 | AL4: =(G4/H4)*Q4 -> 0 | AM4: =(G4/H4)*R4 -> 0 | AN4: =(G4/H4)*S4 -> 0 | AO4: =(G4/H4)*T4 -> 0 | AP4: =(G4/H4)*U4 -> 0 | AQ4: =(G4/H4)*V4 -> 0 | AR4: =SUM(AG4:AQ4)*0.08 -> 178440 | AS4: =SUM(AG4:AR4) -> 2408940 | AT4: =AS4 -> 2408940 | AU4: =AA4 -> CÁT LÁI | AV4: LCL | AW4: ADCDNB-26.01-004616 | AX4: , từ Cảng Cát Lái đến KCN Bàu Xéo, Đồng Nai | AY4: 46055
A5: PS260746 | B5: 5204969 | C5: S02096936 | D5: 46051 | E5: 107940077120 | F5: 1 | G5: 241.98 | H5: 241.98 | I5: 1.474 | L5: {=IF(H5=0, _xleta.T, IF(H5<=1000, 1290000, IF(H5<=2000, 1460000, IF(H5<=3000, 2186000, IF(H5<=5000, 2296000, ff)))))} -> 1290000 | M5: 940500 | Z5: 50H-66757 | AA5: CÁT LÁI | AB5: =A5 -> PS260746 | AC5: =B5 -> 5204969 | AD5: =D5 -> 46051 | AE5: =G5/H5*J5 -> 0 | AF5: =(G5/H5)*K5 -> 0 | AG5: =(G5/H5)*L5 -> 1290000 | AH5: =(G5/H5)*M5 -> 940500 | AI5: =(G5/H5)*N5 -> 0 | AJ5: =(G5/H5)*O5 -> 0 | AK5: =(G5/H5)*P5 -> 0 | AL5: =(G5/H5)*Q5 -> 0 | AM5: =(G5/H5)*R5 -> 0 | AN5: =(G5/H5)*S5 -> 0 | AO5: =(G5/H5)*T5 -> 0 | AP5: =(G5/H5)*U5 -> 0 | AQ5: =(G5/H5)*V5 -> 0 | AR5: =SUM(AG5:AQ5)*0.08 -> 178440 | AS5: =SUM(AG5:AR5) -> 2408940 | AT5: =AS5 -> 2408940 | AU5: =AA5 -> CÁT LÁI | AV5: LCL | AW5: ADCDNB-26.01-004617 | AX5: , từ Cảng Cát Lái đến KCN Bàu Xéo, Đồng Nai | AY5: 46055
A6: PS260737 | B6: 5196209 | C6: CGH/HCM-018/26 | D6: 46052 | E6: 107943625640 | F6: 1 | G6: 191.6 | H6: 191.6 | I6: 0.86 | L6: {=IF(H6=0, _xleta.T, IF(H6<=1000, 1290000, IF(H6<=2000, 1460000, IF(H6<=3000, 2186000, IF(H6<=5000, 2296000, ff)))))} -> 1290000 | M6: 940500 | AA6: CÁT LÁI | AB6: =A6 -> PS260737 | AC6: =B6 -> 5196209 | AD6: =D6 -> 46052 | AE6: =G6/H6*J6 -> 0 | AF6: =(G6/H6)*K6 -> 0 | AG6: =(G6/H6)*L6 -> 1290000 | AH6: =(G6/H6)*M6 -> 940500 | AI6: =(G6/H6)*N6 -> 0 | AJ6: =(G6/H6)*O6 -> 0 | AK6: =(G6/H6)*P6 -> 0 | AL6: =(G6/H6)*Q6 -> 0 | AM6: =(G6/H6)*R6 -> 0 | AN6: =(G6/H6)*S6 -> 0 | AO6: =(G6/H6)*T6 -> 0 | AP6: =(G6/H6)*U6 -> 0 | AQ6: =(G6/H6)*V6 -> 0 | AR6: =SUM(AG6:AQ6)*0.08 -> 178440 | AS6: =SUM(AG6:AR6) -> 2408940 | AT6: =AS6 -> 2408940 | AU6: =AA6 -> CÁT LÁI | AV6: LCL | AW6: ADCDNB-26.01-004619 | AX6: , từ Cảng Cát Lái đến KCN Bàu Xéo, Đồng Nai | AY6: 46055
A7: PS260716 | B7: PS26-716 | C7: CGH/HCM-018/26A | D7: 46052 | E7: 107943647930 | F7: 1 | G7: 792.5 | H7: 792.5 | I7: 1.91 | L7: {=IF(H7=0, _xleta.T, IF(H7<=1000, 1290000, IF(H7<=2000, 1460000, IF(H7<=3000, 2186000, IF(H7<=5000, 2296000, ff)))))} -> 1290000 | M7: 940500 | Z7: 50H-69181 | AA7: CÁT LÁI | AB7: =A7 -> PS260716 | AC7: =B7 -> PS26-716 | AD7: =D7 -> 46052 | AE7: =G7/H7*J7 -> 0 | AF7: =(G7/H7)*K7 -> 0 | AG7: =(G7/H7)*L7 -> 1290000 | AH7: =(G7/H7)*M7 -> 940500 | AI7: =(G7/H7)*N7 -> 0 | AJ7: =(G7/H7)*O7 -> 0 | AK7: =(G7/H7)*P7 -> 0 | AL7: =(G7/H7)*Q7 -> 0 | AM7: =(G7/H7)*R7 -> 0 | AN7: =(G7/H7)*S7 -> 0 | AO7: =(G7/H7)*T7 -> 0 | AP7: =(G7/H7)*U7 -> 0 | AQ7: =(G7/H7)*V7 -> 0 | AR7: =SUM(AG7:AQ7)*0.08 -> 178440 | AS7: =SUM(AG7:AR7) -> 2408940 | AT7: =AS7 -> 2408940 | AU7: =AA7 -> CÁT LÁI | AV7: LCL | AW7: ADCDNB-26.01-004636 | AX7: , từ Cảng Cát Lái đến KCN Bàu Xéo, Đồng Nai | AY7: 46055
A8: PS260742 | B8: PS26-742 | C8: CGH/HCM-018/26B | D8: 46052 | E8: 107943576750 | F8: 1 | G8: 2511 | H8: 2511 | I8: 6.38 | L8: {=IF(H8=0, _xleta.T, IF(H8<=1000, 1290000, IF(H8<=2000, 1460000, IF(H8<=3000, 2186000, IF(H8<=5000, 2296000, ff)))))} -> 2186000 | M8: 940500 | Z8: 50H-66757 | AA8: CÁT LÁI | AB8: =A8 -> PS260742 | AC8: =B8 -> PS26-742 | AD8: =D8 -> 46052 | AE8: =G8/H8*J8 -> 0 | AF8: =(G8/H8)*K8 -> 0 | AG8: =(G8/H8)*L8 -> 2186000 | AH8: =(G8/H8)*M8 -> 940500 | AI8: =(G8/H8)*N8 -> 0 | AJ8: =(G8/H8)*O8 -> 0 | AK8: =(G8/H8)*P8 -> 0 | AL8: =(G8/H8)*Q8 -> 0 | AM8: =(G8/H8)*R8 -> 0 | AN8: =(G8/H8)*S8 -> 0 | AO8: =(G8/H8)*T8 -> 0 | AP8: =(G8/H8)*U8 -> 0 | AQ8: =(G8/H8)*V8 -> 0 | AR8: =SUM(AG8:AQ8)*0.08 -> 250120 | AS8: =SUM(AG8:AR8) -> 3376620 | AT8: =AS8 -> 3376620 | AU8: =AA8 -> CÁT LÁI | AV8: LCL | AW8: ADCDNB-26.01-004637 | AX8: , từ Cảng Cát Lái đến KCN Bàu Xéo, Đồng Nai | AY8: 46055
A9: PS260768 | B9: 2603/SLTW-PS | C9: 112600036770481 | D9: 46052 | E9: 107944314110 | F9: 1 | G9: 7867 | H9: 7867 | L9: =2596000*2 -> 5192000 | M9: 940500 | Z9: 50E46443 60H11265 | AA9: TAN THUAN | AB9: =A9 -> PS260768 | AC9: =B9 -> 2603/SLTW-PS | AD9: =D9 -> 46052 | AE9: =G9/H9*J9 -> 0 | AF9: =(G9/H9)*K9 -> 0 | AG9: =(G9/H9)*L9 -> 5192000 | AH9: =(G9/H9)*M9 -> 940500 | AI9: =(G9/H9)*N9 -> 0 | AJ9: =(G9/H9)*O9 -> 0 | AK9: =(G9/H9)*P9 -> 0 | AL9: =(G9/H9)*Q9 -> 0 | AM9: =(G9/H9)*R9 -> 0 | AN9: =(G9/H9)*S9 -> 0 | AO9: =(G9/H9)*T9 -> 0 | AP9: =(G9/H9)*U9 -> 0 | AQ9: =(G9/H9)*V9 -> 0 | AR9: =SUM(AG9:AQ9)*0.08 -> 490600 | AS9: =SUM(AG9:AR9) -> 6623100 | AT9: =AS9 -> 6623100 | AU9: =AA9 -> TAN THUAN | AV9: LCL | AW9: ADCDNB-26.01-004627 | AX9: , từ Tân Thuận về KCN Bàu Xéo, Đồng Nai | AY9: 46055 | AZ9: 50E46443 60H11265 | BA9: 2 X 5MT
A10: PS260788 | B10: PC260130VY | C10: JWE5150187 | D10: 46055 | E10: 107946861300 | F10: 1 | G10: 17 | H10: 17 | L10: =IF(H10<=50,1060000, IF(H10<=200, 1210000, IF(H10<=500, 1230000, IF(H10<=1000, 1440000, IF(H10<=2000, 1990000, IF(H10>2000, 1990000+(H10-2000)*1464)))))) -> 1060000 | M10: 940500 | Z10: 50H69104 | AA10: TCS | AB10: =A10 -> PS260788 | AC10: =B10 -> PC260130VY | AD10: =D10 -> 46055 | AE10: =G10/H10*J10 -> 0 | AF10: =(G10/H10)*K10 -> 0 | AG10: =(G10/H10)*L10 -> 1060000 | AH10: =(G10/H10)*M10 -> 940500 | AI10: =(G10/H10)*N10 -> 0 | AJ10: =(G10/H10)*O10 -> 0 | AK10: =(G10/H10)*P10 -> 0 | AL10: =(G10/H10)*Q10 -> 0 | AM10: =(G10/H10)*R10 -> 0 | AN10: =(G10/H10)*S10 -> 0 | AO10: =(G10/H10)*T10 -> 0 | AP10: =(G10/H10)*U10 -> 0 | AQ10: =(G10/H10)*V10 -> 0 | AR10: =SUM(AG10:AQ10)*0.08 -> 160040 | AS10: =SUM(AG10:AR10) -> 2160540 | AT10: =AS10 -> 2160540 | AU10: =AA10 -> TCS | AV10: AIR | AW10: ADCDNB-26.01-004700 | AX10: , từ Kho TCS đến KCN Bàu Xéo , Đồng Nai | AY10: 46056 | AZ10: 50H69104 | BA10: 1 X 1MT
A11: PS260775 | B11: HH20260128001 | C11: 8704238410 | D11: 46052 | E11: 107944026410 | F11: 1 | G11: 5.7 | H11: 5.7 | M11: 570000 | AA11: DHL | AB11: =A11 -> PS260775 | AC11: =B11 -> HH20260128001 | AD11: =D11 -> 46052 | AE11: =G11/H11*J11 -> 0 | AF11: =(G11/H11)*K11 -> 0 | AG11: =(G11/H11)*L11 -> 0 | AH11: =(G11/H11)*M11 -> 570000 | AI11: =(G11/H11)*N11 -> 0 | AJ11: =(G11/H11)*O11 -> 0 | AK11: =(G11/H11)*P11 -> 0 | AL11: =(G11/H11)*Q11 -> 0 | AM11: =(G11/H11)*R11 -> 0 | AN11: =(G11/H11)*S11 -> 0 | AO11: =(G11/H11)*T11 -> 0 | AP11: =(G11/H11)*U11 -> 0 | AQ11: =(G11/H11)*V11 -> 0 | AR11: =SUM(AG11:AQ11)*0.08 -> 45600 | AS11: =SUM(AG11:AR11) -> 615600 | AT11: =AS11 -> 615600 | AU11: =AA11 -> DHL | AV11: EXP | AW11: ADCDNB-26.01-004630
A12: PS260772 | B12: EXD1-26-VY0127 | C12: 8704018536 | D12: 46053 | E12: 107946396610 | F12: 1 | G12: 19.5 | H12: 19.5 | M12: 570000 | AA12: DHL | AB12: =A12 -> PS260772 | AC12: =B12 -> EXD1-26-VY0127 | AD12: =D12 -> 46053 | AE12: =G12/H12*J12 -> 0 | AF12: =(G12/H12)*K12 -> 0 | AG12: =(G12/H12)*L12 -> 0 | AH12: =(G12/H12)*M12 -> 570000 | AI12: =(G12/H12)*N12 -> 0 | AJ12: =(G12/H12)*O12 -> 0 | AK12: =(G12/H12)*P12 -> 0 | AL12: =(G12/H12)*Q12 -> 0 | AM12: =(G12/H12)*R12 -> 0 | AN12: =(G12/H12)*S12 -> 0 | AO12: =(G12/H12)*T12 -> 0 | AP12: =(G12/H12)*U12 -> 0 | AQ12: =(G12/H12)*V12 -> 0 | AR12: =SUM(AG12:AQ12)*0.08 -> 45600 | AS12: =SUM(AG12:AR12) -> 615600 | AT12: =AS12 -> 615600 | AU12: =AA12 -> DHL | AV12: EXP | AW12: ADCDNB-26.02-000302
A13: PS260777 | B13: AT26010642 | C13: 2819783746 | D13: 46053 | E13: 107946398450 | F13: 1 | G13: 16 | H13: 16 | M13: 570000 | AA13: DHL | AB13: =A13 -> PS260777 | AC13: =B13 -> AT26010642 | AD13: =D13 -> 46053 | AE13: =G13/H13*J13 -> 0 | AF13: =(G13/H13)*K13 -> 0 | AG13: =(G13/H13)*L13 -> 0 | AH13: =(G13/H13)*M13 -> 570000 | AI13: =(G13/H13)*N13 -> 0 | AJ13: =(G13/H13)*O13 -> 0 | AK13: =(G13/H13)*P13 -> 0 | AL13: =(G13/H13)*Q13 -> 0 | AM13: =(G13/H13)*R13 -> 0 | AN13: =(G13/H13)*S13 -> 0 | AO13: =(G13/H13)*T13 -> 0 | AP13: =(G13/H13)*U13 -> 0 | AQ13: =(G13/H13)*V13 -> 0 | AR13: =SUM(AG13:AQ13)*0.08 -> 45600 | AS13: =SUM(AG13:AR13) -> 615600 | AT13: =AS13 -> 615600 | AU13: =AA13 -> DHL | AV13: EXP | AW13: ADCDNB-26.02-000303
A14: PS260771 | B14: 005/IEM/I/26 | C14: 4471973100 | D14: 46053 | E14: 107946400110 | F14: 1 | G14: 10.2 | H14: 10.2 | M14: 570000 | AA14: DHL | AB14: =A14 -> PS260771 | AC14: =B14 -> 005/IEM/I/26 | AD14: =D14 -> 46053 | AE14: =G14/H14*J14 -> 0 | AF14: =(G14/H14)*K14 -> 0 | AG14: =(G14/H14)*L14 -> 0 | AH14: =(G14/H14)*M14 -> 570000 | AI14: =(G14/H14)*N14 -> 0 | AJ14: =(G14/H14)*O14 -> 0 | AK14: =(G14/H14)*P14 -> 0 | AL14: =(G14/H14)*Q14 -> 0 | AM14: =(G14/H14)*R14 -> 0 | AN14: =(G14/H14)*S14 -> 0 | AO14: =(G14/H14)*T14 -> 0 | AP14: =(G14/H14)*U14 -> 0 | AQ14: =(G14/H14)*V14 -> 0 | AR14: =SUM(AG14:AQ14)*0.08 -> 45600 | AS14: =SUM(AG14:AR14) -> 615600 | AT14: =AS14 -> 615600 | AU14: =AA14 -> DHL | AV14: EXP | AW14: ADCDNB-26.02-000304
A15: PS260760 | B15: T260122-Y1 | C15: SPOE2601123 | D15: 46052 | E15: 107940953260 | F15: 1 | G15: 668.89 | H15: 668.89 | I15: 2.732 | L15: {=IF(H15=0, _xleta.T, IF(H15<=1000, 1290000, IF(H15<=2000, 1460000, IF(H15<=3000, 2186000, IF(H15<=5000, 2296000, ff)))))} -> 1290000 | M15: 940500 | Z15: 50E46291 | AA15: CÁT LÁI | AB15: =A15 -> PS260760 | AC15: =B15 -> T260122-Y1 | AD15: =D15 -> 46052 | AE15: =G15/H15*J15 -> 0 | AF15: =(G15/H15)*K15 -> 0 | AG15: =(G15/H15)*L15 -> 1290000 | AH15: =(G15/H15)*M15 -> 940500 | AI15: =(G15/H15)*N15 -> 0 | AJ15: =(G15/H15)*O15 -> 0 | AK15: =(G15/H15)*P15 -> 0 | AL15: =(G15/H15)*Q15 -> 0 | AM15: =(G15/H15)*R15 -> 0 | AN15: =(G15/H15)*S15 -> 0 | AO15: =(G15/H15)*T15 -> 0 | AP15: =(G15/H15)*U15 -> 0 | AQ15: =(G15/H15)*V15 -> 0 | AR15: =SUM(AG15:AQ15)*0.08 -> 178440 | AS15: =SUM(AG15:AR15) -> 2408940 | AT15: =AS15 -> 2408940 | AU15: =AA15 -> CÁT LÁI | AV15: LCL | AW15: ADCDNB-26.01-004618 | AX15: , từ Cảng Cát Lái đến KCN Bàu Xéo, Đồng Nai | AY15: 46056 | AZ15: 50E46291 | BA15: 1 X 2MT
A16: PS260748 | B16: EXD1-26-C037 | C16: HTHC26012481 | D16: 46053 | E16: 107946468930 | F16: 1 | G16: 502 | H16: 502 | I16: 1 | L16: {=IF(H16=0, _xleta.T, IF(H16<=1000, 1290000, IF(H16<=2000, 1460000, IF(H16<=3000, 2186000, IF(H16<=5000, 2296000, ff)))))} -> 1290000 | M16: 940500 | Z16: 50E46291 | AA16: CÁT LÁI | AB16: =A16 -> PS260748 | AC16: =B16 -> EXD1-26-C037 | AD16: =D16 -> 46053 | AE16: =G16/H16*J16 -> 0 | AF16: =(G16/H16)*K16 -> 0 | AG16: =(G16/H16)*L16 -> 1290000 | AH16: =(G16/H16)*M16 -> 940500 | AI16: =(G16/H16)*N16 -> 0 | AJ16: =(G16/H16)*O16 -> 0 | AK16: =(G16/H16)*P16 -> 0 | AL16: =(G16/H16)*Q16 -> 0 | AM16: =(G16/H16)*R16 -> 0 | AN16: =(G16/H16)*S16 -> 0 | AO16: =(G16/H16)*T16 -> 0 | AP16: =(G16/H16)*U16 -> 0 | AQ16: =(G16/H16)*V16 -> 0 | AR16: =SUM(AG16:AQ16)*0.08 -> 178440 | AS16: =SUM(AG16:AR16) -> 2408940 | AT16: =AS16 -> 2408940 | AU16: =AA16 -> CÁT LÁI | AV16: LCL | AW16: ADCDNB-26.02-000305 | AX16: , từ Cảng Cát Lái đến KCN Bàu Xéo, Đồng Nai | AY16: 46056
A17: PS260774 | B17: 260121-02 | C17: 20SEA26010169 | D17: 46053 | E17: 107946490300 | F17: 1 | G17: 573 | H17: 573 | I17: 0.9 | L17: {=IF(H17=0, _xleta.T, IF(H17<=1000, 1290000, IF(H17<=2000, 1460000, IF(H17<=3000, 2186000, IF(H17<=5000, 2296000, ff)))))} -> 1290000 | M17: 940500 | Z17: 50E46291 | AA17: CÁT LÁI | AB17: =A17 -> PS260774 | AC17: =B17 -> 260121-02 | AD17: =D17 -> 46053 | AE17: =G17/H17*J17 -> 0 | AF17: =(G17/H17)*K17 -> 0 | AG17: =(G17/H17)*L17 -> 1290000 | AH17: =(G17/H17)*M17 -> 940500 | AI17: =(G17/H17)*N17 -> 0 | AJ17: =(G17/H17)*O17 -> 0 | AK17: =(G17/H17)*P17 -> 0 | AL17: =(G17/H17)*Q17 -> 0 | AM17: =(G17/H17)*R17 -> 0 | AN17: =(G17/H17)*S17 -> 0 | AO17: =(G17/H17)*T17 -> 0 | AP17: =(G17/H17)*U17 -> 0 | AQ17: =(G17/H17)*V17 -> 0 | AR17: =SUM(AG17:AQ17)*0.08 -> 178440 | AS17: =SUM(AG17:AR17) -> 2408940 | AT17: =AS17 -> 2408940 | AU17: =AA17 -> CÁT LÁI | AV17: LCL | AW17: ADCDNB-26.02-000306 | AX17: , từ Cảng Cát Lái đến KCN Bàu Xéo, Đồng Nai | AY17: 46056
A18: PS260837 | B18: 0885089482 | C18: JWE5150192 | D18: 46056 | E18: 107953699600 | F18: 2 | G18: 2.2 | H18: =G18+G19 -> 237 | L18: =IF(H18<=50,1060000, IF(H18<=200, 1210000, IF(H18<=500, 1230000, IF(H18<=1000, 1440000, IF(H18<=2000, 1990000, IF(H18>2000, 1990000+(H18-2000)*1464)))))) -> 1230000 | M18: =940500+70000 -> 1010500 | Z18: 50H70505 | AA18: TCS | AB18: =A18 -> PS260837 | AC18: =B18 -> 0885089482 | AD18: =D18 -> 46056 | AE18: =G18/H18*J18 -> 0 | AF18: =(G18/H18)*K18 -> 0 | AG18: =(G18/H18)*L18 -> 11417.722 | AH18: =(G18/H18)*M18 -> 9380.1688 | AI18: =(G18/H18)*N18 -> 0 | AJ18: =(G18/H18)*O18 -> 0 | AK18: =(G18/H18)*P18 -> 0 | AL18: =(G18/H18)*Q18 -> 0 | AM18: =(G18/H18)*R18 -> 0 | AN18: =(G18/H18)*S18 -> 0 | AO18: =(G18/H18)*T18 -> 0 | AP18: =(G18/H18)*U18 -> 0 | AQ18: =(G18/H18)*V18 -> 0 | AR18: =SUM(AG18:AQ18)*0.08 -> 1663.8312 | AS18: =SUM(AG18:AR18) -> 22461.722 | AT18: =AS18 -> 22461.722 | AU18: =AA18 -> TCS | AV18: AIR | AW18: ADCDNB-26.02-000382 | AX18: , từ Kho TCS đến KCN Bàu Xéo , Đồng Nai | AY18: 46057 | AZ18: 50H70505 | BA18: 1 X 1MT
A19: PS260837 | B19: 0885090860 | C19: JWE5150192 | D19: 46056 | E19: 107953739830 | G19: 234.8 | H19: 237 | L19: =IF(H19<=50,1060000, IF(H19<=200, 1210000, IF(H19<=500, 1230000, IF(H19<=1000, 1440000, IF(H19<=2000, 1990000, IF(H19>2000, 1990000+(H19-2000)*1464)))))) -> 1230000 | M19: =940500+70000 -> 1010500 | Z19: 50H70505 | AA19: TCS | AB19: =A19 -> PS260837 | AC19: =B19 -> 0885090860 | AD19: =D19 -> 46056 | AE19: =G19/H19*J19 -> 0 | AF19: =(G19/H19)*K19 -> 0 | AG19: =(G19/H19)*L19 -> 1218582.3 | AH19: =(G19/H19)*M19 -> 1001119.8 | AI19: =(G19/H19)*N19 -> 0 | AJ19: =(G19/H19)*O19 -> 0 | AK19: =(G19/H19)*P19 -> 0 | AL19: =(G19/H19)*Q19 -> 0 | AM19: =(G19/H19)*R19 -> 0 | AN19: =(G19/H19)*S19 -> 0 | AO19: =(G19/H19)*T19 -> 0 | AP19: =(G19/H19)*U19 -> 0 | AQ19: =(G19/H19)*V19 -> 0 | AR19: =SUM(AG19:AQ19)*0.08 -> 177576.17 | AS19: =SUM(AG19:AR19) -> 2397278.3 | AT19: =AS19 -> 2397278.3 | AU19: =AA19 -> TCS | AV19: AIR | AW19: ADCDNB-26.02-000382 | AX19: , từ Kho TCS đến KCN Bàu Xéo , Đồng Nai | AY19: 46057
A20: PS260835 | B20: PC260202VY | C20: JWE5150195 | D20: 46056 | E20: 107953153600 | F20: 1 | G20: 32 | H20: 32 | L20: =IF(H20<=50,1060000, IF(H20<=200, 1210000, IF(H20<=500, 1230000, IF(H20<=1000, 1440000, IF(H20<=2000, 1990000, IF(H20>2000, 1990000+(H20-2000)*1464)))))) -> 1060000 | M20: 940500 | Z20: 50H70505 | AA20: TCS | AB20: =A20 -> PS260835 | AC20: =B20 -> PC260202VY | AD20: =D20 -> 46056 | AE20: =G20/H20*J20 -> 0 | AF20: =(G20/H20)*K20 -> 0 | AG20: =(G20/H20)*L20 -> 1060000 | AH20: =(G20/H20)*M20 -> 940500 | AI20: =(G20/H20)*N20 -> 0 | AJ20: =(G20/H20)*O20 -> 0 | AK20: =(G20/H20)*P20 -> 0 | AL20: =(G20/H20)*Q20 -> 0 | AM20: =(G20/H20)*R20 -> 0 | AN20: =(G20/H20)*S20 -> 0 | AO20: =(G20/H20)*T20 -> 0 | AP20: =(G20/H20)*U20 -> 0 | AQ20: =(G20/H20)*V20 -> 0 | AR20: =SUM(AG20:AQ20)*0.08 -> 160040 | AS20: =SUM(AG20:AR20) -> 2160540 | AT20: =AS20 -> 2160540 | AU20: =AA20 -> TCS | AV20: AIR | AW20: ADCDNB-26.02-000381 | AX20: , từ Kho TCS đến KCN Bàu Xéo , Đồng Nai | AY20: 46057
A21: PS260806 | B21: LW260129 | C21: 5397965591 | D21: 46056 | E21: 107952134730 | F21: 1 | G21: 32.5 | H21: 32.5 | M21: 570000 | AA21: DHL | AB21: =A21 -> PS260806 | AC21: =B21 -> LW260129 | AD21: =D21 -> 46056 | AE21: =G21/H21*J21 -> 0 | AF21: =(G21/H21)*K21 -> 0 | AG21: =(G21/H21)*L21 -> 0 | AH21: =(G21/H21)*M21 -> 570000 | AI21: =(G21/H21)*N21 -> 0 | AJ21: =(G21/H21)*O21 -> 0 | AK21: =(G21/H21)*P21 -> 0 | AL21: =(G21/H21)*Q21 -> 0 | AM21: =(G21/H21)*R21 -> 0 | AN21: =(G21/H21)*S21 -> 0 | AO21: =(G21/H21)*T21 -> 0 | AP21: =(G21/H21)*U21 -> 0 | AQ21: =(G21/H21)*V21 -> 0 | AR21: =SUM(AG21:AQ21)*0.08 -> 45600 | AS21: =SUM(AG21:AR21) -> 615600 | AT21: =AS21 -> 615600 | AU21: =AA21 -> DHL | AV21: EXP | AW21: ADCDNB-26.02-000449
A22: PS260812 | B22: DJL-260130-007 | C22: 5162691741 | D22: 46055 | E22: 107951879560 | F22: 1 | G22: 0.9 | H22: 0.9 | M22: 570000 | AA22: DHL | AB22: =A22 -> PS260812 | AC22: =B22 -> DJL-260130-007 | AD22: =D22 -> 46055 | AE22: =G22/H22*J22 -> 0 | AF22: =(G22/H22)*K22 -> 0 | AG22: =(G22/H22)*L22 -> 0 | AH22: =(G22/H22)*M22 -> 570000 | AI22: =(G22/H22)*N22 -> 0 | AJ22: =(G22/H22)*O22 -> 0 | AK22: =(G22/H22)*P22 -> 0 | AL22: =(G22/H22)*Q22 -> 0 | AM22: =(G22/H22)*R22 -> 0 | AN22: =(G22/H22)*S22 -> 0 | AO22: =(G22/H22)*T22 -> 0 | AP22: =(G22/H22)*U22 -> 0 | AQ22: =(G22/H22)*V22 -> 0 | AR22: =SUM(AG22:AQ22)*0.08 -> 45600 | AS22: =SUM(AG22:AR22) -> 615600 | AT22: =AS22 -> 615600 | AU22: =AA22 -> DHL | AV22: EXP | AW22: ADCDNB-26.02-000450
A23: PS260814 | B23: IV260103194 | C23: 5162712752 | D23: 46055 | E23: 107951921560 | F23: 1 | G23: 20 | H23: 20 | M23: 570000 | AA23: DHL | AB23: =A23 -> PS260814 | AC23: =B23 -> IV260103194 | AD23: =D23 -> 46055 | AE23: =G23/H23*J23 -> 0 | AF23: =(G23/H23)*K23 -> 0 | AG23: =(G23/H23)*L23 -> 0 | AH23: =(G23/H23)*M23 -> 570000 | AI23: =(G23/H23)*N23 -> 0 | AJ23: =(G23/H23)*O23 -> 0 | AK23: =(G23/H23)*P23 -> 0 | AL23: =(G23/H23)*Q23 -> 0 | AM23: =(G23/H23)*R23 -> 0 | AN23: =(G23/H23)*S23 -> 0 | AO23: =(G23/H23)*T23 -> 0 | AP23: =(G23/H23)*U23 -> 0 | AQ23: =(G23/H23)*V23 -> 0 | AR23: =SUM(AG23:AQ23)*0.08 -> 45600 | AS23: =SUM(AG23:AR23) -> 615600 | AT23: =AS23 -> 615600 | AU23: =AA23 -> DHL | AV23: EXP | AW23: ADCDNB-26.02-000451
A24: PS260805 | B24: IV260102980 | C24: 5162398905 | D24: 46055 | E24: 107951960100 | F24: 1 | G24: 1.5 | H24: 1.5 | M24: 570000 | AA24: DHL | AB24: =A24 -> PS260805 | AC24: =B24 -> IV260102980 | AD24: =D24 -> 46055 | AE24: =G24/H24*J24 -> 0 | AF24: =(G24/H24)*K24 -> 0 | AG24: =(G24/H24)*L24 -> 0 | AH24: =(G24/H24)*M24 -> 570000 | AI24: =(G24/H24)*N24 -> 0 | AJ24: =(G24/H24)*O24 -> 0 | AK24: =(G24/H24)*P24 -> 0 | AL24: =(G24/H24)*Q24 -> 0 | AM24: =(G24/H24)*R24 -> 0 | AN24: =(G24/H24)*S24 -> 0 | AO24: =(G24/H24)*T24 -> 0 | AP24: =(G24/H24)*U24 -> 0 | AQ24: =(G24/H24)*V24 -> 0 | AR24: =SUM(AG24:AQ24)*0.08 -> 45600 | AS24: =SUM(AG24:AR24) -> 615600 | AT24: =AS24 -> 615600 | AU24: =AA24 -> DHL | AV24: EXP | AW24: ADCDNB-26.02-000452
A25: PS260804 | B25: PS26-804 | C25: 5162376693 | D25: 46055 | E25: 107952014220 | F25: 1 | G25: 7.1 | H25: 7.1 | M25: 570000 | AA25: DHL | AB25: =A25 -> PS260804 | AC25: =B25 -> PS26-804 | AD25: =D25 -> 46055 | AE25: =G25/H25*J25 -> 0 | AF25: =(G25/H25)*K25 -> 0 | AG25: =(G25/H25)*L25 -> 0 | AH25: =(G25/H25)*M25 -> 570000 | AI25: =(G25/H25)*N25 -> 0 | AJ25: =(G25/H25)*O25 -> 0 | AK25: =(G25/H25)*P25 -> 0 | AL25: =(G25/H25)*Q25 -> 0 | AM25: =(G25/H25)*R25 -> 0 | AN25: =(G25/H25)*S25 -> 0 | AO25: =(G25/H25)*T25 -> 0 | AP25: =(G25/H25)*U25 -> 0 | AQ25: =(G25/H25)*V25 -> 0 | AR25: =SUM(AG25:AQ25)*0.08 -> 45600 | AS25: =SUM(AG25:AR25) -> 615600 | AT25: =AS25 -> 615600 | AU25: =AA25 -> DHL | AV25: EXP | AW25: ADCDNB-26.02-000453
A26: PS260803 | B26: 00013-00131393 | C26: 5496713843 | D26: 46056 | E26: 107953077740 | F26: 1 | G26: 2.5 | H26: 2.5 | M26: 570000 | AA26: DHL | AB26: =A26 -> PS260803 | AC26: =B26 -> 00013-00131393 | AD26: =D26 -> 46056 | AE26: =G26/H26*J26 -> 0 | AF26: =(G26/H26)*K26 -> 0 | AG26: =(G26/H26)*L26 -> 0 | AH26: =(G26/H26)*M26 -> 570000 | AI26: =(G26/H26)*N26 -> 0 | AJ26: =(G26/H26)*O26 -> 0 | AK26: =(G26/H26)*P26 -> 0 | AL26: =(G26/H26)*Q26 -> 0 | AM26: =(G26/H26)*R26 -> 0 | AN26: =(G26/H26)*S26 -> 0 | AO26: =(G26/H26)*T26 -> 0 | AP26: =(G26/H26)*U26 -> 0 | AQ26: =(G26/H26)*V26 -> 0 | AR26: =SUM(AG26:AQ26)*0.08 -> 45600 | AS26: =SUM(AG26:AR26) -> 615600 | AT26: =AS26 -> 615600 | AU26: =AA26 -> DHL | AV26: EXP | AW26: ADCDNB-26.02-000454
A27: PS260833 | B27: ZS26013001 | C27: 3405477342 | D27: 46056 | E27: 107954071410 | F27: 1 | G27: 4.5 | H27: 4.5 | M27: 570000 | AA27: DHL | AB27: =A27 -> PS260833 | AC27: =B27 -> ZS26013001 | AD27: =D27 -> 46056 | AE27: =G27/H27*J27 -> 0 | AF27: =(G27/H27)*K27 -> 0 | AG27: =(G27/H27)*L27 -> 0 | AH27: =(G27/H27)*M27 -> 570000 | AI27: =(G27/H27)*N27 -> 0 | AJ27: =(G27/H27)*O27 -> 0 | AK27: =(G27/H27)*P27 -> 0 | AL27: =(G27/H27)*Q27 -> 0 | AM27: =(G27/H27)*R27 -> 0 | AN27: =(G27/H27)*S27 -> 0 | AO27: =(G27/H27)*T27 -> 0 | AP27: =(G27/H27)*U27 -> 0 | AQ27: =(G27/H27)*V27 -> 0 | AR27: =SUM(AG27:AQ27)*0.08 -> 45600 | AS27: =SUM(AG27:AR27) -> 615600 | AT27: =AS27 -> 615600 | AU27: =AA27 -> DHL | AV27: EXP | AW27: ADCDNB-26.02-000455
A28: PS260807 | B28: 2/PQR-PS/26 | C28: 112600036867319 | D28: 46056 | E28: 107951650920 | F28: 1 | G28: 218 | H28: 218 | L28: {=IF(H28=0, _xleta.T, IF(H28<=1000, 1790000, IF(H28<=2000, 1960000, IF(H28<=3000, 2686000, IF(H28<=5000, 2796000, ff)))))} -> 1790000 | M28: 940500 | Z28: 50H69350 | AA28: HIỆP PHƯỚC | AB28: =A28 -> PS260807 | AC28: =B28 -> 2/PQR-PS/26 | AD28: =D28 -> 46056 | AE28: =G28/H28*J28 -> 0 | AF28: =(G28/H28)*K28 -> 0 | AG28: =(G28/H28)*L28 -> 1790000 | AH28: =(G28/H28)*M28 -> 940500 | AI28: =(G28/H28)*N28 -> 0 | AJ28: =(G28/H28)*O28 -> 0 | AK28: =(G28/H28)*P28 -> 0 | AL28: =(G28/H28)*Q28 -> 0 | AM28: =(G28/H28)*R28 -> 0 | AN28: =(G28/H28)*S28 -> 0 | AO28: =(G28/H28)*T28 -> 0 | AP28: =(G28/H28)*U28 -> 0 | AQ28: =(G28/H28)*V28 -> 0 | AR28: =SUM(AG28:AQ28)*0.08 -> 218440 | AS28: =SUM(AG28:AR28) -> 2948940 | AT28: =AS28 -> 2948940 | AU28: =AA28 -> HIỆP PHƯỚC | AV28: LCL | AW28: ADCDNB-26.02-000456 | AX28: , từ Cảng Hiệp Phước đến KCN Bàu Xéo, Đồng Nai | AY28: 46057 | AZ28: 50H69350 | BA28: 1 X 1MT
A29: PS26834 | B29: VV07701/6538/25 | C29: 112600036938787 | D29: 46056 | E29: 107955652450 | F29: 1 | G29: 528 | H29: 528 | L29: {=IF(H29=0, _xleta.T, IF(H29<=1000, 1590000, IF(H29<=2000, 1760000, IF(H29<=3000, 2486000, IF(H29<=5000, 2596000, ff)))))} -> 1590000 | M29: 940500 | Z29: 50E52902 | AA29: TÂN TẠO | AB29: =A29 -> PS26834 | AC29: =B29 -> VV07701/6538/25 | AD29: =D29 -> 46056 | AE29: =G29/H29*J29 -> 0 | AF29: =(G29/H29)*K29 -> 0 | AG29: =(G29/H29)*L29 -> 1590000 | AH29: =(G29/H29)*M29 -> 940500 | AI29: =(G29/H29)*N29 -> 0 | AJ29: =(G29/H29)*O29 -> 0 | AK29: =(G29/H29)*P29 -> 0 | AL29: =(G29/H29)*Q29 -> 0 | AM29: =(G29/H29)*R29 -> 0 | AN29: =(G29/H29)*S29 -> 0 | AO29: =(G29/H29)*T29 -> 0 | AP29: =(G29/H29)*U29 -> 0 | AQ29: =(G29/H29)*V29 -> 0 | AR29: =SUM(AG29:AQ29)*0.08 -> 202440 | AS29: =SUM(AG29:AR29) -> 2732940 | AT29: =AS29 -> 2732940 | AU29: =AA29 -> TÂN TẠO | AV29: LCL | AW29: ADCDNB-26.02-000487 | AX29: , từ Tân Tạo đến KCN Bàu Xéo, Đồng Nai | AY29: 46057 | AZ29: 50E52902 | BA29: 1 X 1MT
A30: PS260871 | B30: PC2602032VY | C30: JWE5150205 | D30: 46057 | E30: 107957066710 | F30: 1 | G30: 1 | H30: 1 | L30: =IF(H30<=50,1060000, IF(H30<=200, 1210000, IF(H30<=500, 1230000, IF(H30<=1000, 1440000, IF(H30<=2000, 1990000, IF(H30>2000, 1990000+(H30-2000)*1464)))))) -> 1060000 | M30: 940500 | Z30: 50H69559 | AA30: TCS | AB30: =A30 -> PS260871 | AC30: =B30 -> PC2602032VY | AD30: =D30 -> 46057 | AE30: =G30/H30*J30 -> 0 | AF30: =(G30/H30)*K30 -> 0 | AG30: =(G30/H30)*L30 -> 1060000 | AH30: =(G30/H30)*M30 -> 940500 | AI30: =(G30/H30)*N30 -> 0 | AJ30: =(G30/H30)*O30 -> 0 | AK30: =(G30/H30)*P30 -> 0 | AL30: =(G30/H30)*Q30 -> 0 | AM30: =(G30/H30)*R30 -> 0 | AN30: =(G30/H30)*S30 -> 0 | AO30: =(G30/H30)*T30 -> 0 | AP30: =(G30/H30)*U30 -> 0 | AQ30: =(G30/H30)*V30 -> 0 | AR30: =SUM(AG30:AQ30)*0.08 -> 160040 | AS30: =SUM(AG30:AR30) -> 2160540 | AT30: =AS30 -> 2160540 | AU30: =AA30 -> TCS | AV30: AIR | AW30: ADCDNB-26.02-000561 | AX30: , từ Kho TCS đến KCN Bàu Xéo , Đồng Nai | AY30: 46058 | AZ30: 50H69559 | BA30: 1 X 1MT
A31: PS260870 | B31: G8-20260203 VY (B) | C31: JWE5150200 | D31: 46057 | E31: 107957082550 | F31: 1 | G31: 2 | H31: 2 | L31: =IF(H31<=50,1060000, IF(H31<=200, 1210000, IF(H31<=500, 1230000, IF(H31<=1000, 1440000, IF(H31<=2000, 1990000, IF(H31>2000, 1990000+(H31-2000)*1464)))))) -> 1060000 | M31: 940500 | Z31: 50H69559 | AA31: TCS | AB31: =A31 -> PS260870 | AC31: =B31 -> G8-20260203 VY (B) | AD31: =D31 -> 46057 | AE31: =G31/H31*J31 -> 0 | AF31: =(G31/H31)*K31 -> 0 | AG31: =(G31/H31)*L31 -> 1060000 | AH31: =(G31/H31)*M31 -> 940500 | AI31: =(G31/H31)*N31 -> 0 | AJ31: =(G31/H31)*O31 -> 0 | AK31: =(G31/H31)*P31 -> 0 | AL31: =(G31/H31)*Q31 -> 0 | AM31: =(G31/H31)*R31 -> 0 | AN31: =(G31/H31)*S31 -> 0 | AO31: =(G31/H31)*T31 -> 0 | AP31: =(G31/H31)*U31 -> 0 | AQ31: =(G31/H31)*V31 -> 0 | AR31: =SUM(AG31:AQ31)*0.08 -> 160040 | AS31: =SUM(AG31:AR31) -> 2160540 | AT31: =AS31 -> 2160540 | AU31: =AA31 -> TCS | AV31: AIR | AW31: ADCDNB-26.02-000556 | AX31: , từ Kho TCS đến KCN Bàu Xéo , Đồng Nai | AY31: 46058
A32: PS260869 | B32: PC260203VY | C32: JWE5150204 | D32: 46057 | E32: 107957099500 | F32: 1 | G32: 30 | H32: 30 | L32: =IF(H32<=50,1060000, IF(H32<=200, 1210000, IF(H32<=500, 1230000, IF(H32<=1000, 1440000, IF(H32<=2000, 1990000, IF(H32>2000, 1990000+(H32-2000)*1464)))))) -> 1060000 | M32: 940500 | Z32: 50H69559 | AA32: TCS | AB32: =A32 -> PS260869 | AC32: =B32 -> PC260203VY | AD32: =D32 -> 46057 | AE32: =G32/H32*J32 -> 0 | AF32: =(G32/H32)*K32 -> 0 | AG32: =(G32/H32)*L32 -> 1060000 | AH32: =(G32/H32)*M32 -> 940500 | AI32: =(G32/H32)*N32 -> 0 | AJ32: =(G32/H32)*O32 -> 0 | AK32: =(G32/H32)*P32 -> 0 | AL32: =(G32/H32)*Q32 -> 0 | AM32: =(G32/H32)*R32 -> 0 | AN32: =(G32/H32)*S32 -> 0 | AO32: =(G32/H32)*T32 -> 0 | AP32: =(G32/H32)*U32 -> 0 | AQ32: =(G32/H32)*V32 -> 0 | AR32: =SUM(AG32:AQ32)*0.08 -> 160040 | AS32: =SUM(AG32:AR32) -> 2160540 | AT32: =AS32 -> 2160540 | AU32: =AA32 -> TCS | AV32: AIR | AW32: ADCDNB-26.02-000552 | AX32: , từ Kho TCS đến KCN Bàu Xéo , Đồng Nai | AY32: 46058
A33: PS260842 | B33: T260130-Y2 | C33: SPX2601073 | D33: 46056 | E33: 107954923200 | F33: 1 | G33: 23 | H33: 23 | L33: =IF(H33<=50,1060000, IF(H33<=200, 1210000, IF(H33<=500, 1230000, IF(H33<=1000, 1440000, IF(H33<=2000, 1990000, IF(H33>2000, 1990000+(H33-2000)*1464)))))) -> 1060000 | M33: 940500 | Z33: 50H69559 | AA33: TCS | AB33: =A33 -> PS260842 | AC33: =B33 -> T260130-Y2 | AD33: =D33 -> 46056 | AE33: =G33/H33*J33 -> 0 | AF33: =(G33/H33)*K33 -> 0 | AG33: =(G33/H33)*L33 -> 1060000 | AH33: =(G33/H33)*M33 -> 940500 | AI33: =(G33/H33)*N33 -> 0 | AJ33: =(G33/H33)*O33 -> 0 | AK33: =(G33/H33)*P33 -> 0 | AL33: =(G33/H33)*Q33 -> 0 | AM33: =(G33/H33)*R33 -> 0 | AN33: =(G33/H33)*S33 -> 0 | AO33: =(G33/H33)*T33 -> 0 | AP33: =(G33/H33)*U33 -> 0 | AQ33: =(G33/H33)*V33 -> 0 | AR33: =SUM(AG33:AQ33)*0.08 -> 160040 | AS33: =SUM(AG33:AR33) -> 2160540 | AT33: =AS33 -> 2160540 | AU33: =AA33 -> TCS | AV33: AIR | AW33: ADCDNB-26.02-000577 | AX33: , từ Kho TCS đến KCN Bàu Xéo , Đồng Nai | AY33: 46058
A34: PS260860 | B34: 2601/190/VY | C34: SBS80010951 | D34: 46057 | E34: 107959027260 | F34: 1 | G34: 426.3 | H34: 426.3 | L34: =IF(H34<=50,1060000, IF(H34<=200, 1210000, IF(H34<=500, 1230000, IF(H34<=1000, 1440000, IF(H34<=2000, 1990000, IF(H34>2000, 1990000+(H34-2000)*1464)))))) -> 1230000 | M34: 940500 | Z34: 50H69559 | AA34: TCS | AB34: =A34 -> PS260860 | AC34: =B34 -> 2601/190/VY | AD34: =D34 -> 46057 | AE34: =G34/H34*J34 -> 0 | AF34: =(G34/H34)*K34 -> 0 | AG34: =(G34/H34)*L34 -> 1230000 | AH34: =(G34/H34)*M34 -> 940500 | AI34: =(G34/H34)*N34 -> 0 | AJ34: =(G34/H34)*O34 -> 0 | AK34: =(G34/H34)*P34 -> 0 | AL34: =(G34/H34)*Q34 -> 0 | AM34: =(G34/H34)*R34 -> 0 | AN34: =(G34/H34)*S34 -> 0 | AO34: =(G34/H34)*T34 -> 0 | AP34: =(G34/H34)*U34 -> 0 | AQ34: =(G34/H34)*V34 -> 0 | AR34: =SUM(AG34:AQ34)*0.08 -> 173640 | AS34: =SUM(AG34:AR34) -> 2344140 | AT34: =AS34 -> 2344140 | AU34: =AA34 -> TCS | AV34: AIR | AW34: ADCDNB-26.02-000578 | AX34: , từ Kho TCS đến KCN Bàu Xéo , Đồng Nai | AY34: 46058
A35: PS260841 | B35: T260130-YH1 | C35: 2526261964 | D35: 46056 | E35: 107954970060 | F35: 1 | G35: 29 | H35: 29 | M35: 570000 | AA35: DHL | AB35: =A35 -> PS260841 | AC35: =B35 -> T260130-YH1 | AD35: =D35 -> 46056 | AE35: =G35/H35*J35 -> 0 | AF35: =(G35/H35)*K35 -> 0 | AG35: =(G35/H35)*L35 -> 0 | AH35: =(G35/H35)*M35 -> 570000 | AI35: =(G35/H35)*N35 -> 0 | AJ35: =(G35/H35)*O35 -> 0 | AK35: =(G35/H35)*P35 -> 0 | AL35: =(G35/H35)*Q35 -> 0 | AM35: =(G35/H35)*R35 -> 0 | AN35: =(G35/H35)*S35 -> 0 | AO35: =(G35/H35)*T35 -> 0 | AP35: =(G35/H35)*U35 -> 0 | AQ35: =(G35/H35)*V35 -> 0 | AR35: =SUM(AG35:AQ35)*0.08 -> 45600 | AS35: =SUM(AG35:AR35) -> 615600 | AT35: =AS35 -> 615600 | AU35: =AA35 -> DHL | AV35: EXP | AW35: ADCDNB-26.02-000588
A36: PS260839 | B36: SO43432 | C36: 5162567023 | D36: 46056 | E36: 107955674520 | F36: 1 | G36: 1.4 | H36: 1.4 | M36: 570000 | AA36: DHL | AB36: =A36 -> PS260839 | AC36: =B36 -> SO43432 | AD36: =D36 -> 46056 | AE36: =G36/H36*J36 -> 0 | AF36: =(G36/H36)*K36 -> 0 | AG36: =(G36/H36)*L36 -> 0 | AH36: =(G36/H36)*M36 -> 570000 | AI36: =(G36/H36)*N36 -> 0 | AJ36: =(G36/H36)*O36 -> 0 | AK36: =(G36/H36)*P36 -> 0 | AL36: =(G36/H36)*Q36 -> 0 | AM36: =(G36/H36)*R36 -> 0 | AN36: =(G36/H36)*S36 -> 0 | AO36: =(G36/H36)*T36 -> 0 | AP36: =(G36/H36)*U36 -> 0 | AQ36: =(G36/H36)*V36 -> 0 | AR36: =SUM(AG36:AQ36)*0.08 -> 45600 | AS36: =SUM(AG36:AR36) -> 615600 | AT36: =AS36 -> 615600 | AU36: =AA36 -> DHL | AV36: EXP | AW36: ADCDNB-26.02-000589
A37: PS260845 | B37: DI26A00774 | C37: 5162758672 | D37: 46056 | E37: 107955697140 | F37: 1 | G37: 3.7 | H37: 3.7 | M37: 570000 | AA37: DHL | AB37: =A37 -> PS260845 | AC37: =B37 -> DI26A00774 | AD37: =D37 -> 46056 | AE37: =G37/H37*J37 -> 0 | AF37: =(G37/H37)*K37 -> 0 | AG37: =(G37/H37)*L37 -> 0 | AH37: =(G37/H37)*M37 -> 570000 | AI37: =(G37/H37)*N37 -> 0 | AJ37: =(G37/H37)*O37 -> 0 | AK37: =(G37/H37)*P37 -> 0 | AL37: =(G37/H37)*Q37 -> 0 | AM37: =(G37/H37)*R37 -> 0 | AN37: =(G37/H37)*S37 -> 0 | AO37: =(G37/H37)*T37 -> 0 | AP37: =(G37/H37)*U37 -> 0 | AQ37: =(G37/H37)*V37 -> 0 | AR37: =SUM(AG37:AQ37)*0.08 -> 45600 | AS37: =SUM(AG37:AR37) -> 615600 | AT37: =AS37 -> 615600 | AU37: =AA37 -> DHL | AV37: EXP | AW37: ADCDNB-26.02-000590
A38: PS260846 | B38: 5228244 | C38: 5397938210 | D38: 46056 | E38: 107955722600 | F38: 1 | G38: 5.5 | H38: 5.5 | M38: 570000 | AA38: DHL | AB38: =A38 -> PS260846 | AC38: =B38 -> 5228244 | AD38: =D38 -> 46056 | AE38: =G38/H38*J38 -> 0 | AF38: =(G38/H38)*K38 -> 0 | AG38: =(G38/H38)*L38 -> 0 | AH38: =(G38/H38)*M38 -> 570000 | AI38: =(G38/H38)*N38 -> 0 | AJ38: =(G38/H38)*O38 -> 0 | AK38: =(G38/H38)*P38 -> 0 | AL38: =(G38/H38)*Q38 -> 0 | AM38: =(G38/H38)*R38 -> 0 | AN38: =(G38/H38)*S38 -> 0 | AO38: =(G38/H38)*T38 -> 0 | AP38: =(G38/H38)*U38 -> 0 | AQ38: =(G38/H38)*V38 -> 0 | AR38: =SUM(AG38:AQ38)*0.08 -> 45600 | AS38: =SUM(AG38:AR38) -> 615600 | AT38: =AS38 -> 615600 | AU38: =AA38 -> DHL | AV38: EXP | AW38: ADCDNB-26.02-000591
A39: PS260861 | B39: OHTY260148 | C39: 5162437534 | D39: 46057 | E39: 107957389040 | F39: 1 | G39: 13.5 | H39: 13.5 | M39: 570000 | AA39: DHL | AB39: =A39 -> PS260861 | AC39: =B39 -> OHTY260148 | AD39: =D39 -> 46057 | AE39: =G39/H39*J39 -> 0 | AF39: =(G39/H39)*K39 -> 0 | AG39: =(G39/H39)*L39 -> 0 | AH39: =(G39/H39)*M39 -> 570000 | AI39: =(G39/H39)*N39 -> 0 | AJ39: =(G39/H39)*O39 -> 0 | AK39: =(G39/H39)*P39 -> 0 | AL39: =(G39/H39)*Q39 -> 0 | AM39: =(G39/H39)*R39 -> 0 | AN39: =(G39/H39)*S39 -> 0 | AO39: =(G39/H39)*T39 -> 0 | AP39: =(G39/H39)*U39 -> 0 | AQ39: =(G39/H39)*V39 -> 0 | AR39: =SUM(AG39:AQ39)*0.08 -> 45600 | AS39: =SUM(AG39:AR39) -> 615600 | AT39: =AS39 -> 615600 | AU39: =AA39 -> DHL | AV39: EXP | AW39: ADCDNB-26.02-000592
A40: PS260741 | B40: IV260102262 | C40: XMNSGN26010647 | D40: 46057 | E40: 107957353340 | F40: 1 | G40: 262.93 | H40: 262.93 | I40: 1.71 | L40: {=IF(H40=0, _xleta.T, IF(H40<=1000, 1290000, IF(H40<=2000, 1460000, IF(H40<=3000, 2186000, IF(H40<=5000, 2296000, ff)))))} -> 1290000 | M40: 940500 | Z40: 50E46592 | AA40: CÁT LÁI | AB40: =A40 -> PS260741 | AC40: =B40 -> IV260102262 | AD40: =D40 -> 46057 | AE40: =G40/H40*J40 -> 0 | AF40: =(G40/H40)*K40 -> 0 | AG40: =(G40/H40)*L40 -> 1290000 | AH40: =(G40/H40)*M40 -> 940500 | AI40: =(G40/H40)*N40 -> 0 | AJ40: =(G40/H40)*O40 -> 0 | AK40: =(G40/H40)*P40 -> 0 | AL40: =(G40/H40)*Q40 -> 0 | AM40: =(G40/H40)*R40 -> 0 | AN40: =(G40/H40)*S40 -> 0 | AO40: =(G40/H40)*T40 -> 0 | AP40: =(G40/H40)*U40 -> 0 | AQ40: =(G40/H40)*V40 -> 0 | AR40: =SUM(AG40:AQ40)*0.08 -> 178440 | AS40: =SUM(AG40:AR40) -> 2408940 | AT40: =AS40 -> 2408940 | AU40: =AA40 -> CÁT LÁI | AV40: LCL | AW40: ADCDNB-26.02-000417 | AX40: , từ Cảng Cát Lái đến KCN Bàu Xéo, Đồng Nai | AY40: 46058 | AZ40: 50E46592 | BA40: 1 X 1MT
A41: PS260773 | B41: DJL-260119-005 | C41: 20SEA26010179 | D41: 46057 | E41: 107959901340 | F41: 1 | G41: 135.2 | H41: 135.2 | I41: 0.332 | L41: {=IF(H41=0, _xleta.T, IF(H41<=1000, 1290000, IF(H41<=2000, 1460000, IF(H41<=3000, 2186000, IF(H41<=5000, 2296000, ff)))))} -> 1290000 | M41: 940500 | AA41: CÁT LÁI | AB41: =A41 -> PS260773 | AC41: =B41 -> DJL-260119-005 | AD41: =D41 -> 46057 | AE41: =G41/H41*J41 -> 0 | AF41: =(G41/H41)*K41 -> 0 | AG41: =(G41/H41)*L41 -> 1290000 | AH41: =(G41/H41)*M41 -> 940500 | AI41: =(G41/H41)*N41 -> 0 | AJ41: =(G41/H41)*O41 -> 0 | AK41: =(G41/H41)*P41 -> 0 | AL41: =(G41/H41)*Q41 -> 0 | AM41: =(G41/H41)*R41 -> 0 | AN41: =(G41/H41)*S41 -> 0 | AO41: =(G41/H41)*T41 -> 0 | AP41: =(G41/H41)*U41 -> 0 | AQ41: =(G41/H41)*V41 -> 0 | AR41: =SUM(AG41:AQ41)*0.08 -> 178440 | AS41: =SUM(AG41:AR41) -> 2408940 | AT41: =AS41 -> 2408940 | AU41: =AA41 -> CÁT LÁI | AV41: LCL | AW41: ADCDNB-26.02-000627 | AX41: , từ Cảng Cát Lái đến KCN Bàu Xéo, Đồng Nai | AY41: 46058
A42: PS260811 | B42: 260116-6384 (C ) | C42: 2HCC8SN101HC7505 | D42: 46057 | E42: 107951317130 | F42: 1 | G42: 25.2 | H42: 25.2 | I42: 0.07 | L42: {=IF(H42=0, _xleta.T, IF(H42<=1000, 1290000, IF(H42<=2000, 1460000, IF(H42<=3000, 2186000, IF(H42<=5000, 2296000, ff)))))} -> 1290000 | M42: 940500 | Z42: 50E54467 | AA42: CÁT LÁI | AB42: =A42 -> PS260811 | AC42: =B42 -> 260116-6384 (C ) | AD42: =D42 -> 46057 | AE42: =G42/H42*J42 -> 0 | AF42: =(G42/H42)*K42 -> 0 | AG42: =(G42/H42)*L42 -> 1290000 | AH42: =(G42/H42)*M42 -> 940500 | AI42: =(G42/H42)*N42 -> 0 | AJ42: =(G42/H42)*O42 -> 0 | AK42: =(G42/H42)*P42 -> 0 | AL42: =(G42/H42)*Q42 -> 0 | AM42: =(G42/H42)*R42 -> 0 | AN42: =(G42/H42)*S42 -> 0 | AO42: =(G42/H42)*T42 -> 0 | AP42: =(G42/H42)*U42 -> 0 | AQ42: =(G42/H42)*V42 -> 0 | AR42: =SUM(AG42:AQ42)*0.08 -> 178440 | AS42: =SUM(AG42:AR42) -> 2408940 | AT42: =AS42 -> 2408940 | AU42: =AA42 -> CÁT LÁI | AV42: LCL | AW42: ADCDNB-26.02-000614 | AX42: , từ Cảng Cát Lái đến KCN Bàu Xéo, Đồng Nai | AY42: 46058 | AZ42: 50E54467 | BA42: 1 X 1MT
A43: PS260808 | B43: IN-JF260122 | C43: DGPE26010235 | D43: 46055 | E43: 107949727320 | F43: 1 | G43: 417 | H43: 417 | I43: 1.97 | L43: {=IF(H43=0, _xleta.T, IF(H43<=1000, 1290000, IF(H43<=2000, 1460000, IF(H43<=3000, 2186000, IF(H43<=5000, 2296000, ff)))))} -> 1290000 | M43: 940500 | Z43: 50E46291 | AA43: CÁT LÁI | AB43: =A43 -> PS260808 | AC43: =B43 -> IN-JF260122 | AD43: =D43 -> 46055 | AE43: =G43/H43*J43 -> 0 | AF43: =(G43/H43)*K43 -> 0 | AG43: =(G43/H43)*L43 -> 1290000 | AH43: =(G43/H43)*M43 -> 940500 | AI43: =(G43/H43)*N43 -> 0 | AJ43: =(G43/H43)*O43 -> 0 | AK43: =(G43/H43)*P43 -> 0 | AL43: =(G43/H43)*Q43 -> 0 | AM43: =(G43/H43)*R43 -> 0 | AN43: =(G43/H43)*S43 -> 0 | AO43: =(G43/H43)*T43 -> 0 | AP43: =(G43/H43)*U43 -> 0 | AQ43: =(G43/H43)*V43 -> 0 | AR43: =SUM(AG43:AQ43)*0.08 -> 178440 | AS43: =SUM(AG43:AR43) -> 2408940 | AT43: =AS43 -> 2408940 | AU43: =AA43 -> CÁT LÁI | AV43: LCL | AW43: ADCDNB-26.01-004720 | AX43: , từ Cảng Cát Lái đến KCN Bàu Xéo, Đồng Nai | AY43: 46058 | AZ43: 50E46291 | BA43: 1 X 2MT
A44: PS260819 | B44: KS20260125001 | C44: HTHC26012564 | D44: 46056 | E44: 107953343040 | F44: 1 | G44: 514 | H44: 514 | I44: 2 | L44: {=IF(H44=0, _xleta.T, IF(H44<=1000, 1290000, IF(H44<=2000, 1460000, IF(H44<=3000, 2186000, IF(H44<=5000, 2296000, ff)))))} -> 1290000 | M44: 940500 | Z44: 50E46291 | AA44: CÁT LÁI | AB44: =A44 -> PS260819 | AC44: =B44 -> KS20260125001 | AD44: =D44 -> 46056 | AE44: =G44/H44*J44 -> 0 | AF44: =(G44/H44)*K44 -> 0 | AG44: =(G44/H44)*L44 -> 1290000 | AH44: =(G44/H44)*M44 -> 940500 | AI44: =(G44/H44)*N44 -> 0 | AJ44: =(G44/H44)*O44 -> 0 | AK44: =(G44/H44)*P44 -> 0 | AL44: =(G44/H44)*Q44 -> 0 | AM44: =(G44/H44)*R44 -> 0 | AN44: =(G44/H44)*S44 -> 0 | AO44: =(G44/H44)*T44 -> 0 | AP44: =(G44/H44)*U44 -> 0 | AQ44: =(G44/H44)*V44 -> 0 | AR44: =SUM(AG44:AQ44)*0.08 -> 178440 | AS44: =SUM(AG44:AR44) -> 2408940 | AT44: =AS44 -> 2408940 | AU44: =AA44 -> CÁT LÁI | AV44: LCL | AW44: ADCDNB-26.02-000378 | AX44: , từ Cảng Cát Lái đến KCN Bàu Xéo, Đồng Nai | AY44: 46058
A45: PS260776 | B45: VY260129TTTL | C45: 112600036989361 | D45: 46057 | E45: 107959084440 | F45: 1 | G45: 2109.1 | H45: 2109.1 | L45: {=IF(H45=0, _xleta.T, IF(H45<=1000, 1290000, IF(H45<=2000, 1460000, IF(H45<=3000, 2186000, IF(H45<=5000, 2296000, ff)))))} -> 2186000 | M45: 940500 | Z45: 50H69181 | AA45: THÀNH LONG | AB45: =A45 -> PS260776 | AC45: =B45 -> VY260129TTTL | AD45: =D45 -> 46057 | AE45: =G45/H45*J45 -> 0 | AF45: =(G45/H45)*K45 -> 0 | AG45: =(G45/H45)*L45 -> 2186000 | AH45: =(G45/H45)*M45 -> 940500 | AI45: =(G45/H45)*N45 -> 0 | AJ45: =(G45/H45)*O45 -> 0 | AK45: =(G45/H45)*P45 -> 0 | AL45: =(G45/H45)*Q45 -> 0 | AM45: =(G45/H45)*R45 -> 0 | AN45: =(G45/H45)*S45 -> 0 | AO45: =(G45/H45)*T45 -> 0 | AP45: =(G45/H45)*U45 -> 0 | AQ45: =(G45/H45)*V45 -> 0 | AR45: =SUM(AG45:AQ45)*0.08 -> 250120 | AS45: =SUM(AG45:AR45) -> 3376620 | AT45: =AS45 -> 3376620 | AU45: =AA45 -> THÀNH LONG | AV45: LCL | AW45: ADCDNB-26.02-000630 | AX45: , từ Thành Long đến KCN Bàu Xéo, Đồng Nai | AY45: 46058 | AZ45: 50H69181 | BA45: 1 X 5MT
A46: PS260820 | B46: PS26-820 | C46: 112600036810693 | D46: 46057 | E46: 107957665060 | F46: 1 | G46: 632.64 | H46: 632.64 | M46: 389500 | AA46: KNQ LF LOGISTICS | AB46: =A46 -> PS260820 | AC46: =B46 -> PS26-820 | AD46: =D46 -> 46057 | AE46: =G46/H46*J46 -> 0 | AF46: =(G46/H46)*K46 -> 0 | AG46: =(G46/H46)*L46 -> 0 | AH46: =(G46/H46)*M46 -> 389500 | AI46: =(G46/H46)*N46 -> 0 | AJ46: =(G46/H46)*O46 -> 0 | AK46: =(G46/H46)*P46 -> 0 | AL46: =(G46/H46)*Q46 -> 0 | AM46: =(G46/H46)*R46 -> 0 | AN46: =(G46/H46)*S46 -> 0 | AO46: =(G46/H46)*T46 -> 0 | AP46: =(G46/H46)*U46 -> 0 | AQ46: =(G46/H46)*V46 -> 0 | AR46: =SUM(AG46:AQ46)*0.08 -> 31160 | AS46: =SUM(AG46:AR46) -> 420660 | AT46: =AS46 -> 420660 | AU46: =AA46 -> KNQ LF LOGISTICS | AV46: LCL-KNQ | AW46: ADCDNB-26.02-000593
A47: PS260787 | B47: 0885016367 | C47: 2HCC8SN101HC7510 | D47: 46057 | E47: 107951038160 | F47: 1 | G47: 240 | H47: 240 | I47: 0.16 | L47: {=IF(H47=0, _xleta.T, IF(H47<=1000, 1290000, IF(H47<=2000, 1460000, IF(H47<=3000, 2186000, IF(H47<=5000, 2296000, ff)))))} -> 1290000 | M47: 940500 | Z47: 50E52902 | AA47: CÁT LÁI | AB47: =A47 -> PS260787 | AC47: =B47 -> 0885016367 | AD47: =D47 -> 46057 | AE47: =G47/H47*J47 -> 0 | AF47: =(G47/H47)*K47 -> 0 | AG47: =(G47/H47)*L47 -> 1290000 | AH47: =(G47/H47)*M47 -> 940500 | AI47: =(G47/H47)*N47 -> 0 | AJ47: =(G47/H47)*O47 -> 0 | AK47: =(G47/H47)*P47 -> 0 | AL47: =(G47/H47)*Q47 -> 0 | AM47: =(G47/H47)*R47 -> 0 | AN47: =(G47/H47)*S47 -> 0 | AO47: =(G47/H47)*T47 -> 0 | AP47: =(G47/H47)*U47 -> 0 | AQ47: =(G47/H47)*V47 -> 0 | AR47: =SUM(AG47:AQ47)*0.08 -> 178440 | AS47: =SUM(AG47:AR47) -> 2408940 | AT47: =AS47 -> 2408940 | AU47: =AA47 -> CÁT LÁI | AV47: LCL | AW47: ADCDNB-26.02-000891 | AX47: , từ Cảng Cát Lái đến KCN Bàu Xéo, Đồng Nai | AY47: 46059 | AZ47: 50E52902 | BA47: 1 X 1MT
A48: PS260887 | B48: INV-26011247 | C48: SBS80010946 | D48: 46058 | E48: 107961132310 | F48: 1 | G48: 81.8 | H48: 81.8 | L48: =IF(H48<=50,1060000, IF(H48<=200, 1210000, IF(H48<=500, 1230000, IF(H48<=1000, 1440000, IF(H48<=2000, 1990000, IF(H48>2000, 1990000+(H48-2000)*1464)))))) -> 1210000 | M48: 940500 | Z48: 50E54467 | AA48: TCS | AB48: =A48 -> PS260887 | AC48: =B48 -> INV-26011247 | AD48: =D48 -> 46058 | AE48: =G48/H48*J48 -> 0 | AF48: =(G48/H48)*K48 -> 0 | AG48: =(G48/H48)*L48 -> 1210000 | AH48: =(G48/H48)*M48 -> 940500 | AI48: =(G48/H48)*N48 -> 0 | AJ48: =(G48/H48)*O48 -> 0 | AK48: =(G48/H48)*P48 -> 0 | AL48: =(G48/H48)*Q48 -> 0 | AM48: =(G48/H48)*R48 -> 0 | AN48: =(G48/H48)*S48 -> 0 | AO48: =(G48/H48)*T48 -> 0 | AP48: =(G48/H48)*U48 -> 0 | AQ48: =(G48/H48)*V48 -> 0 | AR48: =SUM(AG48:AQ48)*0.08 -> 172040 | AS48: =SUM(AG48:AR48) -> 2322540 | AT48: =AS48 -> 2322540 | AU48: =AA48 -> TCS | AV48: AIR | AW48: ADCDNB-26.02-000861 | AX48: , từ Kho TCS đến KCN Bàu Xéo , Đồng Nai | AY48: 46059 | AZ48: 50E54467 | BA48: 1 X 1MT
A49: PS260891 | B49: 5223535 | C49: SNC20260075 | D49: 46058 | E49: 107961155630 | F49: 1 | G49: 95 | H49: 95 | L49: =IF(H49<=50,1060000, IF(H49<=200, 1210000, IF(H49<=500, 1230000, IF(H49<=1000, 1440000, IF(H49<=2000, 1990000, IF(H49>2000, 1990000+(H49-2000)*1464)))))) -> 1210000 | M49: 940500 | Z49: 50E54467 | AA49: TCS | AB49: =A49 -> PS260891 | AC49: =B49 -> 5223535 | AD49: =D49 -> 46058 | AE49: =G49/H49*J49 -> 0 | AF49: =(G49/H49)*K49 -> 0 | AG49: =(G49/H49)*L49 -> 1210000 | AH49: =(G49/H49)*M49 -> 940500 | AI49: =(G49/H49)*N49 -> 0 | AJ49: =(G49/H49)*O49 -> 0 | AK49: =(G49/H49)*P49 -> 0 | AL49: =(G49/H49)*Q49 -> 0 | AM49: =(G49/H49)*R49 -> 0 | AN49: =(G49/H49)*S49 -> 0 | AO49: =(G49/H49)*T49 -> 0 | AP49: =(G49/H49)*U49 -> 0 | AQ49: =(G49/H49)*V49 -> 0 | AR49: =SUM(AG49:AQ49)*0.08 -> 172040 | AS49: =SUM(AG49:AR49) -> 2322540 | AT49: =AS49 -> 2322540 | AU49: =AA49 -> TCS | AV49: AIR | AW49: ADCDNB-26.02-000890 | AX49: , từ Kho TCS đến KCN Bàu Xéo , Đồng Nai | AY49: 46059
A50: PS260911 | B50: IV260200118 | C50: XMNA007373 | D50: 46058 | E50: 107961654360 | F50: 1 | G50: 307 | H50: 307 | L50: =IF(H50<=50,1060000, IF(H50<=200, 1210000, IF(H50<=500, 1230000, IF(H50<=1000, 1440000, IF(H50<=2000, 1990000, IF(H50>2000, 1990000+(H50-2000)*1464)))))) -> 1230000 | M50: 940500 | Z50: 50E54467 | AA50: SCSC | AB50: =A50 -> PS260911 | AC50: =B50 -> IV260200118 | AD50: =D50 -> 46058 | AE50: =G50/H50*J50 -> 0 | AF50: =(G50/H50)*K50 -> 0 | AG50: =(G50/H50)*L50 -> 1230000 | AH50: =(G50/H50)*M50 -> 940500 | AI50: =(G50/H50)*N50 -> 0 | AJ50: =(G50/H50)*O50 -> 0 | AK50: =(G50/H50)*P50 -> 0 | AL50: =(G50/H50)*Q50 -> 0 | AM50: =(G50/H50)*R50 -> 0 | AN50: =(G50/H50)*S50 -> 0 | AO50: =(G50/H50)*T50 -> 0 | AP50: =(G50/H50)*U50 -> 0 | AQ50: =(G50/H50)*V50 -> 0 | AR50: =SUM(AG50:AQ50)*0.08 -> 173640 | AS50: =SUM(AG50:AR50) -> 2344140 | AT50: =AS50 -> 2344140 | AU50: =AA50 -> SCSC | AV50: AIR | AW50: ADCDNB-26.02-000520 | AX50: , từ Kho SCSC đến KCN Bàu Xéo , Đồng Nai | AY50: 46059
A51: PS260751 | B51: T260125-Y1 | C51: SPOE2601139 | D51: 46057 | E51: 107951389710 | F51: 1 | G51: 104.35 | H51: 104.35 | I51: 0.342 | L51: {=IF(H51=0, _xleta.T, IF(H51<=1000, 1290000, IF(H51<=2000, 1460000, IF(H51<=3000, 2186000, IF(H51<=5000, 2296000, ff)))))} -> 1290000 | M51: 940500 | Z51: 50H69104 | AA51: CÁT LÁI | AB51: =A51 -> PS260751 | AC51: =B51 -> T260125-Y1 | AD51: =D51 -> 46057 | AE51: =G51/H51*J51 -> 0 | AF51: =(G51/H51)*K51 -> 0 | AG51: =(G51/H51)*L51 -> 1290000 | AH51: =(G51/H51)*M51 -> 940500 | AI51: =(G51/H51)*N51 -> 0 | AJ51: =(G51/H51)*O51 -> 0 | AK51: =(G51/H51)*P51 -> 0 | AL51: =(G51/H51)*Q51 -> 0 | AM51: =(G51/H51)*R51 -> 0 | AN51: =(G51/H51)*S51 -> 0 | AO51: =(G51/H51)*T51 -> 0 | AP51: =(G51/H51)*U51 -> 0 | AQ51: =(G51/H51)*V51 -> 0 | AR51: =SUM(AG51:AQ51)*0.08 -> 178440 | AS51: =SUM(AG51:AR51) -> 2408940 | AT51: =AS51 -> 2408940 | AU51: =AA51 -> CÁT LÁI | AV51: LCL | AW51: ADCDNB-26.02-000612 | AX51: , từ Cảng Cát Lái đến KCN Bàu Xéo, Đồng Nai | AY51: 46059 | AZ51: 50H69104 | BA51: 1 X 1MT
A52: PS260813 | B52: PS26-813 | C52: 20SEA26010140 | D52: 46058 | E52: 107961575520 | F52: 1 | G52: 238.38 | H52: 238.38 | I52: 0.494 | L52: {=IF(H52=0, _xleta.T, IF(H52<=1000, 1290000, IF(H52<=2000, 1460000, IF(H52<=3000, 2186000, IF(H52<=5000, 2296000, ff)))))} -> 1290000 | M52: 940500 | AA52: CÁT LÁI | AB52: =A52 -> PS260813 | AC52: =B52 -> PS26-813 | AD52: =D52 -> 46058 | AE52: =G52/H52*J52 -> 0 | AF52: =(G52/H52)*K52 -> 0 | AG52: =(G52/H52)*L52 -> 1290000 | AH52: =(G52/H52)*M52 -> 940500 | AI52: =(G52/H52)*N52 -> 0 | AJ52: =(G52/H52)*O52 -> 0 | AK52: =(G52/H52)*P52 -> 0 | AL52: =(G52/H52)*Q52 -> 0 | AM52: =(G52/H52)*R52 -> 0 | AN52: =(G52/H52)*S52 -> 0 | AO52: =(G52/H52)*T52 -> 0 | AP52: =(G52/H52)*U52 -> 0 | AQ52: =(G52/H52)*V52 -> 0 | AR52: =SUM(AG52:AQ52)*0.08 -> 178440 | AS52: =SUM(AG52:AR52) -> 2408940 | AT52: =AS52 -> 2408940 | AU52: =AA52 -> CÁT LÁI | AV52: LCL | AW52: ADCDNB-26.02-000873 | AX52: , từ Cảng Cát Lái đến KCN Bàu Xéo, Đồng Nai | AY52: 46059
A53: PS260851 | B53: HP2312G | C53: SZHTHCM2601121 | D53: 46058 | E53: 107960948540 | F53: 1 | G53: 1696.5 | H53: 1696.5 | I53: 3.84 | L53: {=IF(H53=0, _xleta.T, IF(H53<=1000, 1290000, IF(H53<=2000, 1460000, IF(H53<=3000, 2186000, IF(H53<=5000, 2296000, ff)))))} -> 1460000 | M53: 940500 | Z53: 50H69559 | AA53: TÂN CẢNG PHÚ HỮU | AB53: =A53 -> PS260851 | AC53: =B53 -> HP2312G | AD53: =D53 -> 46058 | AE53: =G53/H53*J53 -> 0 | AF53: =(G53/H53)*K53 -> 0 | AG53: =(G53/H53)*L53 -> 1460000 | AH53: =(G53/H53)*M53 -> 940500 | AI53: =(G53/H53)*N53 -> 0 | AJ53: =(G53/H53)*O53 -> 0 | AK53: =(G53/H53)*P53 -> 0 | AL53: =(G53/H53)*Q53 -> 0 | AM53: =(G53/H53)*R53 -> 0 | AN53: =(G53/H53)*S53 -> 0 | AO53: =(G53/H53)*T53 -> 0 | AP53: =(G53/H53)*U53 -> 0 | AQ53: =(G53/H53)*V53 -> 0 | AR53: =SUM(AG53:AQ53)*0.08 -> 192040 | AS53: =SUM(AG53:AR53) -> 2592540 | AT53: =AS53 -> 2592540 | AU53: =AA53 -> TÂN CẢNG PHÚ HỮU | AV53: LCL | AW53: ADCDNB-26.02-000415 | AX53: , từ Tân Cảng Phú Hữu đến KCN Bàu Xéo, Đồng Nai | AY53: 46059 | AZ53: 50H69559 | BA53: 1 X 2MT
A54: PS260849 | B54: XR20260127001 | C54: DGPE26010290 | D54: 46057 | E54: 107956924830 | F54: 1 | G54: 242.7 | H54: 242.7 | I54: 1.163 | L54: {=IF(H54=0, _xleta.T, IF(H54<=1000, 1290000, IF(H54<=2000, 1460000, IF(H54<=3000, 2186000, IF(H54<=5000, 2296000, ff)))))} -> 1290000 | M54: 940500 | Z54: 50H69181 | AA54: CÁT LÁI | AB54: =A54 -> PS260849 | AC54: =B54 -> XR20260127001 | AD54: =D54 -> 46057 | AE54: =G54/H54*J54 -> 0 | AF54: =(G54/H54)*K54 -> 0 | AG54: =(G54/H54)*L54 -> 1290000 | AH54: =(G54/H54)*M54 -> 940500 | AI54: =(G54/H54)*N54 -> 0 | AJ54: =(G54/H54)*O54 -> 0 | AK54: =(G54/H54)*P54 -> 0 | AL54: =(G54/H54)*Q54 -> 0 | AM54: =(G54/H54)*R54 -> 0 | AN54: =(G54/H54)*S54 -> 0 | AO54: =(G54/H54)*T54 -> 0 | AP54: =(G54/H54)*U54 -> 0 | AQ54: =(G54/H54)*V54 -> 0 | AR54: =SUM(AG54:AQ54)*0.08 -> 178440 | AS54: =SUM(AG54:AR54) -> 2408940 | AT54: =AS54 -> 2408940 | AU54: =AA54 -> CÁT LÁI | AV54: LCL | AW54: ADCDNB-26.02-000414 | AX54: , từ Cảng Cát Lái đến KCN Bàu Xéo, Đồng Nai | AY54: 46059 | AZ54: 50H69181 | BA54: 1 X 5MT
A55: PS260838 | B55: IV260102270 | C55: LXMHCM26011481 | D55: 46057 | E55: 107956924240 | F55: 1 | G55: 575.67 | H55: 575.67 | I55: 2.05 | L55: {=IF(H55=0, _xleta.T, IF(H55<=1000, 1290000, IF(H55<=2000, 1460000, IF(H55<=3000, 2186000, IF(H55<=5000, 2296000, ff)))))} -> 1290000 | M55: 940500 | Z55: 50H69181 | AA55: CÁT LÁI | AB55: =A55 -> PS260838 | AC55: =B55 -> IV260102270 | AD55: =D55 -> 46057 | AE55: =G55/H55*J55 -> 0 | AF55: =(G55/H55)*K55 -> 0 | AG55: =(G55/H55)*L55 -> 1290000 | AH55: =(G55/H55)*M55 -> 940500 | AI55: =(G55/H55)*N55 -> 0 | AJ55: =(G55/H55)*O55 -> 0 | AK55: =(G55/H55)*P55 -> 0 | AL55: =(G55/H55)*Q55 -> 0 | AM55: =(G55/H55)*R55 -> 0 | AN55: =(G55/H55)*S55 -> 0 | AO55: =(G55/H55)*T55 -> 0 | AP55: =(G55/H55)*U55 -> 0 | AQ55: =(G55/H55)*V55 -> 0 | AR55: =SUM(AG55:AQ55)*0.08 -> 178440 | AS55: =SUM(AG55:AR55) -> 2408940 | AT55: =AS55 -> 2408940 | AU55: =AA55 -> CÁT LÁI | AV55: LCL | AW55: ADCDNB-26.02-000379 | AX55: , từ Cảng Cát Lái đến KCN Bàu Xéo, Đồng Nai | AY55: 46059
A56: PS260850 | B56: DL20260126 | C56: DGPE26010285 | D56: 46057 | E56: 107956926600 | F56: 1 | G56: 1182.1 | H56: 1182.1 | I56: 5.891 | L56: {=IF(H56=0, _xleta.T, IF(H56<=1000, 1290000, IF(H56<=2000, 1460000, IF(H56<=3000, 2186000, IF(H56<=5000, 2296000, ff)))))} -> 1460000 | M56: 940500 | Z56: 50H69181 | AA56: CÁT LÁI | AB56: =A56 -> PS260850 | AC56: =B56 -> DL20260126 | AD56: =D56 -> 46057 | AE56: =G56/H56*J56 -> 0 | AF56: =(G56/H56)*K56 -> 0 | AG56: =(G56/H56)*L56 -> 1460000 | AH56: =(G56/H56)*M56 -> 940500 | AI56: =(G56/H56)*N56 -> 0 | AJ56: =(G56/H56)*O56 -> 0 | AK56: =(G56/H56)*P56 -> 0 | AL56: =(G56/H56)*Q56 -> 0 | AM56: =(G56/H56)*R56 -> 0 | AN56: =(G56/H56)*S56 -> 0 | AO56: =(G56/H56)*T56 -> 0 | AP56: =(G56/H56)*U56 -> 0 | AQ56: =(G56/H56)*V56 -> 0 | AR56: =SUM(AG56:AQ56)*0.08 -> 192040 | AS56: =SUM(AG56:AR56) -> 2592540 | AT56: =AS56 -> 2592540 | AU56: =AA56 -> CÁT LÁI | AV56: LCL | AW56: ADCDNB-26.02-000413 | AX56: , từ Cảng Cát Lái đến KCN Bàu Xéo, Đồng Nai | AY56: 46059
A57: PS260888 | B57: 5227537 | C57: 122600037080423 | D57: 46059 | E57: 107965223330 | F57: 1 | G57: 1520.9 | H57: 1520.9 | L57: {=IF(H57=0, _xleta.T, IF(H57<=1000, 1290000, IF(H57<=2000, 1460000, IF(H57<=3000, 2186000, IF(H57<=5000, 2296000, ff)))))} -> 1460000 | M57: 940500 | Z57: 50E52902 | AA57: THÀNH LONG | AB57: =A57 -> PS260888 | AC57: =B57 -> 5227537 | AD57: =D57 -> 46059 | AE57: =G57/H57*J57 -> 0 | AF57: =(G57/H57)*K57 -> 0 | AG57: =(G57/H57)*L57 -> 1460000 | AH57: =(G57/H57)*M57 -> 940500 | AI57: =(G57/H57)*N57 -> 0 | AJ57: =(G57/H57)*O57 -> 0 | AK57: =(G57/H57)*P57 -> 0 | AL57: =(G57/H57)*Q57 -> 0 | AM57: =(G57/H57)*R57 -> 0 | AN57: =(G57/H57)*S57 -> 0 | AO57: =(G57/H57)*T57 -> 0 | AP57: =(G57/H57)*U57 -> 0 | AQ57: =(G57/H57)*V57 -> 0 | AR57: =SUM(AG57:AQ57)*0.08 -> 192040 | AS57: =SUM(AG57:AR57) -> 2592540 | AT57: =AS57 -> 2592540 | AU57: =AA57 -> THÀNH LONG | AV57: LCL | AW57: ADCDNB-26.02-001019 | AX57: , từ Thành Long đến KCN Bàu Xéo, Đồng Nai | AY57: 46060 | AZ57: 50E52902 | BA57: 1 X 2MT
A58: PS260889 | B58: 5227539 | C58: 112600037080829 | D58: 46059 | E58: 107965249600 | F58: 1 | G58: 1475.5 | H58: 1475.5 | L58: {=IF(H58=0, _xleta.T, IF(H58<=1000, 1290000, IF(H58<=2000, 1460000, IF(H58<=3000, 2186000, IF(H58<=5000, 2296000, ff)))))} -> 1460000 | M58: 940500 | Z58: 50E46291 | AA58: THÀNH LONG | AB58: =A58 -> PS260889 | AC58: =B58 -> 5227539 | AD58: =D58 -> 46059 | AE58: =G58/H58*J58 -> 0 | AF58: =(G58/H58)*K58 -> 0 | AG58: =(G58/H58)*L58 -> 1460000 | AH58: =(G58/H58)*M58 -> 940500 | AI58: =(G58/H58)*N58 -> 0 | AJ58: =(G58/H58)*O58 -> 0 | AK58: =(G58/H58)*P58 -> 0 | AL58: =(G58/H58)*Q58 -> 0 | AM58: =(G58/H58)*R58 -> 0 | AN58: =(G58/H58)*S58 -> 0 | AO58: =(G58/H58)*T58 -> 0 | AP58: =(G58/H58)*U58 -> 0 | AQ58: =(G58/H58)*V58 -> 0 | AR58: =SUM(AG58:AQ58)*0.08 -> 192040 | AS58: =SUM(AG58:AR58) -> 2592540 | AT58: =AS58 -> 2592540 | AU58: =AA58 -> THÀNH LONG | AV58: LCL | AW58: ADCDNB-26.02-001020 | AX58: , từ Thành Long đến KCN Bàu Xéo, Đồng Nai | AY58: 46060 | AZ58: 50E46291 | BA58: 1 X 2MT
A59: PS260890 | B59: 5227536 | C59: 112600037081243 | D59: 46059 | E59: 107965290310 | F59: 1 | G59: 2524.5 | H59: 2524.5 | L59: {=IF(H59=0, _xleta.T, IF(H59<=1000, 1290000, IF(H59<=2000, 1460000, IF(H59<=3000, 2186000, IF(H59<=5000, 2296000, ff)))))} -> 2186000 | M59: 940500 | Z59: 50H70505 | AA59: THÀNH LONG | AB59: =A59 -> PS260890 | AC59: =B59 -> 5227536 | AD59: =D59 -> 46059 | AE59: =G59/H59*J59 -> 0 | AF59: =(G59/H59)*K59 -> 0 | AG59: =(G59/H59)*L59 -> 2186000 | AH59: =(G59/H59)*M59 -> 940500 | AI59: =(G59/H59)*N59 -> 0 | AJ59: =(G59/H59)*O59 -> 0 | AK59: =(G59/H59)*P59 -> 0 | AL59: =(G59/H59)*Q59 -> 0 | AM59: =(G59/H59)*R59 -> 0 | AN59: =(G59/H59)*S59 -> 0 | AO59: =(G59/H59)*T59 -> 0 | AP59: =(G59/H59)*U59 -> 0 | AQ59: =(G59/H59)*V59 -> 0 | AR59: =SUM(AG59:AQ59)*0.08 -> 250120 | AS59: =SUM(AG59:AR59) -> 3376620 | AT59: =AS59 -> 3376620 | AU59: =AA59 -> THÀNH LONG | AV59: LCL | AW59: ADCDNB-26.02-001021 | AX59: , từ Thành Long đến KCN Bàu Xéo, Đồng Nai | AY59: 46060 | AZ59: 50H70505 | BA59: 1 X 5MT
A60: PS260908 | B60: 0885103500 | C60: JWE5150203 | D60: 46058 | E60: 107961540630 | F60: 2 | G60: 130 | H60: 130 | L60: =IF(H60<=50,1060000, IF(H60<=200, 1210000, IF(H60<=500, 1230000, IF(H60<=1000, 1440000, IF(H60<=2000, 1990000, IF(H60>2000, 1990000+(H60-2000)*1464)))))) -> 1210000 | M60: =940500+70000 -> 1010500 | Z60: 50H70505 | AA60: TCS | AB60: =A60 -> PS260908 | AC60: =B60 -> 0885103500 | AD60: =D60 -> 46058 | AE60: =G60/H60*J60 -> 0 | AF60: =(G60/H60)*K60 -> 0 | AG60: =(G60/H60)*L60 -> 1210000 | AH60: =(G60/H60)*M60 -> 1010500 | AI60: =(G60/H60)*N60 -> 0 | AJ60: =(G60/H60)*O60 -> 0 | AK60: =(G60/H60)*P60 -> 0 | AL60: =(G60/H60)*Q60 -> 0 | AM60: =(G60/H60)*R60 -> 0 | AN60: =(G60/H60)*S60 -> 0 | AO60: =(G60/H60)*T60 -> 0 | AP60: =(G60/H60)*U60 -> 0 | AQ60: =(G60/H60)*V60 -> 0 | AR60: =SUM(AG60:AQ60)*0.08 -> 177640 | AS60: =SUM(AG60:AR60) -> 2398140 | AT60: =AS60 -> 2398140 | AU60: =AA60 -> TCS | AV60: AIR | AW60: ADCDNB-26.02-000855 | AX60: , từ Kho TCS đến KCN Bàu Xéo , Đồng Nai | AY60: 46060 | AZ60: 50H70505 | BA60: 1 X 1MT
A61: PS260908 | B61: 0885103500 | C61: JWE5150203 | D61: 46058 | E61: 107961578800 | H61: 130 | L61: =IF(H61<=50,1060000, IF(H61<=200, 1210000, IF(H61<=500, 1230000, IF(H61<=1000, 1440000, IF(H61<=2000, 1990000, IF(H61>2000, 1990000+(H61-2000)*1464)))))) -> 1210000 | M61: =940500+70000 -> 1010500 | Z61: 50H70505 | AA61: TCS | AB61: =A61 -> PS260908 | AC61: =B61 -> 0885103500 | AD61: =D61 -> 46058 | AE61: =G61/H61*J61 -> 0 | AF61: =(G61/H61)*K61 -> 0 | AG61: =(G61/H61)*L61 -> 0 | AH61: =(G61/H61)*M61 -> 0 | AI61: =(G61/H61)*N61 -> 0 | AJ61: =(G61/H61)*O61 -> 0 | AK61: =(G61/H61)*P61 -> 0 | AL61: =(G61/H61)*Q61 -> 0 | AM61: =(G61/H61)*R61 -> 0 | AN61: =(G61/H61)*S61 -> 0 | AO61: =(G61/H61)*T61 -> 0 | AP61: =(G61/H61)*U61 -> 0 | AQ61: =(G61/H61)*V61 -> 0 | AR61: =SUM(AG61:AQ61)*0.08 -> 0 | AS61: =SUM(AG61:AR61) -> 0 | AT61: =AS61 -> 0 | AU61: =AA61 -> TCS | AV61: AIR | AW61: ADCDNB-26.02-000855 | AX61: , từ Kho TCS đến KCN Bàu Xéo , Đồng Nai | AY61: 46060
A62: PS260905 | B62: PC260204VY | C62: JWE5150211 | D62: 46058 | E62: 107960939810 | F62: 1 | G62: 32 | H62: 32 | L62: =IF(H62<=50,1060000, IF(H62<=200, 1210000, IF(H62<=500, 1230000, IF(H62<=1000, 1440000, IF(H62<=2000, 1990000, IF(H62>2000, 1990000+(H62-2000)*1464)))))) -> 1060000 | M62: 940500 | Z62: 50H70505 | AA62: TCS | AB62: =A62 -> PS260905 | AC62: =B62 -> PC260204VY | AD62: =D62 -> 46058 | AE62: =G62/H62*J62 -> 0 | AF62: =(G62/H62)*K62 -> 0 | AG62: =(G62/H62)*L62 -> 1060000 | AH62: =(G62/H62)*M62 -> 940500 | AI62: =(G62/H62)*N62 -> 0 | AJ62: =(G62/H62)*O62 -> 0 | AK62: =(G62/H62)*P62 -> 0 | AL62: =(G62/H62)*Q62 -> 0 | AM62: =(G62/H62)*R62 -> 0 | AN62: =(G62/H62)*S62 -> 0 | AO62: =(G62/H62)*T62 -> 0 | AP62: =(G62/H62)*U62 -> 0 | AQ62: =(G62/H62)*V62 -> 0 | AR62: =SUM(AG62:AQ62)*0.08 -> 160040 | AS62: =SUM(AG62:AR62) -> 2160540 | AT62: =AS62 -> 2160540 | AU62: =AA62 -> TCS | AV62: AIR | AW62: ADCDNB-26.02-000856 | AX62: , từ Kho TCS đến KCN Bàu Xéo , Đồng Nai | AY62: 46060
A63: PS260900 | B63: IE26020013 | C63: 2476695782 | D63: 46058 | E63: 107961531310 | F63: 1 | G63: 53 | H63: 53 | M63: 570000 | AA63: DHL | AB63: =A63 -> PS260900 | AC63: =B63 -> IE26020013 | AD63: =D63 -> 46058 | AE63: =G63/H63*J63 -> 0 | AF63: =(G63/H63)*K63 -> 0 | AG63: =(G63/H63)*L63 -> 0 | AH63: =(G63/H63)*M63 -> 570000 | AI63: =(G63/H63)*N63 -> 0 | AJ63: =(G63/H63)*O63 -> 0 | AK63: =(G63/H63)*P63 -> 0 | AL63: =(G63/H63)*Q63 -> 0 | AM63: =(G63/H63)*R63 -> 0 | AN63: =(G63/H63)*S63 -> 0 | AO63: =(G63/H63)*T63 -> 0 | AP63: =(G63/H63)*U63 -> 0 | AQ63: =(G63/H63)*V63 -> 0 | AR63: =SUM(AG63:AQ63)*0.08 -> 45600 | AS63: =SUM(AG63:AR63) -> 615600 | AT63: =AS63 -> 615600 | AU63: =AA63 -> DHL | AV63: EXP | AW63: ADCDNB-26.02-000881
A64: PS260895 | B64: DSHK2026020301 | C64: 5163261596 | D64: 46058 | E64: 107961504450 | F64: 1 | G64: 0.2 | H64: 0.2 | M64: 570000 | AA64: DHL | AB64: =A64 -> PS260895 | AC64: =B64 -> DSHK2026020301 | AD64: =D64 -> 46058 | AE64: =G64/H64*J64 -> 0 | AF64: =(G64/H64)*K64 -> 0 | AG64: =(G64/H64)*L64 -> 0 | AH64: =(G64/H64)*M64 -> 570000 | AI64: =(G64/H64)*N64 -> 0 | AJ64: =(G64/H64)*O64 -> 0 | AK64: =(G64/H64)*P64 -> 0 | AL64: =(G64/H64)*Q64 -> 0 | AM64: =(G64/H64)*R64 -> 0 | AN64: =(G64/H64)*S64 -> 0 | AO64: =(G64/H64)*T64 -> 0 | AP64: =(G64/H64)*U64 -> 0 | AQ64: =(G64/H64)*V64 -> 0 | AR64: =SUM(AG64:AQ64)*0.08 -> 45600 | AS64: =SUM(AG64:AR64) -> 615600 | AT64: =AS64 -> 615600 | AU64: =AA64 -> DHL | AV64: EXP | AW64: ADCDNB-26.02-000882
A65: PS260916 | B65: 5229051 | C65: 1138362116 | D65: 46058 | E65: 107963121230 | F65: 1 | G65: 15 | H65: 15 | M65: 570000 | AA65: DHL | AB65: =A65 -> PS260916 | AC65: =B65 -> 5229051 | AD65: =D65 -> 46058 | AE65: =G65/H65*J65 -> 0 | AF65: =(G65/H65)*K65 -> 0 | AG65: =(G65/H65)*L65 -> 0 | AH65: =(G65/H65)*M65 -> 570000 | AI65: =(G65/H65)*N65 -> 0 | AJ65: =(G65/H65)*O65 -> 0 | AK65: =(G65/H65)*P65 -> 0 | AL65: =(G65/H65)*Q65 -> 0 | AM65: =(G65/H65)*R65 -> 0 | AN65: =(G65/H65)*S65 -> 0 | AO65: =(G65/H65)*T65 -> 0 | AP65: =(G65/H65)*U65 -> 0 | AQ65: =(G65/H65)*V65 -> 0 | AR65: =SUM(AG65:AQ65)*0.08 -> 45600 | AS65: =SUM(AG65:AR65) -> 615600 | AT65: =AS65 -> 615600 | AU65: =AA65 -> DHL | AV65: EXP | AW65: ADCDNB-26.02-001051
A66: PS260940 | B66: 260203-01 | C66: 5163206904 | D66: 46059 | E66: 107965195660 | F66: 1 | G66: 0.4 | H66: 0.4 | M66: 570000 | AA66: DHL | AB66: =A66 -> PS260940 | AC66: =B66 -> 260203-01 | AD66: =D66 -> 46059 | AE66: =G66/H66*J66 -> 0 | AF66: =(G66/H66)*K66 -> 0 | AG66: =(G66/H66)*L66 -> 0 | AH66: =(G66/H66)*M66 -> 570000 | AI66: =(G66/H66)*N66 -> 0 | AJ66: =(G66/H66)*O66 -> 0 | AK66: =(G66/H66)*P66 -> 0 | AL66: =(G66/H66)*Q66 -> 0 | AM66: =(G66/H66)*R66 -> 0 | AN66: =(G66/H66)*S66 -> 0 | AO66: =(G66/H66)*T66 -> 0 | AP66: =(G66/H66)*U66 -> 0 | AQ66: =(G66/H66)*V66 -> 0 | AR66: =SUM(AG66:AQ66)*0.08 -> 45600 | AS66: =SUM(AG66:AR66) -> 615600 | AT66: =AS66 -> 615600 | AU66: =AA66 -> DHL | AV66: EXP | AW66: ADCDNB-26.02-001052
A67: PS260901 | B67: YCT260127-60 | C67: LPEX2601669 | D67: 46059 | E67: 107965649850 | F67: 1 | G67: 22 | H67: 22 | I67: 0.066 | L67: {=IF(H67=0, _xleta.T, IF(H67<=1000, 1290000, IF(H67<=2000, 1460000, IF(H67<=3000, 2186000, IF(H67<=5000, 2296000, ff)))))} -> 1290000 | M67: 940500 | Z67: 50H69181 | AA67: CÁT LÁI | AB67: =A67 -> PS260901 | AC67: =B67 -> YCT260127-60 | AD67: =D67 -> 46059 | AE67: =G67/H67*J67 -> 0 | AF67: =(G67/H67)*K67 -> 0 | AG67: =(G67/H67)*L67 -> 1290000 | AH67: =(G67/H67)*M67 -> 940500 | AI67: =(G67/H67)*N67 -> 0 | AJ67: =(G67/H67)*O67 -> 0 | AK67: =(G67/H67)*P67 -> 0 | AL67: =(G67/H67)*Q67 -> 0 | AM67: =(G67/H67)*R67 -> 0 | AN67: =(G67/H67)*S67 -> 0 | AO67: =(G67/H67)*T67 -> 0 | AP67: =(G67/H67)*U67 -> 0 | AQ67: =(G67/H67)*V67 -> 0 | AR67: =SUM(AG67:AQ67)*0.08 -> 178440 | AS67: =SUM(AG67:AR67) -> 2408940 | AT67: =AS67 -> 2408940 | AU67: =AA67 -> CÁT LÁI | AV67: LCL | AW67: ADCDNB-26.02-001054 | AX67: , từ Cảng Cát Lái đến KCN Bàu Xéo, Đồng Nai | AY67: 46060 | AZ67: 50H69181 | BA67: 1 X 2MT
A68: PS260840 | B68: T260129-Y1 | C68: SPOE2601155 | D68: 46058 | E68: 107961717840 | F68: 1 | G68: 3.86 | H68: 3.86 | I68: 0.036 | L68: {=IF(H68=0, _xleta.T, IF(H68<=1000, 1290000, IF(H68<=2000, 1460000, IF(H68<=3000, 2186000, IF(H68<=5000, 2296000, ff)))))} -> 1290000 | M68: 940500 | AA68: CÁT LÁI | AB68: =A68 -> PS260840 | AC68: =B68 -> T260129-Y1 | AD68: =D68 -> 46058 | AE68: =G68/H68*J68 -> 0 | AF68: =(G68/H68)*K68 -> 0 | AG68: =(G68/H68)*L68 -> 1290000 | AH68: =(G68/H68)*M68 -> 940500 | AI68: =(G68/H68)*N68 -> 0 | AJ68: =(G68/H68)*O68 -> 0 | AK68: =(G68/H68)*P68 -> 0 | AL68: =(G68/H68)*Q68 -> 0 | AM68: =(G68/H68)*R68 -> 0 | AN68: =(G68/H68)*S68 -> 0 | AO68: =(G68/H68)*T68 -> 0 | AP68: =(G68/H68)*U68 -> 0 | AQ68: =(G68/H68)*V68 -> 0 | AR68: =SUM(AG68:AQ68)*0.08 -> 178440 | AS68: =SUM(AG68:AR68) -> 2408940 | AT68: =AS68 -> 2408940 | AU68: =AA68 -> CÁT LÁI | AV68: LCL | AW68: ADCDNB-26.02-001055 | AX68: , từ Cảng Cát Lái đến KCN Bàu Xéo, Đồng Nai | AY68: 46060
A69: PS260816 | B69: IE26010493 | C69: 08SEA2601090 | D69: 46058 | E69: 107961610300 | F69: 1 | G69: 928 | H69: 928 | I69: 3.447 | L69: {=IF(H69=0, _xleta.T, IF(H69<=1000, 1290000, IF(H69<=2000, 1460000, IF(H69<=3000, 2186000, IF(H69<=5000, 2296000, ff)))))} -> 1290000 | M69: 940500 | Z69: 50H69181 | AA69: CÁT LÁI | AB69: =A69 -> PS260816 | AC69: =B69 -> IE26010493 | AD69: =D69 -> 46058 | AE69: =G69/H69*J69 -> 0 | AF69: =(G69/H69)*K69 -> 0 | AG69: =(G69/H69)*L69 -> 1290000 | AH69: =(G69/H69)*M69 -> 940500 | AI69: =(G69/H69)*N69 -> 0 | AJ69: =(G69/H69)*O69 -> 0 | AK69: =(G69/H69)*P69 -> 0 | AL69: =(G69/H69)*Q69 -> 0 | AM69: =(G69/H69)*R69 -> 0 | AN69: =(G69/H69)*S69 -> 0 | AO69: =(G69/H69)*T69 -> 0 | AP69: =(G69/H69)*U69 -> 0 | AQ69: =(G69/H69)*V69 -> 0 | AR69: =SUM(AG69:AQ69)*0.08 -> 178440 | AS69: =SUM(AG69:AR69) -> 2408940 | AT69: =AS69 -> 2408940 | AU69: =AA69 -> CÁT LÁI | AV69: LCL | AW69: ADCDNB-26.02-001056 | AX69: , từ Cảng Cát Lái đến KCN Bàu Xéo, Đồng Nai | AY69: 46060
A70: PS260872 | B70: HK20260127 | C70: 20SEA26010228 | D70: 46057 | E70: 107958196950 | F70: 1 | G70: 444.8 | H70: 444.8 | I70: 1.647 | L70: {=IF(H70=0, _xleta.T, IF(H70<=1000, 1290000, IF(H70<=2000, 1460000, IF(H70<=3000, 2186000, IF(H70<=5000, 2296000, ff)))))} -> 1290000 | M70: 940500 | Z70: 50H69104 | AA70: CÁT LÁI | AB70: =A70 -> PS260872 | AC70: =B70 -> HK20260127 | AD70: =D70 -> 46057 | AE70: =G70/H70*J70 -> 0 | AF70: =(G70/H70)*K70 -> 0 | AG70: =(G70/H70)*L70 -> 1290000 | AH70: =(G70/H70)*M70 -> 940500 | AI70: =(G70/H70)*N70 -> 0 | AJ70: =(G70/H70)*O70 -> 0 | AK70: =(G70/H70)*P70 -> 0 | AL70: =(G70/H70)*Q70 -> 0 | AM70: =(G70/H70)*R70 -> 0 | AN70: =(G70/H70)*S70 -> 0 | AO70: =(G70/H70)*T70 -> 0 | AP70: =(G70/H70)*U70 -> 0 | AQ70: =(G70/H70)*V70 -> 0 | AR70: =SUM(AG70:AQ70)*0.08 -> 178440 | AS70: =SUM(AG70:AR70) -> 2408940 | AT70: =AS70 -> 2408940 | AU70: =AA70 -> CÁT LÁI | AV70: LCL | AW70: ADCDNB-26.02-000597 | AX70: , từ Cảng Cát Lái đến KCN Bàu Xéo, Đồng Nai | AY70: 46060 | AZ70: 50H69104 | BA70: 1 X 1MT
A71: PS260832 | B71: 2601/153/VY | C71: HOEX26010278 | D71: 46057 | E71: 107959051800 | F71: 1 | G71: 2017.4 | H71: 2017.4 | I71: 7.864 | L71: {=IF(H71=0, _xleta.T, IF(H71<=1000, 1590000, IF(H71<=2000, 1760000, IF(H71<=3000, 2486000, IF(H71<=5000, 2596000, ff)))))} -> 2486000 | M71: 940500 | Z71: 50E52902 | AA71: SPITC | AB71: =A71 -> PS260832 | AC71: =B71 -> 2601/153/VY | AD71: =D71 -> 46057 | AE71: =G71/H71*J71 -> 0 | AF71: =(G71/H71)*K71 -> 0 | AG71: =(G71/H71)*L71 -> 2486000 | AH71: =(G71/H71)*M71 -> 940500 | AI71: =(G71/H71)*N71 -> 0 | AJ71: =(G71/H71)*O71 -> 0 | AK71: =(G71/H71)*P71 -> 0 | AL71: =(G71/H71)*Q71 -> 0 | AM71: =(G71/H71)*R71 -> 0 | AN71: =(G71/H71)*S71 -> 0 | AO71: =(G71/H71)*T71 -> 0 | AP71: =(G71/H71)*U71 -> 0 | AQ71: =(G71/H71)*V71 -> 0 | AR71: =SUM(AG71:AQ71)*0.08 -> 274120 | AS71: =SUM(AG71:AR71) -> 3700620 | AT71: =AS71 -> 3700620 | AU71: =AA71 -> SPITC | AV71: LCL | AW71: ADCDNB-26.02-000858 | AX71: , từ Cảng SPITC đến KCN Bàu Xéo, Đồng Nai | AY71: 46062 | AZ71: 50E52902 | BA71: 1 X 5MT
A72: PS26778 | B72: EBD-PSSP260129 | C72: Local | D72: 46056 | E72: 107946567520 | F72: 1 | M72: 389500 | AA72: Local | AB72: =A72 -> PS26778 | AC72: =B72 -> EBD-PSSP260129 | AD72: =D72 -> 46056 | AH72: =+M72 -> 389500 | AR72: =SUM(AG72:AQ72)*0.08 -> 31160 | AS72: =SUM(AG72:AR72) -> 420660 | AT72: =AS72 -> 420660 | AU72: =AA72 -> Local
A73: PS26781 | B73: VY/023-2026 | C73: Local | D73: 46056 | E73: 107946603700 | F73: 1 | M73: 389500 | AA73: Local | AB73: =A73 -> PS26781 | AC73: =B73 -> VY/023-2026 | AD73: =D73 -> 46056 | AH73: =+M73 -> 389500 | AR73: =SUM(AG73:AQ73)*0.08 -> 31160 | AS73: =SUM(AG73:AR73) -> 420660 | AT73: =AS73 -> 420660 | AU73: =AA73 -> Local
A74: PS26782 | B74: 24/PSHK/26 | C74: Local | D74: 46056 | E74: 107946640430 | F74: 1 | M74: 389500 | AA74: Local | AB74: =A74 -> PS26782 | AC74: =B74 -> 24/PSHK/26 | AD74: =D74 -> 46056 | AH74: =+M74 -> 389500 | AR74: =SUM(AG74:AQ74)*0.08 -> 31160 | AS74: =SUM(AG74:AR74) -> 420660 | AT74: =AS74 -> 420660 | AU74: =AA74 -> Local
A75: PS26783 | B75: 176/BG-PS-34 | C75: Local | D75: 46056 | E75: 107946665630 | F75: 1 | M75: 389500 | AA75: Local | AB75: =A75 -> PS26783 | AC75: =B75 -> 176/BG-PS-34 | AD75: =D75 -> 46056 | AH75: =+M75 -> 389500 | AR75: =SUM(AG75:AQ75)*0.08 -> 31160 | AS75: =SUM(AG75:AR75) -> 420660 | AT75: =AS75 -> 420660 | AU75: =AA75 -> Local
A76: PS26780 | B76: 5199674 | C76: Local | D76: 46056 | E76: 107946735520 | F76: 1 | M76: 389500 | AA76: Local | AB76: =A76 -> PS26780 | AC76: =B76 -> 5199674 | AD76: =D76 -> 46056 | AH76: =+M76 -> 389500 | AR76: =SUM(AG76:AQ76)*0.08 -> 31160 | AS76: =SUM(AG76:AR76) -> 420660 | AT76: =AS76 -> 420660 | AU76: =AA76 -> Local
A77: PS26779 | B77: 5199675 | C77: Local | D77: 46056 | E77: 107946822060 | F77: 1 | M77: 389500 | AA77: Local | AB77: =A77 -> PS26779 | AC77: =B77 -> 5199675 | AD77: =D77 -> 46056 | AH77: =+M77 -> 389500 | AR77: =SUM(AG77:AQ77)*0.08 -> 31160 | AS77: =SUM(AG77:AR77) -> 420660 | AT77: =AS77 -> 420660 | AU77: =AA77 -> Local
A78: PS26792 | B78: 5216215 | C78: Local | D78: 46056 | E78: 107952998860 | F78: 1 | M78: 389500 | AA78: Local | AB78: =A78 -> PS26792 | AC78: =B78 -> 5216215 | AD78: =D78 -> 46056 | AH78: =+M78 -> 389500 | AR78: =SUM(AG78:AQ78)*0.08 -> 31160 | AS78: =SUM(AG78:AR78) -> 420660 | AT78: =AS78 -> 420660 | AU78: =AA78 -> Local
A79: PS26793 | B79: 850C260101934 | C79: Local | D79: 46056 | E79: 107953008700 | F79: 1 | M79: 389500 | AA79: Local | AB79: =A79 -> PS26793 | AC79: =B79 -> 850C260101934 | AD79: =D79 -> 46056 | AH79: =+M79 -> 389500 | AR79: =SUM(AG79:AQ79)*0.08 -> 31160 | AS79: =SUM(AG79:AR79) -> 420660 | AT79: =AS79 -> 420660 | AU79: =AA79 -> Local
A80: PS26749 | B80: EBD-PSTPU260127 | C80: Local | D80: 46056 | E80: 107950987760 | F80: 1 | M80: 389500 | AA80: Local | AB80: =A80 -> PS26749 | AC80: =B80 -> EBD-PSTPU260127 | AD80: =D80 -> 46056 | AH80: =+M80 -> 389500 | AR80: =SUM(AG80:AQ80)*0.08 -> 31160 | AS80: =SUM(AG80:AR80) -> 420660 | AT80: =AS80 -> 420660 | AU80: =AA80 -> Local
A81: PS26821 | B81: 25/PSHK/26 | C81: Local | D81: 46056 | E81: 107951009350 | F81: 1 | M81: 389500 | AA81: Local | AB81: =A81 -> PS26821 | AC81: =B81 -> 25/PSHK/26 | AD81: =D81 -> 46056 | AH81: =+M81 -> 389500 | AR81: =SUM(AG81:AQ81)*0.08 -> 31160 | AS81: =SUM(AG81:AR81) -> 420660 | AT81: =AS81 -> 420660 | AU81: =AA81 -> Local
A82: PS26818 | B82: 5199231 | C82: Local | D82: 46056 | E82: 107952999820 | F82: 1 | M82: 389500 | AA82: Local | AB82: =A82 -> PS26818 | AC82: =B82 -> 5199231 | AD82: =D82 -> 46056 | AH82: =+M82 -> 389500 | AR82: =SUM(AG82:AQ82)*0.08 -> 31160 | AS82: =SUM(AG82:AR82) -> 420660 | AT82: =AS82 -> 420660 | AU82: =AA82 -> Local
A83: PS26826 | B83: 26/PSHK/26 | C83: Local | D83: 46056 | E83: 107952099510 | F83: 1 | M83: 389500 | AA83: Local | AB83: =A83 -> PS26826 | AC83: =B83 -> 26/PSHK/26 | AD83: =D83 -> 46056 | AH83: =+M83 -> 389500 | AR83: =SUM(AG83:AQ83)*0.08 -> 31160 | AS83: =SUM(AG83:AR83) -> 420660 | AT83: =AS83 -> 420660 | AU83: =AA83 -> Local
... A154: PS26949 | B154: BSV260205-221501 | C154: Local | D154: 46060 | E154: 107969094660 | F154: 1 | M154: 389500 | AA154: Local | AB154: =A154 -> PS26949 | AC154: =B154 -> BSV260205-221501 | AD154: =D154 -> 46060 | AH154: =+M154 -> 389500 | AR154: =SUM(AG154:AQ154)*0.08 -> 31160 | AS154: =SUM(AG154:AR154) -> 420660 | AT154: =AS154 -> 420660 | AU154: =AA154 -> Local
AG155: =SUM(AG3:AG154) -> 66576000 | AH155: =SUM(AH3:AH154) -> 86882000 | AI155: =SUM(AI3:AI154) -> 0 | AJ155: =SUM(AJ3:AJ154) -> 0 | AK155: =SUM(AK3:AK154) -> 0 | AL155: =SUM(AL3:AL154) -> 0 | AM155: =SUM(AM3:AM154) -> 0 | AN155: =SUM(AN3:AN154) -> 0 | ... AU155: =SUM(AU3:AU154) -> 0
AH157: trucking charge | AJ157: =AG155+AQ155+AP155 -> 66576000 | AK157: ='FCL - IMPORT'!AJ29 -> 60820000 | AL157: =AJ157+AK157 -> 127396000 | AN157: Not include VAT
AH158: service charge | AJ158: =AH155 -> 86882000 | AK158: ='FCL - IMPORT'!AJ28 -> 19467500 | AL158: =AJ158+AK158 -> 106349500 | AN158: Not include VAT
AH159: passthrough - FREIGHT | AJ159: =AI155+AJ155+AK155+AL155+AM155+AN155+AO155 -> 0 | AK159: ='FCL - IMPORT'!AJ30 -> 0 | AL159: =AJ159+AK159 -> 0 | AN159: Not include VAT
AH160: service air export | AJ160: =#REF! -> #REF! | AL160: =AJ160+AK160 -> #REF! | AN160: Not include VAT
AH161: trucking air export | AJ161: =#REF! -> #REF! | AL161: =AJ161+AK161 -> #REF! | AN161: Not include VAT
AJ163: =SUM(AJ157:AJ161) -> #REF! | AK163: =SUM(AK157:AK161) -> 80287500 | AL163: =SUM(AL157:AL161) -> #REF!
AJ166: =AJ157+AJ158+AK157+AK158+AJ160+AJ161 -> #REF!

Sheet LCL+LOCAL - IMPORT   (CHECK XE)
A1: LCL + LOCAL
A2: No | B2: INVOICE No | C2: AWB,B/L No | D2: DATE C/D | E2: Declaration | F2: Number of CD | G2: KGS | H2: KGS OF BL | I2: CBM | J2: FREIGHT AIR | K2: FREIGHT SEA | L2: TRUCKING FEE | M2: SERVICE FEE | N2: CFS | O2: CIC | P2: THC | Q2: D/O | R2: HANDLING | S2: STORAGE | T2: CSHT | U2: TOLL FEE | V2: INCURRED | W2: VAT PASS THROUGH | X2: CLEARING EXPENSE | Y2: TOTAL | Z2: SỐ XE | AA2: PORT | AB2: No | AC2: INVOICE No | AD2: DATE | AE2: FREIGHT AIR PER P/L | AF2: FREIGHT SEA PER P/L | AG2: TRUCKING FEE | AH2: SERVICE FEE | AI2: CFS | AJ2: CIC | AK2: THC | AL2: D/O | AM2: HANDLING | AN2: STORAGE | AO2: CSHT | AP2: TOLL FEE | AQ2: INCURRED | AR2: VAT PASS THROUGH | AS2: CLEARING EXPENSE PER P/L | AT2: TOTAL | AU2: PORT | AW2: SỐ JOB FILE OF ADC | AX2: Nơi đi - Nơi đến | AY2: NGÀY GIAO HÀNG | AZ2: XE THỰC TẾ | BB2: GIÁ XE CHẠY THEO BÁO GIÁ | BC2: CHÊNH LỆCH
A3: PS260717 | B3: EX-26010076 | C3: SE26010032/003 | D3: 46051 | E3: 107938104260 | F3: 1 | G3: 194.46 | H3: 194.46 | I3: 0.832 | M3: 940500 | Z3: 50H-69181 | AA3: CÁT LÁI | AB3: =A3 -> PS260717 | AC3: =B3 -> EX-26010076 | AD3: =D3 -> 46051 | AE3: =G3/H3*J3 -> 0 | AF3: =(G3/H3)*K3 -> 0 | AG3: =(G3/H3)*L3 -> 0 | AH3: =(G3/H3)*M3 -> 940500 | AI3: =(G3/H3)*N3 -> 0 | AJ3: =(G3/H3)*O3 -> 0 | AK3: =(G3/H3)*P3 -> 0 | AL3: =(G3/H3)*Q3 -> 0 | AM3: =(G3/H3)*R3 -> 0 | AN3: =(G3/H3)*S3 -> 0 | AO3: =(G3/H3)*T3 -> 0 | AP3: =(G3/H3)*U3 -> 0 | AQ3: =(G3/H3)*V3 -> 0 | AR3: =SUM(AG3:AQ3)*0.08 -> 75240 | AS3: =SUM(AG3:AR3) -> 1015740 | AT3: =AS3 -> 1015740 | AU3: =AA3 -> CÁT LÁI | AV3: LCL | AW3: ADCDNB-26.01-004426 | AX3: , từ Cảng Cát Lái đến KCN Bàu Xéo, Đồng Nai | AY3: 46055 | AZ3: 50H-69181 50H-66757 | BA3: 2 X 5MT | BB3: 1290000 | BC3: =BB3-L3 -> 1290000
A4: PS260508 | B4: OHTY260012 | C4: 08SEA2601035 | D4: 46052 | E4: 107942880510 | F4: 1 | G4: 666 | H4: 666 | I4: 5.032 | L4: {=IF(H4=0, _xleta.T, IF(H4<=1000, 1290000, IF(H4<=2000, 1460000, IF(H4<=3000, 2186000, IF(H4<=5000, 2296000, ff)))))} -> 1290000 | M4: 940500 | AA4: CÁT LÁI | AB4: =A4 -> PS260508 | AC4: =B4 -> OHTY260012 | AD4: =D4 -> 46052 | AE4: =G4/H4*J4 -> 0 | AF4: =(G4/H4)*K4 -> 0 | AG4: =(G4/H4)*L4 -> 1290000 | AH4: =(G4/H4)*M4 -> 940500 | AI4: =(G4/H4)*N4 -> 0 | AJ4: =(G4/H4)*O4 -> 0 | AK4: =(G4/H4)*P4 -> 0 | AL4: =(G4/H4)*Q4 -> 0 | AM4: =(G4/H4)*R4 -> 0 | AN4: =(G4/H4)*S4 -> 0 | AO4: =(G4/H4)*T4 -> 0 | AP4: =(G4/H4)*U4 -> 0 | AQ4: =(G4/H4)*V4 -> 0 | AR4: =SUM(AG4:AQ4)*0.08 -> 178440 | AS4: =SUM(AG4:AR4) -> 2408940 | AT4: =AS4 -> 2408940 | AU4: =AA4 -> CÁT LÁI | AV4: LCL | AW4: ADCDNB-26.01-004616 | AX4: , từ Cảng Cát Lái đến KCN Bàu Xéo, Đồng Nai | AY4: 46055 | BB4: 1290000 | BC4: =BB4-L4 -> 0
A5: PS260746 | B5: 5204969 | C5: S02096936 | D5: 46051 | E5: 107940077120 | F5: 1 | G5: 241.98 | H5: 241.98 | I5: 1.474 | L5: {=IF(H5=0, _xleta.T, IF(H5<=1000, 1290000, IF(H5<=2000, 1460000, IF(H5<=3000, 2186000, IF(H5<=5000, 2296000, ff)))))} -> 1290000 | M5: 940500 | Z5: 50H-66757 | AA5: CÁT LÁI | AB5: =A5 -> PS260746 | AC5: =B5 -> 5204969 | AD5: =D5 -> 46051 | AE5: =G5/H5*J5 -> 0 | AF5: =(G5/H5)*K5 -> 0 | AG5: =(G5/H5)*L5 -> 1290000 | AH5: =(G5/H5)*M5 -> 940500 | AI5: =(G5/H5)*N5 -> 0 | AJ5: =(G5/H5)*O5 -> 0 | AK5: =(G5/H5)*P5 -> 0 | AL5: =(G5/H5)*Q5 -> 0 | AM5: =(G5/H5)*R5 -> 0 | AN5: =(G5/H5)*S5 -> 0 | AO5: =(G5/H5)*T5 -> 0 | AP5: =(G5/H5)*U5 -> 0 | AQ5: =(G5/H5)*V5 -> 0 | AR5: =SUM(AG5:AQ5)*0.08 -> 178440 | AS5: =SUM(AG5:AR5) -> 2408940 | AT5: =AS5 -> 2408940 | AU5: =AA5 -> CÁT LÁI | AV5: LCL | AW5: ADCDNB-26.01-004617 | AX5: , từ Cảng Cát Lái đến KCN Bàu Xéo, Đồng Nai | AY5: 46055 | BB5: 1290000 | BC5: =BB5-L5 -> 0
A6: PS260737 | B6: 5196209 | C6: CGH/HCM-018/26 | D6: 46052 | E6: 107943625640 | F6: 1 | G6: 191.6 | H6: 191.6 | I6: 0.86 | M6: 940500 | AA6: CÁT LÁI | AB6: =A6 -> PS260737 | AC6: =B6 -> 5196209 | AD6: =D6 -> 46052 | AE6: =G6/H6*J6 -> 0 | AF6: =(G6/H6)*K6 -> 0 | AG6: =(G6/H6)*L6 -> 0 | AH6: =(G6/H6)*M6 -> 940500 | AI6: =(G6/H6)*N6 -> 0 | AJ6: =(G6/H6)*O6 -> 0 | AK6: =(G6/H6)*P6 -> 0 | AL6: =(G6/H6)*Q6 -> 0 | AM6: =(G6/H6)*R6 -> 0 | AN6: =(G6/H6)*S6 -> 0 | AO6: =(G6/H6)*T6 -> 0 | AP6: =(G6/H6)*U6 -> 0 | AQ6: =(G6/H6)*V6 -> 0 | AR6: =SUM(AG6:AQ6)*0.08 -> 75240 | AS6: =SUM(AG6:AR6) -> 1015740 | AT6: =AS6 -> 1015740 | AU6: =AA6 -> CÁT LÁI | AV6: LCL | AW6: ADCDNB-26.01-004619 | AX6: , từ Cảng Cát Lái đến KCN Bàu Xéo, Đồng Nai | AY6: 46055 | BB6: 1290000 | BC6: =BB6-L6 -> 1290000
A7: PS260716 | B7: PS26-716 | C7: CGH/HCM-018/26A | D7: 46052 | E7: 107943647930 | F7: 1 | G7: 792.5 | H7: 792.5 | I7: 1.91 | L7: {=IF(H7=0, _xleta.T, IF(H7<=1000, 1290000, IF(H7<=2000, 1460000, IF(H7<=3000, 2186000, IF(H7<=5000, 2296000, ff)))))} -> 1290000 | M7: 940500 | Z7: 50H-69181 | AA7: CÁT LÁI | AB7: =A7 -> PS260716 | AC7: =B7 -> PS26-716 | AD7: =D7 -> 46052 | AE7: =G7/H7*J7 -> 0 | AF7: =(G7/H7)*K7 -> 0 | AG7: =(G7/H7)*L7 -> 1290000 | AH7: =(G7/H7)*M7 -> 940500 | AI7: =(G7/H7)*N7 -> 0 | AJ7: =(G7/H7)*O7 -> 0 | AK7: =(G7/H7)*P7 -> 0 | AL7: =(G7/H7)*Q7 -> 0 | AM7: =(G7/H7)*R7 -> 0 | AN7: =(G7/H7)*S7 -> 0 | AO7: =(G7/H7)*T7 -> 0 | AP7: =(G7/H7)*U7 -> 0 | AQ7: =(G7/H7)*V7 -> 0 | AR7: =SUM(AG7:AQ7)*0.08 -> 178440 | AS7: =SUM(AG7:AR7) -> 2408940 | AT7: =AS7 -> 2408940 | AU7: =AA7 -> CÁT LÁI | AV7: LCL | AW7: ADCDNB-26.01-004636 | AX7: , từ Cảng Cát Lái đến KCN Bàu Xéo, Đồng Nai | AY7: 46055 | BB7: 1290000 | BC7: =BB7-L7 -> 0
A8: PS260742 | B8: PS26-742 | C8: CGH/HCM-018/26B | D8: 46052 | E8: 107943576750 | F8: 1 | G8: 2511 | H8: 2511 | I8: 6.38 | L8: {=IF(H8=0, _xleta.T, IF(H8<=1000, 1290000, IF(H8<=2000, 1460000, IF(H8<=3000, 2186000, IF(H8<=5000, 2296000, ff)))))} -> 2186000 | M8: 940500 | Z8: 50H-66757 | AA8: CÁT LÁI | AB8: =A8 -> PS260742 | AC8: =B8 -> PS26-742 | AD8: =D8 -> 46052 | AE8: =G8/H8*J8 -> 0 | AF8: =(G8/H8)*K8 -> 0 | AG8: =(G8/H8)*L8 -> 2186000 | AH8: =(G8/H8)*M8 -> 940500 | AI8: =(G8/H8)*N8 -> 0 | AJ8: =(G8/H8)*O8 -> 0 | AK8: =(G8/H8)*P8 -> 0 | AL8: =(G8/H8)*Q8 -> 0 | AM8: =(G8/H8)*R8 -> 0 | AN8: =(G8/H8)*S8 -> 0 | AO8: =(G8/H8)*T8 -> 0 | AP8: =(G8/H8)*U8 -> 0 | AQ8: =(G8/H8)*V8 -> 0 | AR8: =SUM(AG8:AQ8)*0.08 -> 250120 | AS8: =SUM(AG8:AR8) -> 3376620 | AT8: =AS8 -> 3376620 | AU8: =AA8 -> CÁT LÁI | AV8: LCL | AW8: ADCDNB-26.01-004637 | AX8: , từ Cảng Cát Lái đến KCN Bàu Xéo, Đồng Nai | AY8: 46055 | BB8: 2186000 | BC8: =BB8-L8 -> 0
A9: PS260768 | B9: 2603/SLTW-PS | C9: 112600036770481 | D9: 46052 | E9: 107944314110 | F9: 1 | G9: 7867 | H9: 7867 | L9: =2596000*2 -> 5192000 | M9: 940500 | Z9: 50E46443 60H11265 | AA9: TAN THUAN | AB9: =A9 -> PS260768 | AC9: =B9 -> 2603/SLTW-PS | AD9: =D9 -> 46052 | AE9: =G9/H9*J9 -> 0 | AF9: =(G9/H9)*K9 -> 0 | AG9: =(G9/H9)*L9 -> 5192000 | AH9: =(G9/H9)*M9 -> 940500 | AI9: =(G9/H9)*N9 -> 0 | AJ9: =(G9/H9)*O9 -> 0 | AK9: =(G9/H9)*P9 -> 0 | AL9: =(G9/H9)*Q9 -> 0 | AM9: =(G9/H9)*R9 -> 0 | AN9: =(G9/H9)*S9 -> 0 | AO9: =(G9/H9)*T9 -> 0 | AP9: =(G9/H9)*U9 -> 0 | AQ9: =(G9/H9)*V9 -> 0 | AR9: =SUM(AG9:AQ9)*0.08 -> 490600 | AS9: =SUM(AG9:AR9) -> 6623100 | AT9: =AS9 -> 6623100 | AU9: =AA9 -> TAN THUAN | AV9: LCL | AW9: ADCDNB-26.01-004627 | AX9: , từ Tân Thuận về KCN Bàu Xéo, Đồng Nai | AY9: 46055 | AZ9: 50E46443 60H11265 | BA9: 2 X 5MT | BB9: 5192000 | BC9: =BB9-L9 -> 0
A10: PS260788 | B10: PC260130VY | C10: JWE5150187 | D10: 46055 | E10: 107946861300 | F10: 1 | G10: 17 | H10: 17 | L10: =IF(H10<=50,1060000, IF(H10<=200, 1210000, IF(H10<=500, 1230000, IF(H10<=1000, 1440000, IF(H10<=2000, 1990000, IF(H10>2000, 1990000+(H10-2000)*1464)))))) -> 1060000 | M10: 940500 | Z10: 50H69104 | AA10: TCS | AB10: =A10 -> PS260788 | AC10: =B10 -> PC260130VY | AD10: =D10 -> 46055 | AE10: =G10/H10*J10 -> 0 | AF10: =(G10/H10)*K10 -> 0 | AG10: =(G10/H10)*L10 -> 1060000 | AH10: =(G10/H10)*M10 -> 940500 | AI10: =(G10/H10)*N10 -> 0 | AJ10: =(G10/H10)*O10 -> 0 | AK10: =(G10/H10)*P10 -> 0 | AL10: =(G10/H10)*Q10 -> 0 | AM10: =(G10/H10)*R10 -> 0 | AN10: =(G10/H10)*S10 -> 0 | AO10: =(G10/H10)*T10 -> 0 | AP10: =(G10/H10)*U10 -> 0 | AQ10: =(G10/H10)*V10 -> 0 | AR10: =SUM(AG10:AQ10)*0.08 -> 160040 | AS10: =SUM(AG10:AR10) -> 2160540 | AT10: =AS10 -> 2160540 | AU10: =AA10 -> TCS | AV10: AIR | AW10: ADCDNB-26.01-004700 | AX10: , từ Kho TCS đến KCN Bàu Xéo , Đồng Nai | AY10: 46056 | AZ10: 50H69104 | BA10: 1 X 1MT | BB10: 1060000
A11: PS260775 | B11: HH20260128001 | C11: 8704238410 | D11: 46052 | E11: 107944026410 | F11: 1 | G11: 5.7 | H11: 5.7 | M11: 570000 | AA11: DHL | AB11: =A11 -> PS260775 | AC11: =B11 -> HH20260128001 | AD11: =D11 -> 46052 | AE11: =G11/H11*J11 -> 0 | AF11: =(G11/H11)*K11 -> 0 | AG11: =(G11/H11)*L11 -> 0 | AH11: =(G11/H11)*M11 -> 570000 | AI11: =(G11/H11)*N11 -> 0 | AJ11: =(G11/H11)*O11 -> 0 | AK11: =(G11/H11)*P11 -> 0 | AL11: =(G11/H11)*Q11 -> 0 | AM11: =(G11/H11)*R11 -> 0 | AN11: =(G11/H11)*S11 -> 0 | AO11: =(G11/H11)*T11 -> 0 | AP11: =(G11/H11)*U11 -> 0 | AQ11: =(G11/H11)*V11 -> 0 | AR11: =SUM(AG11:AQ11)*0.08 -> 45600 | AS11: =SUM(AG11:AR11) -> 615600 | AT11: =AS11 -> 615600 | AU11: =AA11 -> DHL | AV11: EXP | AW11: ADCDNB-26.01-004630
A12: PS260772 | B12: EXD1-26-VY0127 | C12: 8704018536 | D12: 46053 | E12: 107946396610 | F12: 1 | G12: 19.5 | H12: 19.5 | M12: 570000 | AA12: DHL | AB12: =A12 -> PS260772 | AC12: =B12 -> EXD1-26-VY0127 | AD12: =D12 -> 46053 | AE12: =G12/H12*J12 -> 0 | AF12: =(G12/H12)*K12 -> 0 | AG12: =(G12/H12)*L12 -> 0 | AH12: =(G12/H12)*M12 -> 570000 | AI12: =(G12/H12)*N12 -> 0 | AJ12: =(G12/H12)*O12 -> 0 | AK12: =(G12/H12)*P12 -> 0 | AL12: =(G12/H12)*Q12 -> 0 | AM12: =(G12/H12)*R12 -> 0 | AN12: =(G12/H12)*S12 -> 0 | AO12: =(G12/H12)*T12 -> 0 | AP12: =(G12/H12)*U12 -> 0 | AQ12: =(G12/H12)*V12 -> 0 | AR12: =SUM(AG12:AQ12)*0.08 -> 45600 | AS12: =SUM(AG12:AR12) -> 615600 | AT12: =AS12 -> 615600 | AU12: =AA12 -> DHL | AV12: EXP | AW12: ADCDNB-26.02-000302
A13: PS260777 | B13: AT26010642 | C13: 2819783746 | D13: 46053 | E13: 107946398450 | F13: 1 | G13: 16 | H13: 16 | M13: 570000 | AA13: DHL | AB13: =A13 -> PS260777 | AC13: =B13 -> AT26010642 | AD13: =D13 -> 46053 | AE13: =G13/H13*J13 -> 0 | AF13: =(G13/H13)*K13 -> 0 | AG13: =(G13/H13)*L13 -> 0 | AH13: =(G13/H13)*M13 -> 570000 | AI13: =(G13/H13)*N13 -> 0 | AJ13: =(G13/H13)*O13 -> 0 | AK13: =(G13/H13)*P13 -> 0 | AL13: =(G13/H13)*Q13 -> 0 | AM13: =(G13/H13)*R13 -> 0 | AN13: =(G13/H13)*S13 -> 0 | AO13: =(G13/H13)*T13 -> 0 | AP13: =(G13/H13)*U13 -> 0 | AQ13: =(G13/H13)*V13 -> 0 | AR13: =SUM(AG13:AQ13)*0.08 -> 45600 | AS13: =SUM(AG13:AR13) -> 615600 | AT13: =AS13 -> 615600 | AU13: =AA13 -> DHL | AV13: EXP | AW13: ADCDNB-26.02-000303
A14: PS260771 | B14: 005/IEM/I/26 | C14: 4471973100 | D14: 46053 | E14: 107946400110 | F14: 1 | G14: 10.2 | H14: 10.2 | M14: 570000 | AA14: DHL | AB14: =A14 -> PS260771 | AC14: =B14 -> 005/IEM/I/26 | AD14: =D14 -> 46053 | AE14: =G14/H14*J14 -> 0 | AF14: =(G14/H14)*K14 -> 0 | AG14: =(G14/H14)*L14 -> 0 | AH14: =(G14/H14)*M14 -> 570000 | AI14: =(G14/H14)*N14 -> 0 | AJ14: =(G14/H14)*O14 -> 0 | AK14: =(G14/H14)*P14 -> 0 | AL14: =(G14/H14)*Q14 -> 0 | AM14: =(G14/H14)*R14 -> 0 | AN14: =(G14/H14)*S14 -> 0 | AO14: =(G14/H14)*T14 -> 0 | AP14: =(G14/H14)*U14 -> 0 | AQ14: =(G14/H14)*V14 -> 0 | AR14: =SUM(AG14:AQ14)*0.08 -> 45600 | AS14: =SUM(AG14:AR14) -> 615600 | AT14: =AS14 -> 615600 | AU14: =AA14 -> DHL | AV14: EXP | AW14: ADCDNB-26.02-000304
A15: PS260760 | B15: T260122-Y1 | C15: SPOE2601123 | D15: 46052 | E15: 107940953260 | F15: 1 | G15: 668.89 | H15: 668.89 | I15: 2.732 | L15: {=IF(H15=0, _xleta.T, IF(H15<=1000, 1290000, IF(H15<=2000, 1460000, IF(H15<=3000, 2186000, IF(H15<=5000, 2296000, ff)))))} -> 1290000 | M15: 940500 | Z15: 50E46291 | AA15: CÁT LÁI | AB15: =A15 -> PS260760 | AC15: =B15 -> T260122-Y1 | AD15: =D15 -> 46052 | AE15: =G15/H15*J15 -> 0 | AF15: =(G15/H15)*K15 -> 0 | AG15: =(G15/H15)*L15 -> 1290000 | AH15: =(G15/H15)*M15 -> 940500 | AI15: =(G15/H15)*N15 -> 0 | AJ15: =(G15/H15)*O15 -> 0 | AK15: =(G15/H15)*P15 -> 0 | AL15: =(G15/H15)*Q15 -> 0 | AM15: =(G15/H15)*R15 -> 0 | AN15: =(G15/H15)*S15 -> 0 | AO15: =(G15/H15)*T15 -> 0 | AP15: =(G15/H15)*U15 -> 0 | AQ15: =(G15/H15)*V15 -> 0 | AR15: =SUM(AG15:AQ15)*0.08 -> 178440 | AS15: =SUM(AG15:AR15) -> 2408940 | AT15: =AS15 -> 2408940 | AU15: =AA15 -> CÁT LÁI | AV15: LCL | AW15: ADCDNB-26.01-004618 | AX15: , từ Cảng Cát Lái đến KCN Bàu Xéo, Đồng Nai | AY15: 46056 | AZ15: 50E46291 | BA15: 1 X 2MT | BB15: 1290000 | BC15: =BB15-L15 -> 0
A16: PS260748 | B16: EXD1-26-C037 | C16: HTHC26012481 | D16: 46053 | E16: 107946468930 | F16: 1 | G16: 502 | H16: 502 | I16: 1 | L16: {=IF(H16=0, _xleta.T, IF(H16<=1000, 1290000, IF(H16<=2000, 1460000, IF(H16<=3000, 2186000, IF(H16<=5000, 2296000, ff)))))} -> 1290000 | M16: 940500 | Z16: 50E46291 | AA16: CÁT LÁI | AB16: =A16 -> PS260748 | AC16: =B16 -> EXD1-26-C037 | AD16: =D16 -> 46053 | AE16: =G16/H16*J16 -> 0 | AF16: =(G16/H16)*K16 -> 0 | AG16: =(G16/H16)*L16 -> 1290000 | AH16: =(G16/H16)*M16 -> 940500 | AI16: =(G16/H16)*N16 -> 0 | AJ16: =(G16/H16)*O16 -> 0 | AK16: =(G16/H16)*P16 -> 0 | AL16: =(G16/H16)*Q16 -> 0 | AM16: =(G16/H16)*R16 -> 0 | AN16: =(G16/H16)*S16 -> 0 | AO16: =(G16/H16)*T16 -> 0 | AP16: =(G16/H16)*U16 -> 0 | AQ16: =(G16/H16)*V16 -> 0 | AR16: =SUM(AG16:AQ16)*0.08 -> 178440 | AS16: =SUM(AG16:AR16) -> 2408940 | AT16: =AS16 -> 2408940 | AU16: =AA16 -> CÁT LÁI | AV16: LCL | AW16: ADCDNB-26.02-000305 | AX16: , từ Cảng Cát Lái đến KCN Bàu Xéo, Đồng Nai | AY16: 46056 | BB16: 1290000 | BC16: =BB16-L16 -> 0
A17: PS260774 | B17: 260121-02 | C17: 20SEA26010169 | D17: 46053 | E17: 107946490300 | F17: 1 | G17: 573 | H17: 573 | I17: 0.9 | L17: {=IF(H17=0, _xleta.T, IF(H17<=1000, 1290000, IF(H17<=2000, 1460000, IF(H17<=3000, 2186000, IF(H17<=5000, 2296000, ff)))))} -> 1290000 | M17: 940500 | Z17: 50E46291 | AA17: CÁT LÁI | AB17: =A17 -> PS260774 | AC17: =B17 -> 260121-02 | AD17: =D17 -> 46053 | AE17: =G17/H17*J17 -> 0 | AF17: =(G17/H17)*K17 -> 0 | AG17: =(G17/H17)*L17 -> 1290000 | AH17: =(G17/H17)*M17 -> 940500 | AI17: =(G17/H17)*N17 -> 0 | AJ17: =(G17/H17)*O17 -> 0 | AK17: =(G17/H17)*P17 -> 0 | AL17: =(G17/H17)*Q17 -> 0 | AM17: =(G17/H17)*R17 -> 0 | AN17: =(G17/H17)*S17 -> 0 | AO17: =(G17/H17)*T17 -> 0 | AP17: =(G17/H17)*U17 -> 0 | AQ17: =(G17/H17)*V17 -> 0 | AR17: =SUM(AG17:AQ17)*0.08 -> 178440 | AS17: =SUM(AG17:AR17) -> 2408940 | AT17: =AS17 -> 2408940 | AU17: =AA17 -> CÁT LÁI | AV17: LCL | AW17: ADCDNB-26.02-000306 | AX17: , từ Cảng Cát Lái đến KCN Bàu Xéo, Đồng Nai | AY17: 46056 | BB17: 1290000 | BC17: =BB17-L17 -> 0
A18: PS260837 | B18: 0885089482 | C18: JWE5150192 | D18: 46056 | E18: 107953699600 | F18: 2 | G18: 2.2 | H18: =G18+G19 -> 237 | L18: =IF(H18<=50,1060000, IF(H18<=200, 1210000, IF(H18<=500, 1230000, IF(H18<=1000, 1440000, IF(H18<=2000, 1990000, IF(H18>2000, 1990000+(H18-2000)*1464)))))) -> 1230000 | M18: =940500+70000 -> 1010500 | Z18: 50H70505 | AA18: TCS | AB18: =A18 -> PS260837 | AC18: =B18 -> 0885089482 | AD18: =D18 -> 46056 | AE18: =G18/H18*J18 -> 0 | AF18: =(G18/H18)*K18 -> 0 | AG18: =(G18/H18)*L18 -> 11417.722 | AH18: =(G18/H18)*M18 -> 9380.1688 | AI18: =(G18/H18)*N18 -> 0 | AJ18: =(G18/H18)*O18 -> 0 | AK18: =(G18/H18)*P18 -> 0 | AL18: =(G18/H18)*Q18 -> 0 | AM18: =(G18/H18)*R18 -> 0 | AN18: =(G18/H18)*S18 -> 0 | AO18: =(G18/H18)*T18 -> 0 | AP18: =(G18/H18)*U18 -> 0 | AQ18: =(G18/H18)*V18 -> 0 | AR18: =SUM(AG18:AQ18)*0.08 -> 1663.8312 | AS18: =SUM(AG18:AR18) -> 22461.722 | AT18: =AS18 -> 22461.722 | AU18: =AA18 -> TCS | AV18: AIR | AW18: ADCDNB-26.02-000382 | AX18: , từ Kho TCS đến KCN Bàu Xéo , Đồng Nai | AY18: 46057 | AZ18: 50H70505 | BA18: 1 X 1MT | BB18: 1230000
A19: PS260837 | B19: 0885090860 | C19: JWE5150192 | D19: 46056 | E19: 107953739830 | G19: 234.8 | H19: 237 | L19: =IF(H19<=50,1060000, IF(H19<=200, 1210000, IF(H19<=500, 1230000, IF(H19<=1000, 1440000, IF(H19<=2000, 1990000, IF(H19>2000, 1990000+(H19-2000)*1464)))))) -> 1230000 | M19: =940500+70000 -> 1010500 | Z19: 50H70505 | AA19: TCS | AB19: =A19 -> PS260837 | AC19: =B19 -> 0885090860 | AD19: =D19 -> 46056 | AE19: =G19/H19*J19 -> 0 | AF19: =(G19/H19)*K19 -> 0 | AG19: =(G19/H19)*L19 -> 1218582.3 | AH19: =(G19/H19)*M19 -> 1001119.8 | AI19: =(G19/H19)*N19 -> 0 | AJ19: =(G19/H19)*O19 -> 0 | AK19: =(G19/H19)*P19 -> 0 | AL19: =(G19/H19)*Q19 -> 0 | AM19: =(G19/H19)*R19 -> 0 | AN19: =(G19/H19)*S19 -> 0 | AO19: =(G19/H19)*T19 -> 0 | AP19: =(G19/H19)*U19 -> 0 | AQ19: =(G19/H19)*V19 -> 0 | AR19: =SUM(AG19:AQ19)*0.08 -> 177576.17 | AS19: =SUM(AG19:AR19) -> 2397278.3 | AT19: =AS19 -> 2397278.3 | AU19: =AA19 -> TCS | AV19: AIR | AW19: ADCDNB-26.02-000382 | AX19: , từ Kho TCS đến KCN Bàu Xéo , Đồng Nai | AY19: 46057 | BB19: 1230000
A20: PS260835 | B20: PC260202VY | C20: JWE5150195 | D20: 46056 | E20: 107953153600 | F20: 1 | G20: 32 | H20: 32 | L20: =IF(H20<=50,1060000, IF(H20<=200, 1210000, IF(H20<=500, 1230000, IF(H20<=1000, 1440000, IF(H20<=2000, 1990000, IF(H20>2000, 1990000+(H20-2000)*1464)))))) -> 1060000 | M20: 940500 | Z20: 50H70505 | AA20: TCS | AB20: =A20 -> PS260835 | AC20: =B20 -> PC260202VY | AD20: =D20 -> 46056 | AE20: =G20/H20*J20 -> 0 | AF20: =(G20/H20)*K20 -> 0 | AG20: =(G20/H20)*L20 -> 1060000 | AH20: =(G20/H20)*M20 -> 940500 | AI20: =(G20/H20)*N20 -> 0 | AJ20: =(G20/H20)*O20 -> 0 | AK20: =(G20/H20)*P20 -> 0 | AL20: =(G20/H20)*Q20 -> 0 | AM20: =(G20/H20)*R20 -> 0 | AN20: =(G20/H20)*S20 -> 0 | AO20: =(G20/H20)*T20 -> 0 | AP20: =(G20/H20)*U20 -> 0 | AQ20: =(G20/H20)*V20 -> 0 | AR20: =SUM(AG20:AQ20)*0.08 -> 160040 | AS20: =SUM(AG20:AR20) -> 2160540 | AT20: =AS20 -> 2160540 | AU20: =AA20 -> TCS | AV20: AIR | AW20: ADCDNB-26.02-000381 | AX20: , từ Kho TCS đến KCN Bàu Xéo , Đồng Nai | AY20: 46057 | BB20: 1060000
A21: PS260806 | B21: LW260129 | C21: 5397965591 | D21: 46056 | E21: 107952134730 | F21: 1 | G21: 32.5 | H21: 32.5 | M21: 570000 | AA21: DHL | AB21: =A21 -> PS260806 | AC21: =B21 -> LW260129 | AD21: =D21 -> 46056 | AE21: =G21/H21*J21 -> 0 | AF21: =(G21/H21)*K21 -> 0 | AG21: =(G21/H21)*L21 -> 0 | AH21: =(G21/H21)*M21 -> 570000 | AI21: =(G21/H21)*N21 -> 0 | AJ21: =(G21/H21)*O21 -> 0 | AK21: =(G21/H21)*P21 -> 0 | AL21: =(G21/H21)*Q21 -> 0 | AM21: =(G21/H21)*R21 -> 0 | AN21: =(G21/H21)*S21 -> 0 | AO21: =(G21/H21)*T21 -> 0 | AP21: =(G21/H21)*U21 -> 0 | AQ21: =(G21/H21)*V21 -> 0 | AR21: =SUM(AG21:AQ21)*0.08 -> 45600 | AS21: =SUM(AG21:AR21) -> 615600 | AT21: =AS21 -> 615600 | AU21: =AA21 -> DHL | AV21: EXP | AW21: ADCDNB-26.02-000449
A22: PS260812 | B22: DJL-260130-007 | C22: 5162691741 | D22: 46055 | E22: 107951879560 | F22: 1 | G22: 0.9 | H22: 0.9 | M22: 570000 | AA22: DHL | AB22: =A22 -> PS260812 | AC22: =B22 -> DJL-260130-007 | AD22: =D22 -> 46055 | AE22: =G22/H22*J22 -> 0 | AF22: =(G22/H22)*K22 -> 0 | AG22: =(G22/H22)*L22 -> 0 | AH22: =(G22/H22)*M22 -> 570000 | AI22: =(G22/H22)*N22 -> 0 | AJ22: =(G22/H22)*O22 -> 0 | AK22: =(G22/H22)*P22 -> 0 | AL22: =(G22/H22)*Q22 -> 0 | AM22: =(G22/H22)*R22 -> 0 | AN22: =(G22/H22)*S22 -> 0 | AO22: =(G22/H22)*T22 -> 0 | AP22: =(G22/H22)*U22 -> 0 | AQ22: =(G22/H22)*V22 -> 0 | AR22: =SUM(AG22:AQ22)*0.08 -> 45600 | AS22: =SUM(AG22:AR22) -> 615600 | AT22: =AS22 -> 615600 | AU22: =AA22 -> DHL | AV22: EXP | AW22: ADCDNB-26.02-000450
A23: PS260814 | B23: IV260103194 | C23: 5162712752 | D23: 46055 | E23: 107951921560 | F23: 1 | G23: 20 | H23: 20 | M23: 570000 | AA23: DHL | AB23: =A23 -> PS260814 | AC23: =B23 -> IV260103194 | AD23: =D23 -> 46055 | AE23: =G23/H23*J23 -> 0 | AF23: =(G23/H23)*K23 -> 0 | AG23: =(G23/H23)*L23 -> 0 | AH23: =(G23/H23)*M23 -> 570000 | AI23: =(G23/H23)*N23 -> 0 | AJ23: =(G23/H23)*O23 -> 0 | AK23: =(G23/H23)*P23 -> 0 | AL23: =(G23/H23)*Q23 -> 0 | AM23: =(G23/H23)*R23 -> 0 | AN23: =(G23/H23)*S23 -> 0 | AO23: =(G23/H23)*T23 -> 0 | AP23: =(G23/H23)*U23 -> 0 | AQ23: =(G23/H23)*V23 -> 0 | AR23: =SUM(AG23:AQ23)*0.08 -> 45600 | AS23: =SUM(AG23:AR23) -> 615600 | AT23: =AS23 -> 615600 | AU23: =AA23 -> DHL | AV23: EXP | AW23: ADCDNB-26.02-000451
A24: PS260805 | B24: IV260102980 | C24: 5162398905 | D24: 46055 | E24: 107951960100 | F24: 1 | G24: 1.5 | H24: 1.5 | M24: 570000 | AA24: DHL | AB24: =A24 -> PS260805 | AC24: =B24 -> IV260102980 | AD24: =D24 -> 46055 | AE24: =G24/H24*J24 -> 0 | AF24: =(G24/H24)*K24 -> 0 | AG24: =(G24/H24)*L24 -> 0 | AH24: =(G24/H24)*M24 -> 570000 | AI24: =(G24/H24)*N24 -> 0 | AJ24: =(G24/H24)*O24 -> 0 | AK24: =(G24/H24)*P24 -> 0 | AL24: =(G24/H24)*Q24 -> 0 | AM24: =(G24/H24)*R24 -> 0 | AN24: =(G24/H24)*S24 -> 0 | AO24: =(G24/H24)*T24 -> 0 | AP24: =(G24/H24)*U24 -> 0 | AQ24: =(G24/H24)*V24 -> 0 | AR24: =SUM(AG24:AQ24)*0.08 -> 45600 | AS24: =SUM(AG24:AR24) -> 615600 | AT24: =AS24 -> 615600 | AU24: =AA24 -> DHL | AV24: EXP | AW24: ADCDNB-26.02-000452
A25: PS260804 | B25: PS26-804 | C25: 5162376693 | D25: 46055 | E25: 107952014220 | F25: 1 | G25: 7.1 | H25: 7.1 | M25: 570000 | AA25: DHL | AB25: =A25 -> PS260804 | AC25: =B25 -> PS26-804 | AD25: =D25 -> 46055 | AE25: =G25/H25*J25 -> 0 | AF25: =(G25/H25)*K25 -> 0 | AG25: =(G25/H25)*L25 -> 0 | AH25: =(G25/H25)*M25 -> 570000 | AI25: =(G25/H25)*N25 -> 0 | AJ25: =(G25/H25)*O25 -> 0 | AK25: =(G25/H25)*P25 -> 0 | AL25: =(G25/H25)*Q25 -> 0 | AM25: =(G25/H25)*R25 -> 0 | AN25: =(G25/H25)*S25 -> 0 | AO25: =(G25/H25)*T25 -> 0 | AP25: =(G25/H25)*U25 -> 0 | AQ25: =(G25/H25)*V25 -> 0 | AR25: =SUM(AG25:AQ25)*0.08 -> 45600 | AS25: =SUM(AG25:AR25) -> 615600 | AT25: =AS25 -> 615600 | AU25: =AA25 -> DHL | AV25: EXP | AW25: ADCDNB-26.02-000453
A26: PS260803 | B26: 00013-00131393 | C26: 5496713843 | D26: 46056 | E26: 107953077740 | F26: 1 | G26: 2.5 | H26: 2.5 | M26: 570000 | AA26: DHL | AB26: =A26 -> PS260803 | AC26: =B26 -> 00013-00131393 | AD26: =D26 -> 46056 | AE26: =G26/H26*J26 -> 0 | AF26: =(G26/H26)*K26 -> 0 | AG26: =(G26/H26)*L26 -> 0 | AH26: =(G26/H26)*M26 -> 570000 | AI26: =(G26/H26)*N26 -> 0 | AJ26: =(G26/H26)*O26 -> 0 | AK26: =(G26/H26)*P26 -> 0 | AL26: =(G26/H26)*Q26 -> 0 | AM26: =(G26/H26)*R26 -> 0 | AN26: =(G26/H26)*S26 -> 0 | AO26: =(G26/H26)*T26 -> 0 | AP26: =(G26/H26)*U26 -> 0 | AQ26: =(G26/H26)*V26 -> 0 | AR26: =SUM(AG26:AQ26)*0.08 -> 45600 | AS26: =SUM(AG26:AR26) -> 615600 | AT26: =AS26 -> 615600 | AU26: =AA26 -> DHL | AV26: EXP | AW26: ADCDNB-26.02-000454
A27: PS260833 | B27: ZS26013001 | C27: 3405477342 | D27: 46056 | E27: 107954071410 | F27: 1 | G27: 4.5 | H27: 4.5 | M27: 570000 | AA27: DHL | AB27: =A27 -> PS260833 | AC27: =B27 -> ZS26013001 | AD27: =D27 -> 46056 | AE27: =G27/H27*J27 -> 0 | AF27: =(G27/H27)*K27 -> 0 | AG27: =(G27/H27)*L27 -> 0 | AH27: =(G27/H27)*M27 -> 570000 | AI27: =(G27/H27)*N27 -> 0 | AJ27: =(G27/H27)*O27 -> 0 | AK27: =(G27/H27)*P27 -> 0 | AL27: =(G27/H27)*Q27 -> 0 | AM27: =(G27/H27)*R27 -> 0 | AN27: =(G27/H27)*S27 -> 0 | AO27: =(G27/H27)*T27 -> 0 | AP27: =(G27/H27)*U27 -> 0 | AQ27: =(G27/H27)*V27 -> 0 | AR27: =SUM(AG27:AQ27)*0.08 -> 45600 | AS27: =SUM(AG27:AR27) -> 615600 | AT27: =AS27 -> 615600 | AU27: =AA27 -> DHL | AV27: EXP | AW27: ADCDNB-26.02-000455
A28: PS260807 | B28: 2/PQR-PS/26 | C28: 112600036867319 | D28: 46056 | E28: 107951650920 | F28: 1 | G28: 218 | H28: 218 | L28: {=IF(H28=0, _xleta.T, IF(H28<=1000, 1790000, IF(H28<=2000, 1960000, IF(H28<=3000, 2686000, IF(H28<=5000, 2796000, ff)))))} -> 1790000 | M28: 940500 | Z28: 50H69350 | AA28: HIỆP PHƯỚC | AB28: =A28 -> PS260807 | AC28: =B28 -> 2/PQR-PS/26 | AD28: =D28 -> 46056 | AE28: =G28/H28*J28 -> 0 | AF28: =(G28/H28)*K28 -> 0 | AG28: =(G28/H28)*L28 -> 1790000 | AH28: =(G28/H28)*M28 -> 940500 | AI28: =(G28/H28)*N28 -> 0 | AJ28: =(G28/H28)*O28 -> 0 | AK28: =(G28/H28)*P28 -> 0 | AL28: =(G28/H28)*Q28 -> 0 | AM28: =(G28/H28)*R28 -> 0 | AN28: =(G28/H28)*S28 -> 0 | AO28: =(G28/H28)*T28 -> 0 | AP28: =(G28/H28)*U28 -> 0 | AQ28: =(G28/H28)*V28 -> 0 | AR28: =SUM(AG28:AQ28)*0.08 -> 218440 | AS28: =SUM(AG28:AR28) -> 2948940 | AT28: =AS28 -> 2948940 | AU28: =AA28 -> HIỆP PHƯỚC | AV28: LCL | AW28: ADCDNB-26.02-000456 | AX28: , từ Cảng Hiệp Phước đến KCN Bàu Xéo, Đồng Nai | AY28: 46057 | AZ28: 50H69350 | BA28: 1 X 1MT | BB28: 1790000 | BC28: =BB28-L28 -> 0
A29: PS26834 | B29: VV07701/6538/25 | C29: 112600036938787 | D29: 46056 | E29: 107955652450 | F29: 1 | G29: 528 | H29: 528 | L29: {=IF(H29=0, _xleta.T, IF(H29<=1000, 1590000, IF(H29<=2000, 1760000, IF(H29<=3000, 2486000, IF(H29<=5000, 2596000, ff)))))} -> 1590000 | M29: 940500 | Z29: 50E52902 | AA29: TÂN TẠO | AB29: =A29 -> PS26834 | AC29: =B29 -> VV07701/6538/25 | AD29: =D29 -> 46056 | AE29: =G29/H29*J29 -> 0 | AF29: =(G29/H29)*K29 -> 0 | AG29: =(G29/H29)*L29 -> 1590000 | AH29: =(G29/H29)*M29 -> 940500 | AI29: =(G29/H29)*N29 -> 0 | AJ29: =(G29/H29)*O29 -> 0 | AK29: =(G29/H29)*P29 -> 0 | AL29: =(G29/H29)*Q29 -> 0 | AM29: =(G29/H29)*R29 -> 0 | AN29: =(G29/H29)*S29 -> 0 | AO29: =(G29/H29)*T29 -> 0 | AP29: =(G29/H29)*U29 -> 0 | AQ29: =(G29/H29)*V29 -> 0 | AR29: =SUM(AG29:AQ29)*0.08 -> 202440 | AS29: =SUM(AG29:AR29) -> 2732940 | AT29: =AS29 -> 2732940 | AU29: =AA29 -> TÂN TẠO | AV29: LCL | AW29: ADCDNB-26.02-000487 | AX29: , từ Tân Tạo đến KCN Bàu Xéo, Đồng Nai | AY29: 46057 | AZ29: 50E52902 | BA29: 1 X 1MT | BB29: 1590000 | BC29: =BB29-L29 -> 0
A30: PS260871 | B30: PC2602032VY | C30: JWE5150205 | D30: 46057 | E30: 107957066710 | F30: 1 | G30: 1 | H30: 1 | L30: =IF(H30<=50,1060000, IF(H30<=200, 1210000, IF(H30<=500, 1230000, IF(H30<=1000, 1440000, IF(H30<=2000, 1990000, IF(H30>2000, 1990000+(H30-2000)*1464)))))) -> 1060000 | M30: 940500 | Z30: 50H69559 | AA30: TCS | AB30: =A30 -> PS260871 | AC30: =B30 -> PC2602032VY | AD30: =D30 -> 46057 | AE30: =G30/H30*J30 -> 0 | AF30: =(G30/H30)*K30 -> 0 | AG30: =(G30/H30)*L30 -> 1060000 | AH30: =(G30/H30)*M30 -> 940500 | AI30: =(G30/H30)*N30 -> 0 | AJ30: =(G30/H30)*O30 -> 0 | AK30: =(G30/H30)*P30 -> 0 | AL30: =(G30/H30)*Q30 -> 0 | AM30: =(G30/H30)*R30 -> 0 | AN30: =(G30/H30)*S30 -> 0 | AO30: =(G30/H30)*T30 -> 0 | AP30: =(G30/H30)*U30 -> 0 | AQ30: =(G30/H30)*V30 -> 0 | AR30: =SUM(AG30:AQ30)*0.08 -> 160040 | AS30: =SUM(AG30:AR30) -> 2160540 | AT30: =AS30 -> 2160540 | AU30: =AA30 -> TCS | AV30: AIR | AW30: ADCDNB-26.02-000561 | AX30: , từ Kho TCS đến KCN Bàu Xéo , Đồng Nai | AY30: 46058 | AZ30: 50H69559 | BA30: 1 X 1MT | BB30: 1060000
A31: PS260870 | B31: G8-20260203 VY (B) | C31: JWE5150200 | D31: 46057 | E31: 107957082550 | F31: 1 | G31: 2 | H31: 2 | L31: =IF(H31<=50,1060000, IF(H31<=200, 1210000, IF(H31<=500, 1230000, IF(H31<=1000, 1440000, IF(H31<=2000, 1990000, IF(H31>2000, 1990000+(H31-2000)*1464)))))) -> 1060000 | M31: 940500 | Z31: 50H69559 | AA31: TCS | AB31: =A31 -> PS260870 | AC31: =B31 -> G8-20260203 VY (B) | AD31: =D31 -> 46057 | AE31: =G31/H31*J31 -> 0 | AF31: =(G31/H31)*K31 -> 0 | AG31: =(G31/H31)*L31 -> 1060000 | AH31: =(G31/H31)*M31 -> 940500 | AI31: =(G31/H31)*N31 -> 0 | AJ31: =(G31/H31)*O31 -> 0 | AK31: =(G31/H31)*P31 -> 0 | AL31: =(G31/H31)*Q31 -> 0 | AM31: =(G31/H31)*R31 -> 0 | AN31: =(G31/H31)*S31 -> 0 | AO31: =(G31/H31)*T31 -> 0 | AP31: =(G31/H31)*U31 -> 0 | AQ31: =(G31/H31)*V31 -> 0 | AR31: =SUM(AG31:AQ31)*0.08 -> 160040 | AS31: =SUM(AG31:AR31) -> 2160540 | AT31: =AS31 -> 2160540 | AU31: =AA31 -> TCS | AV31: AIR | AW31: ADCDNB-26.02-000556 | AX31: , từ Kho TCS đến KCN Bàu Xéo , Đồng Nai | AY31: 46058 | BB31: 1060000
A32: PS260869 | B32: PC260203VY | C32: JWE5150204 | D32: 46057 | E32: 107957099500 | F32: 1 | G32: 30 | H32: 30 | L32: =IF(H32<=50,1060000, IF(H32<=200, 1210000, IF(H32<=500, 1230000, IF(H32<=1000, 1440000, IF(H32<=2000, 1990000, IF(H32>2000, 1990000+(H32-2000)*1464)))))) -> 1060000 | M32: 940500 | Z32: 50H69559 | AA32: TCS | AB32: =A32 -> PS260869 | AC32: =B32 -> PC260203VY | AD32: =D32 -> 46057 | AE32: =G32/H32*J32 -> 0 | AF32: =(G32/H32)*K32 -> 0 | AG32: =(G32/H32)*L32 -> 1060000 | AH32: =(G32/H32)*M32 -> 940500 | AI32: =(G32/H32)*N32 -> 0 | AJ32: =(G32/H32)*O32 -> 0 | AK32: =(G32/H32)*P32 -> 0 | AL32: =(G32/H32)*Q32 -> 0 | AM32: =(G32/H32)*R32 -> 0 | AN32: =(G32/H32)*S32 -> 0 | AO32: =(G32/H32)*T32 -> 0 | AP32: =(G32/H32)*U32 -> 0 | AQ32: =(G32/H32)*V32 -> 0 | AR32: =SUM(AG32:AQ32)*0.08 -> 160040 | AS32: =SUM(AG32:AR32) -> 2160540 | AT32: =AS32 -> 2160540 | AU32: =AA32 -> TCS | AV32: AIR | AW32: ADCDNB-26.02-000552 | AX32: , từ Kho TCS đến KCN Bàu Xéo , Đồng Nai | AY32: 46058 | BB32: 1060000
A33: PS260842 | B33: T260130-Y2 | C33: SPX2601073 | D33: 46056 | E33: 107954923200 | F33: 1 | G33: 23 | H33: 23 | L33: =IF(H33<=50,1060000, IF(H33<=200, 1210000, IF(H33<=500, 1230000, IF(H33<=1000, 1440000, IF(H33<=2000, 1990000, IF(H33>2000, 1990000+(H33-2000)*1464)))))) -> 1060000 | M33: 940500 | Z33: 50H69559 | AA33: TCS | AB33: =A33 -> PS260842 | AC33: =B33 -> T260130-Y2 | AD33: =D33 -> 46056 | AE33: =G33/H33*J33 -> 0 | AF33: =(G33/H33)*K33 -> 0 | AG33: =(G33/H33)*L33 -> 1060000 | AH33: =(G33/H33)*M33 -> 940500 | AI33: =(G33/H33)*N33 -> 0 | AJ33: =(G33/H33)*O33 -> 0 | AK33: =(G33/H33)*P33 -> 0 | AL33: =(G33/H33)*Q33 -> 0 | AM33: =(G33/H33)*R33 -> 0 | AN33: =(G33/H33)*S33 -> 0 | AO33: =(G33/H33)*T33 -> 0 | AP33: =(G33/H33)*U33 -> 0 | AQ33: =(G33/H33)*V33 -> 0 | AR33: =SUM(AG33:AQ33)*0.08 -> 160040 | AS33: =SUM(AG33:AR33) -> 2160540 | AT33: =AS33 -> 2160540 | AU33: =AA33 -> TCS | AV33: AIR | AW33: ADCDNB-26.02-000577 | AX33: , từ Kho TCS đến KCN Bàu Xéo , Đồng Nai | AY33: 46058 | BB33: 1060000
